Workbook
Name averages: 'BPI+'!$FK$4:$GP$4
Name bchk1: 'Map of Bracket (for Pred Tools)'!$D$1:$E$16
Name bchk2: 'Map of Bracket (for Pred Tools)'!$D$19:$E$34
Name bchk3: 'Map of Bracket (for Pred Tools)'!$D$36:$E$51
Name bchk4: 'Map of Bracket (for Pred Tools)'!$D$54:$E$69
Name bpiHeaders: 'BPI+'!$1:$1
Name bpiImportCol: 'BPI Import'!$A:$A
Name bpiPlusHeader: 'BPI+'!$A$1:$GP$1
Name bpiPlusTable: 'BPI+'!$A$1:$GQ$279
Name bpiTeams: 'BPI+'!$C:$C
Name bracketLeft: Bracket!$D$2:$M$33
Name bracketRight: Bracket!$P$2:$X$33
Name calculatedResVal: 'Res Value'!$BT:$BT
Name conf1: Seeding!$C:$C
Name conf2: Seeding!$G:$G
Name espnMap: mapping!$J:$J
Name espnMap2: mapping!$K:$K
Name FGA_COEFFS: Formulas!$A$3:$H$3
Name FTA_COEFFS: Formulas!$A$31:$F$31
Name FTPCT_COEFFS: Formulas!$A$38:$D$38
Name fullSDevTable: 'BPI+'!$EC:$FF
Name importBPICol: 'BPI Import'!$B:$B
Name importBPIRkCol: 'BPI Import'!$C:$C
Name INIcol: mapping!$I:$I
Name kpDef: 'KenPom import'!$I:$I
Name kpOff: 'KenPom import'!$G:$G
Name kpTeam: 'KenPom import'!$B:$B
Name kpVal: mapping!$D:$D
Name mascotCol: 'BPI+'!$D:$D
Name perc3pt: 'BPI+'!$FH:$FH
Name qlTable: 'BPI+'!$BL:$BX
Name quad1: 'Map of Bracket (for Pred Tools)'!$C$1:$C$16
Name quadcheck: 'Map of Bracket (for Pred Tools)'!$P$1
Name quadrant1: 'Map of Bracket (for Pred Tools)'!$C$1:$E$16
Name quadrant2: 'Map of Bracket (for Pred Tools)'!$C$19:$E$34
Name quadrant3: 'Map of Bracket (for Pred Tools)'!$C$36:$E$51
Name quadrant4: 'Map of Bracket (for Pred Tools)'!$C$54:$E$69
Name qwqlINIcol: 'Res Value'!$B:$B
Name rank1: Seeding!$A:$A
Name rank2: Seeding!$E:$E
Name resValueTeamCol: 'Res Value'!$A:$A
Name RKTEAM: 'BPI+'!$A:$C
Name rlTable: 'BPI+'!$AK:$AV
Name rowOffset: mapping!$N$2
Name sdevHeader: 'BPI+'!$EC$1:$FF$1
Name sdevTable: 'BPI+'!$EC$1:$FF$53
Name sorCol: 'BPI+'!$J:$J
Name sorRkCol: 'SOR Import'!$B:$B
Name sorRowOffset: mapping!$N$5
Name sorTeamCol: 'SOR Import'!$A:$A
Name statsCategories: 'BPI+'!$CX$1:$DX$1
Name statsNames: mapping!$P:$Q
Name STATSTABLE: 'BPI+'!$CX:$EB
Name statsTable2: 'BPI+'!$CX$1:$FH$53
Name statsTable2header: 'BPI+'!$CX$1:$FH$1
Name statsTitles: '1v1 (Prediction Tool)'!$A$6
Name statTitles: 'BPI+'!$CX$1:$EB$1
Name team1: Seeding!$B:$B
Name team2: Seeding!$F:$F
Name teamA: Bracket!$AE$2

Sheet Stats import
D1: Statistic | E1: Team | F1: National | G1: Conference | H1: Value | I1: National Leader | J1: Value
A2: =IF(NOT(D2=""),INDEX(statsNames,MATCH(D2,mapping!Q:Q,0),1),A1) -> 0 | B2: =INDEX(mapping!R:R,MATCH(A2,mapping!P:P,0),1)+INDEX(mapping!H:H,MATCH(E2,mapping!F:F,0)) -> #N/A | F2: Rank | G2: Rank
A3: =IF(NOT(D3=""),INDEX(statsNames,MATCH(D3,mapping!Q:Q,0),1),A2) -> A:T | B3: =INDEX(mapping!R:R,MATCH(A3,mapping!P:P,0),1)+INDEX(mapping!H:H,MATCH(E3,mapping!F:F,0)) -> 3005 | D3: Assist/Turnover Ratio (361 ranked) | E3: Purdue | F3: 1 | G3: 1 | H3: 2.19 | I3: Purdue | J3: 2.19
A4: =IF(NOT(D4=""),INDEX(statsNames,MATCH(D4,mapping!Q:Q,0),1),A3) -> A:T | B4: =INDEX(mapping!R:R,MATCH(A4,mapping!P:P,0),1)+INDEX(mapping!H:H,MATCH(E4,mapping!F:F,0)) -> 5105 | E4: Liberty | F4: 3 | G4: 1 | H4: 1.95
A5: =IF(NOT(D5=""),INDEX(statsNames,MATCH(D5,mapping!Q:Q,0),1),A4) -> A:T | B5: =INDEX(mapping!R:R,MATCH(A5,mapping!P:P,0),1)+INDEX(mapping!H:H,MATCH(E5,mapping!F:F,0)) -> 4405 | E5: Gonzaga | F5: 4 | G5: 1 | H5: 1.9
A6: =IF(NOT(D6=""),INDEX(statsNames,MATCH(D6,mapping!Q:Q,0),1),A5) -> A:T | B6: =INDEX(mapping!R:R,MATCH(A6,mapping!P:P,0),1)+INDEX(mapping!H:H,MATCH(E6,mapping!F:F,0)) -> 8105 | E6: Arkansas | F6: 5 | G6: 1 | H6: 1.88
A7: =IF(NOT(D7=""),INDEX(statsNames,MATCH(D7,mapping!Q:Q,0),1),A6) -> A:T | B7: =INDEX(mapping!R:R,MATCH(A7,mapping!P:P,0),1)+INDEX(mapping!H:H,MATCH(E7,mapping!F:F,0)) -> 7305 | E7: Nebraska | F7: 6 | G7: 3 | H7: 1.84
A8: =IF(NOT(D8=""),INDEX(statsNames,MATCH(D8,mapping!Q:Q,0),1),A7) -> A:T | B8: =INDEX(mapping!R:R,MATCH(A8,mapping!P:P,0),1)+INDEX(mapping!H:H,MATCH(E8,mapping!F:F,0)) -> 9005 | E8: UCLA | F8: 7 | G8: 4 | H8: 1.84
A9: =IF(NOT(D9=""),INDEX(statsNames,MATCH(D9,mapping!Q:Q,0),1),A8) -> A:T | B9: =INDEX(mapping!R:R,MATCH(A9,mapping!P:P,0),1)+INDEX(mapping!H:H,MATCH(E9,mapping!F:F,0)) -> 4205 | E9: Wisconsin | F9: 10 | G9: 5 | H9: 1.79
A10: =IF(NOT(D10=""),INDEX(statsNames,MATCH(D10,mapping!Q:Q,0),1),A9) -> A:T | B10: =INDEX(mapping!R:R,MATCH(A10,mapping!P:P,0),1)+INDEX(mapping!H:H,MATCH(E10,mapping!F:F,0)) -> 10605 | E10: High Point | F10: 12 | G10: 1 | H10: 1.74
A11: =IF(NOT(D11=""),INDEX(statsNames,MATCH(D11,mapping!Q:Q,0),1),A10) -> A:T | B11: =INDEX(mapping!R:R,MATCH(A11,mapping!P:P,0),1)+INDEX(mapping!H:H,MATCH(E11,mapping!F:F,0)) -> 12505 | E11: Yale | F11: 13 | G11: 2 | H11: 1.73
A12: =IF(NOT(D12=""),INDEX(statsNames,MATCH(D12,mapping!Q:Q,0),1),A11) -> A:T | B12: =INDEX(mapping!R:R,MATCH(A12,mapping!P:P,0),1)+INDEX(mapping!H:H,MATCH(E12,mapping!F:F,0)) -> 2805 | E12: Houston | F12: 14 | G12: 1 | H12: 1.73
A13: =IF(NOT(D13=""),INDEX(statsNames,MATCH(D13,mapping!Q:Q,0),1),A12) -> A:T | B13: =INDEX(mapping!R:R,MATCH(A13,mapping!P:P,0),1)+INDEX(mapping!H:H,MATCH(E13,mapping!F:F,0)) -> 14405 | E13: Vanderbilt | F13: 15 | G13: 2 | H13: 1.72
A14: =IF(NOT(D14=""),INDEX(statsNames,MATCH(D14,mapping!Q:Q,0),1),A13) -> A:T | B14: =INDEX(mapping!R:R,MATCH(A14,mapping!P:P,0),1)+INDEX(mapping!H:H,MATCH(E14,mapping!F:F,0)) -> 1905 | E14: NC State | F14: 16 | G14: 1 | H14: 1.69
A15: =IF(NOT(D15=""),INDEX(statsNames,MATCH(D15,mapping!Q:Q,0),1),A14) -> A:T | B15: =INDEX(mapping!R:R,MATCH(A15,mapping!P:P,0),1)+INDEX(mapping!H:H,MATCH(E15,mapping!F:F,0)) -> 8205 | E15: Akron | F15: 18 | G15: 1 | H15: 1.69
... A89: =IF(NOT(D89=""),INDEX(statsNames,MATCH(D89,mapping!Q:Q,0),1),A88) -> A:T | B89: =INDEX(mapping!R:R,MATCH(A89,mapping!P:P,0),1)+INDEX(mapping!H:H,MATCH(E89,mapping!F:F,0)) -> 18205 | E89: Bethune-Cookman | F89: 309 | G89: 5 | H89: 0.99
A90: =IF(NOT(D90=""),INDEX(statsNames,MATCH(D90,mapping!Q:Q,0),1),A89) -> APG | B90: =INDEX(mapping!R:R,MATCH(A90,mapping!P:P,0),1)+INDEX(mapping!H:H,MATCH(E90,mapping!F:F,0)) -> 3006 | D90: Assists Per Game (361 ranked) | E90: Purdue | F90: 3 | G90: 1 | H90: 19.9 | I90: Cornell | J90: 21.3
A91: =IF(NOT(D91=""),INDEX(statsNames,MATCH(D91,mapping!Q:Q,0),1),A90) -> APG | B91: =INDEX(mapping!R:R,MATCH(A91,mapping!P:P,0),1)+INDEX(mapping!H:H,MATCH(E91,mapping!F:F,0)) -> 7606 | E91: Michigan | F91: 5 | G91: 2 | H91: 18.6
A92: =IF(NOT(D92=""),INDEX(statsNames,MATCH(D92,mapping!Q:Q,0),1),A91) -> APG | B92: =INDEX(mapping!R:R,MATCH(A92,mapping!P:P,0),1)+INDEX(mapping!H:H,MATCH(E92,mapping!F:F,0)) -> 906 | E92: Michigan St. | F92: 6 | G92: 3 | H92: 18.5
A93: =IF(NOT(D93=""),INDEX(statsNames,MATCH(D93,mapping!Q:Q,0),1),A92) -> APG | B93: =INDEX(mapping!R:R,MATCH(A93,mapping!P:P,0),1)+INDEX(mapping!H:H,MATCH(E93,mapping!F:F,0)) -> 8206 | E93: Akron | F93: 7 | G93: 1 | H93: 18.4
A94: =IF(NOT(D94=""),INDEX(statsNames,MATCH(D94,mapping!Q:Q,0),1),A93) -> APG | B94: =INDEX(mapping!R:R,MATCH(A94,mapping!P:P,0),1)+INDEX(mapping!H:H,MATCH(E94,mapping!F:F,0)) -> 17006 | E94: Utah Valley | F94: 8 | G94: 1 | H94: 18.4
A95: =IF(NOT(D95=""),INDEX(statsNames,MATCH(D95,mapping!Q:Q,0),1),A94) -> APG | B95: =INDEX(mapping!R:R,MATCH(A95,mapping!P:P,0),1)+INDEX(mapping!H:H,MATCH(E95,mapping!F:F,0)) -> 2306 | E95: UConn | F95: 9 | G95: 1 | H95: 18.4
A96: =IF(NOT(D96=""),INDEX(statsNames,MATCH(D96,mapping!Q:Q,0),1),A95) -> APG | B96: =INDEX(mapping!R:R,MATCH(A96,mapping!P:P,0),1)+INDEX(mapping!H:H,MATCH(E96,mapping!F:F,0)) -> 4406 | E96: Gonzaga | F96: 10 | G96: 1 | H96: 18.3
A97: =IF(NOT(D97=""),INDEX(statsNames,MATCH(D97,mapping!Q:Q,0),1),A96) -> APG | B97: =INDEX(mapping!R:R,MATCH(A97,mapping!P:P,0),1)+INDEX(mapping!H:H,MATCH(E97,mapping!F:F,0)) -> 16306 | E97: Saint Louis | F97: 10 | G97: 1 | H97: 18.3
A98: =IF(NOT(D98=""),INDEX(statsNames,MATCH(D98,mapping!Q:Q,0),1),A97) -> APG | B98: =INDEX(mapping!R:R,MATCH(A98,mapping!P:P,0),1)+INDEX(mapping!H:H,MATCH(E98,mapping!F:F,0)) -> 3606 | E98: Texas A&M | F98: 12 | G98: 1 | H98: 18.1
A99: =IF(NOT(D99=""),INDEX(statsNames,MATCH(D99,mapping!Q:Q,0),1),A98) -> APG | B99: =INDEX(mapping!R:R,MATCH(A99,mapping!P:P,0),1)+INDEX(mapping!H:H,MATCH(E99,mapping!F:F,0)) -> 7306 | E99: Nebraska | F99: 14 | G99: 4 | H99: 18
A100: =IF(NOT(D100=""),INDEX(statsNames,MATCH(D100,mapping!Q:Q,0),1),A99) -> APG | B100: =INDEX(mapping!R:R,MATCH(A100,mapping!P:P,0),1)+INDEX(mapping!H:H,MATCH(E100,mapping!F:F,0)) -> 15106 | E100: Robert Morris | F100: 16 | G100: 2 | H100: 17.7
A101: =IF(NOT(D101=""),INDEX(statsNames,MATCH(D101,mapping!Q:Q,0),1),A100) -> APG | B101: =INDEX(mapping!R:R,MATCH(A101,mapping!P:P,0),1)+INDEX(mapping!H:H,MATCH(E101,mapping!F:F,0)) -> 1406 | E101: Utah St. | F101: 17 | G101: 1 | H101: 17.6
A102: =IF(NOT(D102=""),INDEX(statsNames,MATCH(D102,mapping!Q:Q,0),1),A101) -> APG | B102: =INDEX(mapping!R:R,MATCH(A102,mapping!P:P,0),1)+INDEX(mapping!H:H,MATCH(E102,mapping!F:F,0)) -> 11206 | E102: South Fla. | F102: 21 | G102: 1 | H102: 17.3
... A176: =IF(NOT(D176=""),INDEX(statsNames,MATCH(D176,mapping!Q:Q,0),1),A175) -> APG | B176: =INDEX(mapping!R:R,MATCH(A176,mapping!P:P,0),1)+INDEX(mapping!H:H,MATCH(E176,mapping!F:F,0)) -> 8706 | E176: Stanford | F176: 318 | G176: 17 | H176: 11.9
A177: =IF(NOT(D177=""),INDEX(statsNames,MATCH(D177,mapping!Q:Q,0),1),A176) -> Bench | B177: =INDEX(mapping!R:R,MATCH(A177,mapping!P:P,0),1)+INDEX(mapping!H:H,MATCH(E177,mapping!F:F,0)) -> 3607 | D177: Bench Points per game (361 ranked) | E177: Texas A&M | F177: 2 | G177: 1 | H177: 35.56 | I177: Tarleton St. | J177: 37.31
A178: =IF(NOT(D178=""),INDEX(statsNames,MATCH(D178,mapping!Q:Q,0),1),A177) -> Bench | B178: =INDEX(mapping!R:R,MATCH(A178,mapping!P:P,0),1)+INDEX(mapping!H:H,MATCH(E178,mapping!F:F,0)) -> 1207 | E178: San Diego St. | F178: 3 | G178: 1 | H178: 35.39
A179: =IF(NOT(D179=""),INDEX(statsNames,MATCH(D179,mapping!Q:Q,0),1),A178) -> Bench | B179: =INDEX(mapping!R:R,MATCH(A179,mapping!P:P,0),1)+INDEX(mapping!H:H,MATCH(E179,mapping!F:F,0)) -> 4407 | E179: Gonzaga | F179: 5 | G179: 1 | H179: 34.73
A180: =IF(NOT(D180=""),INDEX(statsNames,MATCH(D180,mapping!Q:Q,0),1),A179) -> Bench | B180: =INDEX(mapping!R:R,MATCH(A180,mapping!P:P,0),1)+INDEX(mapping!H:H,MATCH(E180,mapping!F:F,0)) -> 13907 | E180: Georgia | F180: 6 | G180: 2 | H180: 34.13
A181: =IF(NOT(D181=""),INDEX(statsNames,MATCH(D181,mapping!Q:Q,0),1),A180) -> Bench | B181: =INDEX(mapping!R:R,MATCH(A181,mapping!P:P,0),1)+INDEX(mapping!H:H,MATCH(E181,mapping!F:F,0)) -> 12207 | E181: VCU | F181: 7 | G181: 1 | H181: 34
A182: =IF(NOT(D182=""),INDEX(statsNames,MATCH(D182,mapping!Q:Q,0),1),A181) -> Bench | B182: =INDEX(mapping!R:R,MATCH(A182,mapping!P:P,0),1)+INDEX(mapping!H:H,MATCH(E182,mapping!F:F,0)) -> 16307 | E182: Saint Louis | F182: 11 | G182: 2 | H182: 33.39
A183: =IF(NOT(D183=""),INDEX(statsNames,MATCH(D183,mapping!Q:Q,0),1),A182) -> Bench | B183: =INDEX(mapping!R:R,MATCH(A183,mapping!P:P,0),1)+INDEX(mapping!H:H,MATCH(E183,mapping!F:F,0)) -> 207 | E183: McNeese | F183: 19 | G183: 1 | H183: 30.76
A184: =IF(NOT(D184=""),INDEX(statsNames,MATCH(D184,mapping!Q:Q,0),1),A183) -> Bench | B184: =INDEX(mapping!R:R,MATCH(A184,mapping!P:P,0),1)+INDEX(mapping!H:H,MATCH(E184,mapping!F:F,0)) -> 10607 | E184: High Point | F184: 22 | G184: 2 | H184: 30.41
A185: =IF(NOT(D185=""),INDEX(statsNames,MATCH(D185,mapping!Q:Q,0),1),A184) -> Bench | B185: =INDEX(mapping!R:R,MATCH(A185,mapping!P:P,0),1)+INDEX(mapping!H:H,MATCH(E185,mapping!F:F,0)) -> 17807 | E185: Santa Clara | F185: 23 | G185: 2 | H185: 30.21
A186: =IF(NOT(D186=""),INDEX(statsNames,MATCH(D186,mapping!Q:Q,0),1),A185) -> Bench | B186: =INDEX(mapping!R:R,MATCH(A186,mapping!P:P,0),1)+INDEX(mapping!H:H,MATCH(E186,mapping!F:F,0)) -> 7607 | E186: Michigan | F186: 25 | G186: 1 | H186: 29.85
A187: =IF(NOT(D187=""),INDEX(statsNames,MATCH(D187,mapping!Q:Q,0),1),A186) -> Bench | B187: =INDEX(mapping!R:R,MATCH(A187,mapping!P:P,0),1)+INDEX(mapping!H:H,MATCH(E187,mapping!F:F,0)) -> 4007 | E187: Clemson | F187: 28 | G187: 1 | H187: 29.65
A188: =IF(NOT(D188=""),INDEX(statsNames,MATCH(D188,mapping!Q:Q,0),1),A187) -> Bench | B188: =INDEX(mapping!R:R,MATCH(A188,mapping!P:P,0),1)+INDEX(mapping!H:H,MATCH(E188,mapping!F:F,0)) -> 8207 | E188: Akron | F188: 33 | G188: 1 | H188: 29.21
A189: =IF(NOT(D189=""),INDEX(statsNames,MATCH(D189,mapping!Q:Q,0),1),A188) -> Bench | B189: =INDEX(mapping!R:R,MATCH(A189,mapping!P:P,0),1)+INDEX(mapping!H:H,MATCH(E189,mapping!F:F,0)) -> 1407 | E189: Utah St. | F189: 35 | G189: 3 | H189: 29.12
... A263: =IF(NOT(D263=""),INDEX(statsNames,MATCH(D263,mapping!Q:Q,0),1),A262) -> Bench | B263: =INDEX(mapping!R:R,MATCH(A263,mapping!P:P,0),1)+INDEX(mapping!H:H,MATCH(E263,mapping!F:F,0)) -> 8507 | E263: Merrimack | F263: 359 | G263: 13 | H263: 8.41
A264: =IF(NOT(D264=""),INDEX(statsNames,MATCH(D264,mapping!Q:Q,0),1),A263) -> BPG | B264: =INDEX(mapping!R:R,MATCH(A264,mapping!P:P,0),1)+INDEX(mapping!H:H,MATCH(E264,mapping!F:F,0)) -> 2608 | D264: Blocks Per Game (361 ranked) | E264: Virginia | F264: 1 | G264: 1 | H264: 6.5 | I264: Virginia | J264: 6.5
A265: =IF(NOT(D265=""),INDEX(statsNames,MATCH(D265,mapping!Q:Q,0),1),A264) -> BPG | B265: =INDEX(mapping!R:R,MATCH(A265,mapping!P:P,0),1)+INDEX(mapping!H:H,MATCH(E265,mapping!F:F,0)) -> 13908 | E265: Georgia | F265: 2 | G265: 1 | H265: 6.1
A266: =IF(NOT(D266=""),INDEX(statsNames,MATCH(D266,mapping!Q:Q,0),1),A265) -> BPG | B266: =INDEX(mapping!R:R,MATCH(A266,mapping!P:P,0),1)+INDEX(mapping!H:H,MATCH(E266,mapping!F:F,0)) -> 7608 | E266: Michigan | F266: 3 | G266: 1 | H266: 6
A267: =IF(NOT(D267=""),INDEX(statsNames,MATCH(D267,mapping!Q:Q,0),1),A266) -> BPG | B267: =INDEX(mapping!R:R,MATCH(A267,mapping!P:P,0),1)+INDEX(mapping!H:H,MATCH(E267,mapping!F:F,0)) -> 7008 | E267: UC Irvine | F267: 4 | G267: 1 | H267: 5.9
A268: =IF(NOT(D268=""),INDEX(statsNames,MATCH(D268,mapping!Q:Q,0),1),A267) -> BPG | B268: =INDEX(mapping!R:R,MATCH(A268,mapping!P:P,0),1)+INDEX(mapping!H:H,MATCH(E268,mapping!F:F,0)) -> 3908 | E268: Kansas | F268: 6 | G268: 1 | H268: 5.7
A269: =IF(NOT(D269=""),INDEX(statsNames,MATCH(D269,mapping!Q:Q,0),1),A268) -> BPG | B269: =INDEX(mapping!R:R,MATCH(A269,mapping!P:P,0),1)+INDEX(mapping!H:H,MATCH(E269,mapping!F:F,0)) -> 10108 | E269: Seton Hall | F269: 7 | G269: 1 | H269: 5.7
A270: =IF(NOT(D270=""),INDEX(statsNames,MATCH(D270,mapping!Q:Q,0),1),A269) -> BPG | B270: =INDEX(mapping!R:R,MATCH(A270,mapping!P:P,0),1)+INDEX(mapping!H:H,MATCH(E270,mapping!F:F,0)) -> 2408 | E270: Southern California | F270: 8 | G270: 2 | H270: 5.7
A271: =IF(NOT(D271=""),INDEX(statsNames,MATCH(D271,mapping!Q:Q,0),1),A270) -> BPG | B271: =INDEX(mapping!R:R,MATCH(A271,mapping!P:P,0),1)+INDEX(mapping!H:H,MATCH(E271,mapping!F:F,0)) -> 17008 | E271: Utah Valley | F271: 9 | G271: 1 | H271: 5.5
A272: =IF(NOT(D272=""),INDEX(statsNames,MATCH(D272,mapping!Q:Q,0),1),A271) -> BPG | B272: =INDEX(mapping!R:R,MATCH(A272,mapping!P:P,0),1)+INDEX(mapping!H:H,MATCH(E272,mapping!F:F,0)) -> 17508 | E272: LIU | F272: 10 | G272: 1 | H272: 5.4
A273: =IF(NOT(D273=""),INDEX(statsNames,MATCH(D273,mapping!Q:Q,0),1),A272) -> BPG | B273: =INDEX(mapping!R:R,MATCH(A273,mapping!P:P,0),1)+INDEX(mapping!H:H,MATCH(E273,mapping!F:F,0)) -> 2308 | E273: UConn | F273: 13 | G273: 2 | H273: 5.3
A274: =IF(NOT(D274=""),INDEX(statsNames,MATCH(D274,mapping!Q:Q,0),1),A273) -> BPG | B274: =INDEX(mapping!R:R,MATCH(A274,mapping!P:P,0),1)+INDEX(mapping!H:H,MATCH(E274,mapping!F:F,0)) -> 8508 | E274: Merrimack | F274: 14 | G274: 1 | H274: 5.1
A275: =IF(NOT(D275=""),INDEX(statsNames,MATCH(D275,mapping!Q:Q,0),1),A274) -> BPG | B275: =INDEX(mapping!R:R,MATCH(A275,mapping!P:P,0),1)+INDEX(mapping!H:H,MATCH(E275,mapping!F:F,0)) -> 8108 | E275: Arkansas | F275: 15 | G275: 2 | H275: 5.1
A276: =IF(NOT(D276=""),INDEX(statsNames,MATCH(D276,mapping!Q:Q,0),1),A275) -> BPG | B276: =INDEX(mapping!R:R,MATCH(A276,mapping!P:P,0),1)+INDEX(mapping!H:H,MATCH(E276,mapping!F:F,0)) -> 3708 | E276: Alabama | F276: 16 | G276: 3 | H276: 5.1
... A350: =IF(NOT(D350=""),INDEX(statsNames,MATCH(D350,mapping!Q:Q,0),1),A349) -> BPG | B350: =INDEX(mapping!R:R,MATCH(A350,mapping!P:P,0),1)+INDEX(mapping!H:H,MATCH(E350,mapping!F:F,0)) -> 5208 | E350: Iowa | F350: 344 | G350: 17 | H350: 2
A351: =IF(NOT(D351=""),INDEX(statsNames,MATCH(D351,mapping!Q:Q,0),1),A350) -> EFG% | B351: =INDEX(mapping!R:R,MATCH(A351,mapping!P:P,0),1)+INDEX(mapping!H:H,MATCH(E351,mapping!F:F,0)) -> 17411 | D351: Effective FG pct (361 ranked) | E351: Miami (OH) | F351: 1 | G351: 1 | H351: 0.612 | I351: Miami (OH) | J351: 0.612
A352: =IF(NOT(D352=""),INDEX(statsNames,MATCH(D352,mapping!Q:Q,0),1),A351) -> EFG% | B352: =INDEX(mapping!R:R,MATCH(A352,mapping!P:P,0),1)+INDEX(mapping!H:H,MATCH(E352,mapping!F:F,0)) -> 5111 | E352: Liberty | F352: 2 | G352: 1 | H352: 0.612
A353: =IF(NOT(D353=""),INDEX(statsNames,MATCH(D353,mapping!Q:Q,0),1),A352) -> EFG% | B353: =INDEX(mapping!R:R,MATCH(A353,mapping!P:P,0),1)+INDEX(mapping!H:H,MATCH(E353,mapping!F:F,0)) -> 16311 | E353: Saint Louis | F353: 4 | G353: 1 | H353: 0.6
A354: =IF(NOT(D354=""),INDEX(statsNames,MATCH(D354,mapping!Q:Q,0),1),A353) -> EFG% | B354: =INDEX(mapping!R:R,MATCH(A354,mapping!P:P,0),1)+INDEX(mapping!H:H,MATCH(E354,mapping!F:F,0)) -> 8211 | E354: Akron | F354: 8 | G354: 2 | H354: 0.588
A355: =IF(NOT(D355=""),INDEX(statsNames,MATCH(D355,mapping!Q:Q,0),1),A354) -> EFG% | B355: =INDEX(mapping!R:R,MATCH(A355,mapping!P:P,0),1)+INDEX(mapping!H:H,MATCH(E355,mapping!F:F,0)) -> 7611 | E355: Michigan | F355: 10 | G355: 1 | H355: 0.582
A356: =IF(NOT(D356=""),INDEX(statsNames,MATCH(D356,mapping!Q:Q,0),1),A355) -> EFG% | B356: =INDEX(mapping!R:R,MATCH(A356,mapping!P:P,0),1)+INDEX(mapping!H:H,MATCH(E356,mapping!F:F,0)) -> 19411 | E356: Boston U. | F356: 11 | G356: 1 | H356: 0.581
A357: =IF(NOT(D357=""),INDEX(statsNames,MATCH(D357,mapping!Q:Q,0),1),A356) -> EFG% | B357: =INDEX(mapping!R:R,MATCH(A357,mapping!P:P,0),1)+INDEX(mapping!H:H,MATCH(E357,mapping!F:F,0)) -> 3011 | E357: Purdue | F357: 12 | G357: 2 | H357: 0.577
A358: =IF(NOT(D358=""),INDEX(statsNames,MATCH(D358,mapping!Q:Q,0),1),A357) -> EFG% | B358: =INDEX(mapping!R:R,MATCH(A358,mapping!P:P,0),1)+INDEX(mapping!H:H,MATCH(E358,mapping!F:F,0)) -> 1411 | E358: Utah St. | F358: 13 | G358: 2 | H358: 0.572
A359: =IF(NOT(D359=""),INDEX(statsNames,MATCH(D359,mapping!Q:Q,0),1),A358) -> EFG% | B359: =INDEX(mapping!R:R,MATCH(A359,mapping!P:P,0),1)+INDEX(mapping!H:H,MATCH(E359,mapping!F:F,0)) -> 12511 | E359: Yale | F359: 14 | G359: 2 | H359: 0.572
A360: =IF(NOT(D360=""),INDEX(statsNames,MATCH(D360,mapping!Q:Q,0),1),A359) -> EFG% | B360: =INDEX(mapping!R:R,MATCH(A360,mapping!P:P,0),1)+INDEX(mapping!H:H,MATCH(E360,mapping!F:F,0)) -> 5411 | E360: Duke | F360: 16 | G360: 1 | H360: 0.568
A361: =IF(NOT(D361=""),INDEX(statsNames,MATCH(D361,mapping!Q:Q,0),1),A360) -> EFG% | B361: =INDEX(mapping!R:R,MATCH(A361,mapping!P:P,0),1)+INDEX(mapping!H:H,MATCH(E361,mapping!F:F,0)) -> 19311 | E361: Queens (NC) | F361: 17 | G361: 2 | H361: 0.567
A362: =IF(NOT(D362=""),INDEX(statsNames,MATCH(D362,mapping!Q:Q,0),1),A361) -> EFG% | B362: =INDEX(mapping!R:R,MATCH(A362,mapping!P:P,0),1)+INDEX(mapping!H:H,MATCH(E362,mapping!F:F,0)) -> 18011 | E362: Tulsa | F362: 18 | G362: 1 | H362: 0.566
A363: =IF(NOT(D363=""),INDEX(statsNames,MATCH(D363,mapping!Q:Q,0),1),A362) -> EFG% | B363: =INDEX(mapping!R:R,MATCH(A363,mapping!P:P,0),1)+INDEX(mapping!H:H,MATCH(E363,mapping!F:F,0)) -> 10611 | E363: High Point | F363: 19 | G363: 1 | H363: 0.566
... A437: =IF(NOT(D437=""),INDEX(statsNames,MATCH(D437,mapping!Q:Q,0),1),A436) -> EFG% | B437: =INDEX(mapping!R:R,MATCH(A437,mapping!P:P,0),1)+INDEX(mapping!H:H,MATCH(E437,mapping!F:F,0)) -> 10111 | E437: Seton Hall | F437: 335 | G437: 11 | H437: 0.476
A438: =IF(NOT(D438=""),INDEX(statsNames,MATCH(D438,mapping!Q:Q,0),1),A437) -> FB | B438: =INDEX(mapping!R:R,MATCH(A438,mapping!P:P,0),1)+INDEX(mapping!H:H,MATCH(E438,mapping!F:F,0)) -> 13912 | D438: Fastbreak Points (361 ranked) | E438: Georgia | F438: 1 | G438: 1 | H438: 19.91 | I438: Georgia | J438: 19.91
A439: =IF(NOT(D439=""),INDEX(statsNames,MATCH(D439,mapping!Q:Q,0),1),A438) -> FB | B439: =INDEX(mapping!R:R,MATCH(A439,mapping!P:P,0),1)+INDEX(mapping!H:H,MATCH(E439,mapping!F:F,0)) -> 8112 | E439: Arkansas | F439: 2 | G439: 2 | H439: 19.39
A440: =IF(NOT(D440=""),INDEX(statsNames,MATCH(D440,mapping!Q:Q,0),1),A439) -> FB | B440: =INDEX(mapping!R:R,MATCH(A440,mapping!P:P,0),1)+INDEX(mapping!H:H,MATCH(E440,mapping!F:F,0)) -> 10612 | E440: High Point | F440: 3 | G440: 1 | H440: 18.88
A441: =IF(NOT(D441=""),INDEX(statsNames,MATCH(D441,mapping!Q:Q,0),1),A440) -> FB | B441: =INDEX(mapping!R:R,MATCH(A441,mapping!P:P,0),1)+INDEX(mapping!H:H,MATCH(E441,mapping!F:F,0)) -> 16312 | E441: Saint Louis | F441: 6 | G441: 1 | H441: 17.03
A442: =IF(NOT(D442=""),INDEX(statsNames,MATCH(D442,mapping!Q:Q,0),1),A441) -> FB | B442: =INDEX(mapping!R:R,MATCH(A442,mapping!P:P,0),1)+INDEX(mapping!H:H,MATCH(E442,mapping!F:F,0)) -> 5712 | E442: Florida | F442: 10 | G442: 3 | H442: 16.09
A443: =IF(NOT(D443=""),INDEX(statsNames,MATCH(D443,mapping!Q:Q,0),1),A442) -> FB | B443: =INDEX(mapping!R:R,MATCH(A443,mapping!P:P,0),1)+INDEX(mapping!H:H,MATCH(E443,mapping!F:F,0)) -> 912 | E443: Michigan St. | F443: 11 | G443: 1 | H443: 16.06
A444: =IF(NOT(D444=""),INDEX(statsNames,MATCH(D444,mapping!Q:Q,0),1),A443) -> FB | B444: =INDEX(mapping!R:R,MATCH(A444,mapping!P:P,0),1)+INDEX(mapping!H:H,MATCH(E444,mapping!F:F,0)) -> 212 | E444: McNeese | F444: 13 | G444: 1 | H444: 15.97
A445: =IF(NOT(D445=""),INDEX(statsNames,MATCH(D445,mapping!Q:Q,0),1),A444) -> FB | B445: =INDEX(mapping!R:R,MATCH(A445,mapping!P:P,0),1)+INDEX(mapping!H:H,MATCH(E445,mapping!F:F,0)) -> 18812 | E445: Tennessee St. | F445: 14 | G445: 2 | H445: 15.91
A446: =IF(NOT(D446=""),INDEX(statsNames,MATCH(D446,mapping!Q:Q,0),1),A445) -> FB | B446: =INDEX(mapping!R:R,MATCH(A446,mapping!P:P,0),1)+INDEX(mapping!H:H,MATCH(E446,mapping!F:F,0)) -> 5512 | E446: Kentucky | F446: 16 | G446: 4 | H446: 15.65
A447: =IF(NOT(D447=""),INDEX(statsNames,MATCH(D447,mapping!Q:Q,0),1),A446) -> FB | B447: =INDEX(mapping!R:R,MATCH(A447,mapping!P:P,0),1)+INDEX(mapping!H:H,MATCH(E447,mapping!F:F,0)) -> 2912 | E447: Arizona | F447: 18 | G447: 1 | H447: 15.53
A448: =IF(NOT(D448=""),INDEX(statsNames,MATCH(D448,mapping!Q:Q,0),1),A447) -> FB | B448: =INDEX(mapping!R:R,MATCH(A448,mapping!P:P,0),1)+INDEX(mapping!H:H,MATCH(E448,mapping!F:F,0)) -> 4412 | E448: Gonzaga | F448: 20 | G448: 1 | H448: 15.24
A449: =IF(NOT(D449=""),INDEX(statsNames,MATCH(D449,mapping!Q:Q,0),1),A448) -> FB | B449: =INDEX(mapping!R:R,MATCH(A449,mapping!P:P,0),1)+INDEX(mapping!H:H,MATCH(E449,mapping!F:F,0)) -> 18212 | E449: Bethune-Cookman | F449: 21 | G449: 2 | H449: 15.22
A450: =IF(NOT(D450=""),INDEX(statsNames,MATCH(D450,mapping!Q:Q,0),1),A449) -> FB | B450: =INDEX(mapping!R:R,MATCH(A450,mapping!P:P,0),1)+INDEX(mapping!H:H,MATCH(E450,mapping!F:F,0)) -> 11212 | E450: South Fla. | F450: 27 | G450: 2 | H450: 14.56
... A524: =IF(NOT(D524=""),INDEX(statsNames,MATCH(D524,mapping!Q:Q,0),1),A523) -> FB | B524: =INDEX(mapping!R:R,MATCH(A524,mapping!P:P,0),1)+INDEX(mapping!H:H,MATCH(E524,mapping!F:F,0)) -> 7912 | E524: Vermont | F524: 359 | G524: 9 | H524: 4.26
A525: =IF(NOT(D525=""),INDEX(statsNames,MATCH(D525,mapping!Q:Q,0),1),A524) -> FG% | B525: =INDEX(mapping!R:R,MATCH(A525,mapping!P:P,0),1)+INDEX(mapping!H:H,MATCH(E525,mapping!F:F,0)) -> 17413 | D525: Field Goal Percentage (361 ranked) | E525: Miami (OH) | F525: 1 | G525: 1 | H525: 52.4 | I525: Miami (OH) | J525: 52.4
A526: =IF(NOT(D526=""),INDEX(statsNames,MATCH(D526,mapping!Q:Q,0),1),A525) -> FG% | B526: =INDEX(mapping!R:R,MATCH(A526,mapping!P:P,0),1)+INDEX(mapping!H:H,MATCH(E526,mapping!F:F,0)) -> 5113 | E526: Liberty | F526: 4 | G526: 1 | H526: 51.4
A527: =IF(NOT(D527=""),INDEX(statsNames,MATCH(D527,mapping!Q:Q,0),1),A526) -> FG% | B527: =INDEX(mapping!R:R,MATCH(A527,mapping!P:P,0),1)+INDEX(mapping!H:H,MATCH(E527,mapping!F:F,0)) -> 4413 | E527: Gonzaga | F527: 5 | G527: 1 | H527: 51
A528: =IF(NOT(D528=""),INDEX(statsNames,MATCH(D528,mapping!Q:Q,0),1),A527) -> FG% | B528: =INDEX(mapping!R:R,MATCH(A528,mapping!P:P,0),1)+INDEX(mapping!H:H,MATCH(E528,mapping!F:F,0)) -> 16313 | E528: Saint Louis | F528: 7 | G528: 1 | H528: 50.9
A529: =IF(NOT(D529=""),INDEX(statsNames,MATCH(D529,mapping!Q:Q,0),1),A528) -> FG% | B529: =INDEX(mapping!R:R,MATCH(A529,mapping!P:P,0),1)+INDEX(mapping!H:H,MATCH(E529,mapping!F:F,0)) -> 7613 | E529: Michigan | F529: 8 | G529: 1 | H529: 50.7
A530: =IF(NOT(D530=""),INDEX(statsNames,MATCH(D530,mapping!Q:Q,0),1),A529) -> FG% | B530: =INDEX(mapping!R:R,MATCH(A530,mapping!P:P,0),1)+INDEX(mapping!H:H,MATCH(E530,mapping!F:F,0)) -> 17013 | E530: Utah Valley | F530: 9 | G530: 1 | H530: 50.3
A531: =IF(NOT(D531=""),INDEX(statsNames,MATCH(D531,mapping!Q:Q,0),1),A530) -> FG% | B531: =INDEX(mapping!R:R,MATCH(A531,mapping!P:P,0),1)+INDEX(mapping!H:H,MATCH(E531,mapping!F:F,0)) -> 8213 | E531: Akron | F531: 10 | G531: 2 | H531: 50.3
A532: =IF(NOT(D532=""),INDEX(statsNames,MATCH(D532,mapping!Q:Q,0),1),A531) -> FG% | B532: =INDEX(mapping!R:R,MATCH(A532,mapping!P:P,0),1)+INDEX(mapping!H:H,MATCH(E532,mapping!F:F,0)) -> 2913 | E532: Arizona | F532: 11 | G532: 1 | H532: 50.2
A533: =IF(NOT(D533=""),INDEX(statsNames,MATCH(D533,mapping!Q:Q,0),1),A532) -> FG% | B533: =INDEX(mapping!R:R,MATCH(A533,mapping!P:P,0),1)+INDEX(mapping!H:H,MATCH(E533,mapping!F:F,0)) -> 113 | E533: Miami (FL) | F533: 12 | G533: 1 | H533: 50.1
A534: =IF(NOT(D534=""),INDEX(statsNames,MATCH(D534,mapping!Q:Q,0),1),A533) -> FG% | B534: =INDEX(mapping!R:R,MATCH(A534,mapping!P:P,0),1)+INDEX(mapping!H:H,MATCH(E534,mapping!F:F,0)) -> 8113 | E534: Arkansas | F534: 13 | G534: 1 | H534: 50
A535: =IF(NOT(D535=""),INDEX(statsNames,MATCH(D535,mapping!Q:Q,0),1),A534) -> FG% | B535: =INDEX(mapping!R:R,MATCH(A535,mapping!P:P,0),1)+INDEX(mapping!H:H,MATCH(E535,mapping!F:F,0)) -> 12513 | E535: Yale | F535: 14 | G535: 1 | H535: 49.9
A536: =IF(NOT(D536=""),INDEX(statsNames,MATCH(D536,mapping!Q:Q,0),1),A535) -> FG% | B536: =INDEX(mapping!R:R,MATCH(A536,mapping!P:P,0),1)+INDEX(mapping!H:H,MATCH(E536,mapping!F:F,0)) -> 1413 | E536: Utah St. | F536: 15 | G536: 1 | H536: 49.8
A537: =IF(NOT(D537=""),INDEX(statsNames,MATCH(D537,mapping!Q:Q,0),1),A536) -> FG% | B537: =INDEX(mapping!R:R,MATCH(A537,mapping!P:P,0),1)+INDEX(mapping!H:H,MATCH(E537,mapping!F:F,0)) -> 3013 | E537: Purdue | F537: 16 | G537: 2 | H537: 49.8
... A611: =IF(NOT(D611=""),INDEX(statsNames,MATCH(D611,mapping!Q:Q,0),1),A610) -> FG% | B611: =INDEX(mapping!R:R,MATCH(A611,mapping!P:P,0),1)+INDEX(mapping!H:H,MATCH(E611,mapping!F:F,0)) -> 8513 | E611: Merrimack | F611: 330 | G611: 10 | H611: 41.6
...

Sheet SODiv Index
A1: Conference | B1: SoD
A2: Big 12 | B2: 1
A3: Big Ten | B3: 1
A4: SEC | B4: 1
A5: Big East | B5: 0.95
A6: ACC | B6: 1
A7: MW | B7: 0.9
A8: American | B8: 0.7
A9: WCC | B9: 0.8
A10: A-10 | B10: 0.7
A11: C-USA | B11: 0.5
A12: MVC | B12: 0.5
A13: Ivy | B13: 0.5
... A32: SWAC | B32: 0.3

Sheet mapping
A1: BPI+ Value | B1: NET Map | C1: Count Check | D1: KP Map | E1: Count Check | F1: Stats Map | G1: Count Check | H1: ID | I1: INI | J1: ESPNimport | K1: ESPNimport2 | L1: Count Check | N1: Row Offset | P1: BPI+ Name | Q1: Stats Category | R1: Stat ID
A2: Miami | B2: Miami (FL) | C2: =COUNTIF('Net Import'!B:B,B2) -> 1 | D2: Miami FL | E2: =COUNTIF('KenPom import'!B:B,D2) -> 1 | F2: Miami (FL) | G2: =IF(COUNTIF('Stats import'!E:E,F2)>1,1,0) -> 1 | H2: 100 | I2: MIA | J2: =CONCATENATE(A2," ",INDEX(mascotCol,MATCH(A2,bpiTeams,0)),I2) -> Miami HurricanesMIA | K2: =CONCATENATE(A2," ",INDEX(mascotCol,MATCH(A2,bpiTeams,0)),A2," ",INDEX(mascotCol,MATCH(A2,bpiTeams,0))) -> Miami HurricanesMiami Hurricanes | L2: =COUNTIF(bpiImportCol,J2) -> 1 | N2: 367 | P2: 3PD% | Q2: Three Point Percentage Defense (361 ranked) | R2: 1
A3: McNeese | B3: McNeese | C3: =COUNTIF('Net Import'!B:B,B3) -> 1 | D3: McNeese | E3: =COUNTIF('KenPom import'!B:B,D3) -> 1 | F3: McNeese | G3: =IF(COUNTIF('Stats import'!E:E,F3)>1,1,0) -> 1 | H3: 200 | I3: MCN | J3: =CONCATENATE(A3," ",INDEX(mascotCol,MATCH(A3,bpiTeams,0)),I3) -> McNeese CowboysMCN | K3: =CONCATENATE(A3," ",INDEX(mascotCol,MATCH(A3,bpiTeams,0)),A3," ",INDEX(mascotCol,MATCH(A3,bpiTeams,0))) -> McNeese CowboysMcNeese Cowboys | L3: =COUNTIF(bpiImportCol,J3) -> 1 | P3: 3PPG | Q3: Three Pointers Per Game (361 ranked) | R3: 2
A4: Ole Miss | B4: Ole Miss | C4: =COUNTIF('Net Import'!B:B,B4) -> 1 | D4: Mississippi | E4: =COUNTIF('KenPom import'!B:B,D4) -> 1 | F4: Ole Miss | G4: =IF(COUNTIF('Stats import'!E:E,F4)>1,1,0) -> 0 | H4: 300 | I4: MISS | J4: =CONCATENATE(A4," ",INDEX(mascotCol,MATCH(A4,bpiTeams,0)),I4) -> #N/A | K4: =CONCATENATE(A4," ",INDEX(mascotCol,MATCH(A4,bpiTeams,0)),A4," ",INDEX(mascotCol,MATCH(A4,bpiTeams,0))) -> #N/A | L4: =COUNTIF(bpiImportCol,J4) -> 0 | N4: SOR Row Offset | P4: 3PT% | Q4: Three Point Percentage (361 ranked) | R4: 3
A5: Fort Wayne | B5: Purdue Fort Wayne | C5: =COUNTIF('Net Import'!B:B,B5) -> 1 | D5: Purdue Fort Wayne | E5: =COUNTIF('KenPom import'!B:B,D5) -> 1 | F5: Purdue Fort Wayne | G5: =IF(COUNTIF('Stats import'!E:E,F5)>1,1,0) -> 0 | H5: 400 | I5: PFW | J5: =CONCATENATE(A5," ",INDEX(mascotCol,MATCH(A5,bpiTeams,0)),I5) -> #N/A | K5: =CONCATENATE(A5," ",INDEX(mascotCol,MATCH(A5,bpiTeams,0)),A5," ",INDEX(mascotCol,MATCH(A5,bpiTeams,0))) -> #N/A | L5: =COUNTIF(bpiImportCol,J5) -> 0 | N5: 366 | P5: 3PTA | Q5: Three Point Attempts Per Game (361 ranked) | R5: 4
A6: Florida State | B6: Florida St. | C6: =COUNTIF('Net Import'!B:B,B6) -> 1 | D6: Florida St. | E6: =COUNTIF('KenPom import'!B:B,D6) -> 1 | F6: Florida St. | G6: =IF(COUNTIF('Stats import'!E:E,F6)>1,1,0) -> 0 | H6: 500 | I6: FSU | J6: =CONCATENATE(A6," ",INDEX(mascotCol,MATCH(A6,bpiTeams,0)),I6) -> #N/A | K6: =CONCATENATE(A6," ",INDEX(mascotCol,MATCH(A6,bpiTeams,0)),A6," ",INDEX(mascotCol,MATCH(A6,bpiTeams,0))) -> #N/A | L6: =COUNTIF(bpiImportCol,J6) -> 0 | P6: A:T | Q6: Assist/Turnover Ratio (361 ranked) | R6: 5
A7: Iowa State | B7: Iowa St. | C7: =COUNTIF('Net Import'!B:B,B7) -> 1 | D7: Iowa St. | E7: =COUNTIF('KenPom import'!B:B,D7) -> 1 | F7: Iowa St. | G7: =IF(COUNTIF('Stats import'!E:E,F7)>1,1,0) -> 1 | H7: 600 | I7: ISU | J7: =CONCATENATE(A7," ",INDEX(mascotCol,MATCH(A7,bpiTeams,0)),I7) -> Iowa State CyclonesISU | K7: =CONCATENATE(A7," ",INDEX(mascotCol,MATCH(A7,bpiTeams,0)),A7," ",INDEX(mascotCol,MATCH(A7,bpiTeams,0))) -> Iowa State CyclonesIowa State Cyclones | L7: =COUNTIF(bpiImportCol,J7) -> 1 | P7: APG | Q7: Assists Per Game (361 ranked) | R7: 6
A8: Kansas State | B8: Kansas St. | C8: =COUNTIF('Net Import'!B:B,B8) -> 1 | D8: Kansas St. | E8: =COUNTIF('KenPom import'!B:B,D8) -> 1 | F8: Kansas St. | G8: =IF(COUNTIF('Stats import'!E:E,F8)>1,1,0) -> 0 | H8: 700 | I8: KSU | J8: =CONCATENATE(A8," ",INDEX(mascotCol,MATCH(A8,bpiTeams,0)),I8) -> #N/A | K8: =CONCATENATE(A8," ",INDEX(mascotCol,MATCH(A8,bpiTeams,0)),A8," ",INDEX(mascotCol,MATCH(A8,bpiTeams,0))) -> #N/A | L8: =COUNTIF(bpiImportCol,J8) -> 0 | P8: Bench | Q8: Bench Points per game (350 ranked) | R8: 7
A9: Weber State | B9: Weber St. | C9: =COUNTIF('Net Import'!B:B,B9) -> 1 | D9: Weber St. | E9: =COUNTIF('KenPom import'!B:B,D9) -> 1 | F9: Weber St. | G9: =IF(COUNTIF('Stats import'!E:E,F9)>1,1,0) -> 0 | H9: 800 | I9: WEB | J9: =CONCATENATE(A9," ",INDEX(mascotCol,MATCH(A9,bpiTeams,0)),I9) -> #N/A | K9: =CONCATENATE(A9," ",INDEX(mascotCol,MATCH(A9,bpiTeams,0)),A9," ",INDEX(mascotCol,MATCH(A9,bpiTeams,0))) -> #N/A | L9: =COUNTIF(bpiImportCol,J9) -> 0 | P9: BPG | Q9: Blocks Per Game (361 ranked) | R9: 8
A10: Michigan State | B10: Michigan St. | C10: =COUNTIF('Net Import'!B:B,B10) -> 1 | D10: Michigan St. | E10: =COUNTIF('KenPom import'!B:B,D10) -> 1 | F10: Michigan St. | G10: =IF(COUNTIF('Stats import'!E:E,F10)>1,1,0) -> 1 | H10: 900 | I10: MSU | J10: =CONCATENATE(A10," ",INDEX(mascotCol,MATCH(A10,bpiTeams,0)),I10) -> Michigan State SpartansMSU | K10: =CONCATENATE(A10," ",INDEX(mascotCol,MATCH(A10,bpiTeams,0)),A10," ",INDEX(mascotCol,MATCH(A10,bpiTeams,0))) -> Michigan State SpartansMichigan State Spartans | L10: =COUNTIF(bpiImportCol,J10) -> 1 | P10: DFG% | Q10: Field Goal Percentage Defense (361 ranked) | R10: 9
A11: Ohio State | B11: Ohio St. | C11: =COUNTIF('Net Import'!B:B,B11) -> 1 | D11: Ohio St. | E11: =COUNTIF('KenPom import'!B:B,D11) -> 1 | F11: Ohio St. | G11: =IF(COUNTIF('Stats import'!E:E,F11)>1,1,0) -> 1 | H11: 1000 | I11: OSU | J11: =CONCATENATE(A11," ",INDEX(mascotCol,MATCH(A11,bpiTeams,0)),I11) -> Ohio State BuckeyesOSU | K11: =CONCATENATE(A11," ",INDEX(mascotCol,MATCH(A11,bpiTeams,0)),A11," ",INDEX(mascotCol,MATCH(A11,bpiTeams,0))) -> Ohio State BuckeyesOhio State Buckeyes | L11: =COUNTIF(bpiImportCol,J11) -> 1 | P11: DRPG | Q11: Rebounds (Defensive) Per Game (361 ranked) | R11: 10
A12: Indiana State | B12: Indiana St. | C12: =COUNTIF('Net Import'!B:B,B12) -> 1 | D12: Indiana St. | E12: =COUNTIF('KenPom import'!B:B,D12) -> 1 | F12: Indiana St. | G12: =IF(COUNTIF('Stats import'!E:E,F12)>1,1,0) -> 0 | H12: 1100 | I12: INST | J12: =CONCATENATE(A12," ",INDEX(mascotCol,MATCH(A12,bpiTeams,0)),I12) -> #N/A | K12: =CONCATENATE(A12," ",INDEX(mascotCol,MATCH(A12,bpiTeams,0)),A12," ",INDEX(mascotCol,MATCH(A12,bpiTeams,0))) -> #N/A | L12: =COUNTIF(bpiImportCol,J12) -> 0 | P12: EFG% | Q12: Effective FG pct (361 ranked) | R12: 11
A13: San Diego State | B13: San Diego St. | C13: =COUNTIF('Net Import'!B:B,B13) -> 1 | D13: San Diego St. | E13: =COUNTIF('KenPom import'!B:B,D13) -> 1 | F13: San Diego St. | G13: =IF(COUNTIF('Stats import'!E:E,F13)>1,1,0) -> 1 | H13: 1200 | I13: SDSU | J13: =CONCATENATE(A13," ",INDEX(mascotCol,MATCH(A13,bpiTeams,0)),I13) -> San Diego State AztecsSDSU | K13: =CONCATENATE(A13," ",INDEX(mascotCol,MATCH(A13,bpiTeams,0)),A13," ",INDEX(mascotCol,MATCH(A13,bpiTeams,0))) -> San Diego State AztecsSan Diego State Aztecs | L13: =COUNTIF(bpiImportCol,J13) -> 1 | P13: FB | Q13: Fastbreak Points (361 ranked) | R13: 12
A14: Colorado State | B14: Colorado St. | C14: =COUNTIF('Net Import'!B:B,B14) -> 1 | D14: Colorado St. | E14: =COUNTIF('KenPom import'!B:B,D14) -> 1 | F14: Colorado St. | G14: =IF(COUNTIF('Stats import'!E:E,F14)>1,1,0) -> 0 | H14: 1300 | I14: CSU | J14: =CONCATENATE(A14," ",INDEX(mascotCol,MATCH(A14,bpiTeams,0)),I14) -> #N/A | K14: =CONCATENATE(A14," ",INDEX(mascotCol,MATCH(A14,bpiTeams,0)),A14," ",INDEX(mascotCol,MATCH(A14,bpiTeams,0))) -> #N/A | L14: =COUNTIF(bpiImportCol,J14) -> 0 | P14: FG% | Q14: Field Goal Percentage (361 ranked) | R14: 13
A15: Utah State | B15: Utah St. | C15: =COUNTIF('Net Import'!B:B,B15) -> 1 | D15: Utah St. | E15: =COUNTIF('KenPom import'!B:B,D15) -> 1 | F15: Utah St. | G15: =IF(COUNTIF('Stats import'!E:E,F15)>1,1,0) -> 1 | H15: 1400 | I15: USU | J15: =CONCATENATE(A15," ",INDEX(mascotCol,MATCH(A15,bpiTeams,0)),I15) -> Utah State AggiesUSU | K15: =CONCATENATE(A15," ",INDEX(mascotCol,MATCH(A15,bpiTeams,0)),A15," ",INDEX(mascotCol,MATCH(A15,bpiTeams,0))) -> Utah State AggiesUtah State Aggies | L15: =COUNTIF(bpiImportCol,J15) -> 1 | P15: FPG | Q15: Fouls Per Game (361 ranked) | R15: 14
A16: Morehead State | B16: Morehead St. | C16: =COUNTIF('Net Import'!B:B,B16) -> 1 | D16: Morehead St. | E16: =COUNTIF('KenPom import'!B:B,D16) -> 1 | F16: Morehead St. | G16: =IF(COUNTIF('Stats import'!E:E,F16)>1,1,0) -> 0 | H16: 1500 | I16: MORE | J16: =CONCATENATE(A16," ",INDEX(mascotCol,MATCH(A16,bpiTeams,0)),I16) -> #N/A | K16: =CONCATENATE(A16," ",INDEX(mascotCol,MATCH(A16,bpiTeams,0)),A16," ",INDEX(mascotCol,MATCH(A16,bpiTeams,0))) -> #N/A | L16: =COUNTIF(bpiImportCol,J16) -> 0 | P16: FT% | Q16: Free Throw Percentage (361 ranked) | R16: 15
A17: Mississippi State | B17: Mississippi St. | C17: =COUNTIF('Net Import'!B:B,B17) -> 1 | D17: Mississippi St. | E17: =COUNTIF('KenPom import'!B:B,D17) -> 1 | F17: Mississippi St. | G17: =IF(COUNTIF('Stats import'!E:E,F17)>1,1,0) -> 0 | H17: 1600 | I17: MSST | J17: =CONCATENATE(A17," ",INDEX(mascotCol,MATCH(A17,bpiTeams,0)),I17) -> #N/A | K17: =CONCATENATE(A17," ",INDEX(mascotCol,MATCH(A17,bpiTeams,0)),A17," ",INDEX(mascotCol,MATCH(A17,bpiTeams,0))) -> #N/A | L17: =COUNTIF(bpiImportCol,J17) -> 0 | P17: FTA | Q17: Free Throw Attempts Per Game (361 ranked) | R17: 16
... A23: Florida Atlantic | B23: Fla. Atlantic | C23: =COUNTIF('Net Import'!B:B,B23) -> 1 | D23: Florida Atlantic | E23: =COUNTIF('KenPom import'!B:B,D23) -> 1 | F23: Fla. Atlantic | G23: =IF(COUNTIF('Stats import'!E:E,F23)>1,1,0) -> 0 | H23: 2200 | I23: FAU | J23: =CONCATENATE(A23," ",INDEX(mascotCol,MATCH(A23,bpiTeams,0)),I23) -> #N/A | K23: =CONCATENATE(A23," ",INDEX(mascotCol,MATCH(A23,bpiTeams,0)),A23," ",INDEX(mascotCol,MATCH(A23,bpiTeams,0))) -> #N/A | L23: =COUNTIF(bpiImportCol,J23) -> 0 | P23: RPG | Q23: Rebounds Per Game (361 ranked) | R23: 22
A24: Connecticut | B24: UConn | C24: =COUNTIF('Net Import'!B:B,B24) -> 1 | D24: Connecticut | E24: =COUNTIF('KenPom import'!B:B,D24) -> 1 | F24: UConn | G24: =IF(COUNTIF('Stats import'!E:E,F24)>1,1,0) -> 1 | H24: 2300 | I24: CONN | J24: UConn HuskiesCONN | K24: =CONCATENATE("UConn"," ",INDEX(mascotCol,MATCH(A24,bpiTeams,0)),"UConn"," ",INDEX(mascotCol,MATCH(A24,bpiTeams,0))) -> UConn HuskiesUConn Huskies | L24: =COUNTIF(bpiImportCol,J24) -> 1 | P24: SM | Q24: Scoring Margin (361 ranked) | R24: 23
A25: USC | B25: Southern California | C25: =COUNTIF('Net Import'!B:B,B25) -> 1 | D25: USC | E25: =COUNTIF('KenPom import'!B:B,D25) -> 1 | F25: Southern California | G25: =IF(COUNTIF('Stats import'!E:E,F25)>1,1,0) -> 1 | H25: 2400 | I25: USC | J25: =CONCATENATE(A25," ",INDEX(mascotCol,MATCH(A25,bpiTeams,0)),I25) -> #N/A | K25: =CONCATENATE(A25," ",INDEX(mascotCol,MATCH(A25,bpiTeams,0)),A25," ",INDEX(mascotCol,MATCH(A25,bpiTeams,0))) -> #N/A | L25: =COUNTIF(bpiImportCol,J25) -> 0 | P25: SPG | Q25: Steals Per Game (361 ranked) | R25: 24
A26: Saint Mary's | B26: Saint Mary's (CA) | C26: =COUNTIF('Net Import'!B:B,B26) -> 1 | D26: Saint Mary's | E26: =COUNTIF('KenPom import'!B:B,D26) -> 1 | F26: Saint Mary's (CA) | G26: =IF(COUNTIF('Stats import'!E:E,F26)>1,1,0) -> 1 | H26: 2500 | I26: SMC | J26: =CONCATENATE(A26," ",INDEX(mascotCol,MATCH(A26,bpiTeams,0)),I26) -> Saint Mary's GaelsSMC | K26: =CONCATENATE(A26," ",INDEX(mascotCol,MATCH(A26,bpiTeams,0)),A26," ",INDEX(mascotCol,MATCH(A26,bpiTeams,0))) -> Saint Mary's GaelsSaint Mary's Gaels | L26: =COUNTIF(bpiImportCol,J26) -> 1 | P26: TM | Q26: Turnover Margin (361 ranked) | R26: 25
A27: Virginia | B27: Virginia | C27: =COUNTIF('Net Import'!B:B,B27) -> 1 | D27: Virginia | E27: =COUNTIF('KenPom import'!B:B,D27) -> 1 | F27: Virginia | G27: =IF(COUNTIF('Stats import'!E:E,F27)>1,1,0) -> 1 | H27: 2600 | I27: UVA | J27: =CONCATENATE(A27," ",INDEX(mascotCol,MATCH(A27,bpiTeams,0)),I27) -> Virginia CavaliersUVA | K27: =CONCATENATE(A27," ",INDEX(mascotCol,MATCH(A27,bpiTeams,0)),A27," ",INDEX(mascotCol,MATCH(A27,bpiTeams,0))) -> Virginia CavaliersVirginia Cavaliers | L27: =COUNTIF(bpiImportCol,J27) -> 1 | P27: TOF | Q27: Turnovers Forced Per Game (361 ranked) | R27: 26
A28: BYU | B28: BYU | C28: =COUNTIF('Net Import'!B:B,B28) -> 1 | D28: BYU | E28: =COUNTIF('KenPom import'!B:B,D28) -> 1 | F28: BYU | G28: =IF(COUNTIF('Stats import'!E:E,F28)>1,1,0) -> 1 | H28: 2700 | I28: BYU | J28: =CONCATENATE(A28," ",INDEX(mascotCol,MATCH(A28,bpiTeams,0)),I28) -> BYU CougarsBYU | K28: =CONCATENATE(A28," ",INDEX(mascotCol,MATCH(A28,bpiTeams,0)),A28," ",INDEX(mascotCol,MATCH(A28,bpiTeams,0))) -> BYU CougarsBYU Cougars | L28: =COUNTIF(bpiImportCol,J28) -> 1 | P28: TPG | Q28: Turnovers Per Game (361 ranked) | R28: 27
A29: Houston | B29: Houston | C29: =COUNTIF('Net Import'!B:B,B29) -> 1 | D29: Houston | E29: =COUNTIF('KenPom import'!B:B,D29) -> 1 | F29: Houston | G29: =IF(COUNTIF('Stats import'!E:E,F29)>1,1,0) -> 1 | H29: 2800 | I29: HOU | J29: =CONCATENATE(A29," ",INDEX(mascotCol,MATCH(A29,bpiTeams,0)),I29) -> Houston CougarsHOU | K29: =CONCATENATE(A29," ",INDEX(mascotCol,MATCH(A29,bpiTeams,0)),A29," ",INDEX(mascotCol,MATCH(A29,bpiTeams,0))) -> Houston CougarsHouston Cougars | L29: =COUNTIF(bpiImportCol,J29) -> 1 | P29: Bench | Q29: Bench Points per game (361 ranked) | R29: 7
A30: Arizona | B30: Arizona | C30: =COUNTIF('Net Import'!B:B,B30) -> 1 | D30: Arizona | E30: =COUNTIF('KenPom import'!B:B,D30) -> 1 | F30: Arizona | G30: =IF(COUNTIF('Stats import'!E:E,F30)>1,1,0) -> 1 | H30: 2900 | I30: ARIZ | J30: =CONCATENATE(A30," ",INDEX(mascotCol,MATCH(A30,bpiTeams,0)),I30) -> Arizona WildcatsARIZ | K30: =CONCATENATE(A30," ",INDEX(mascotCol,MATCH(A30,bpiTeams,0)),A30," ",INDEX(mascotCol,MATCH(A30,bpiTeams,0))) -> Arizona WildcatsArizona Wildcats | L30: =COUNTIF(bpiImportCol,J30) -> 1 | P30: 3PT% | Q30: Three Point Percentage (360 ranked) | R30: 3
A31: Purdue | B31: Purdue | C31: =COUNTIF('Net Import'!B:B,B31) -> 1 | D31: Purdue | E31: =COUNTIF('KenPom import'!B:B,D31) -> 1 | F31: Purdue | G31: =IF(COUNTIF('Stats import'!E:E,F31)>1,1,0) -> 1 | H31: 3000 | I31: PUR | J31: =CONCATENATE(A31," ",INDEX(mascotCol,MATCH(A31,bpiTeams,0)),I31) -> Purdue BoilermakersPUR | K31: =CONCATENATE(A31," ",INDEX(mascotCol,MATCH(A31,bpiTeams,0)),A31," ",INDEX(mascotCol,MATCH(A31,bpiTeams,0))) -> Purdue BoilermakersPurdue Boilermakers | L31: =COUNTIF(bpiImportCol,J31) -> 1
A32: Creighton | B32: Creighton | C32: =COUNTIF('Net Import'!B:B,B32) -> 1 | D32: Creighton | E32: =COUNTIF('KenPom import'!B:B,D32) -> 1 | F32: Creighton | G32: =IF(COUNTIF('Stats import'!E:E,F32)>1,1,0) -> 0 | H32: 3100 | I32: CREI | J32: =CONCATENATE(A32," ",INDEX(mascotCol,MATCH(A32,bpiTeams,0)),I32) -> #N/A | K32: =CONCATENATE(A32," ",INDEX(mascotCol,MATCH(A32,bpiTeams,0)),A32," ",INDEX(mascotCol,MATCH(A32,bpiTeams,0))) -> #N/A | L32: =COUNTIF(bpiImportCol,J32) -> 0
A33: Baylor | B33: Baylor | C33: =COUNTIF('Net Import'!B:B,B33) -> 1 | D33: Baylor | E33: =COUNTIF('KenPom import'!B:B,D33) -> 1 | F33: Baylor | G33: =IF(COUNTIF('Stats import'!E:E,F33)>1,1,0) -> 0 | H33: 3200 | I33: BAY | J33: =CONCATENATE(A33," ",INDEX(mascotCol,MATCH(A33,bpiTeams,0)),I33) -> #N/A | K33: =CONCATENATE(A33," ",INDEX(mascotCol,MATCH(A33,bpiTeams,0)),A33," ",INDEX(mascotCol,MATCH(A33,bpiTeams,0))) -> #N/A | L33: =COUNTIF(bpiImportCol,J33) -> 0
A34: Marquette | B34: Marquette | C34: =COUNTIF('Net Import'!B:B,B34) -> 1 | D34: Marquette | E34: =COUNTIF('KenPom import'!B:B,D34) -> 1 | F34: Marquette | G34: =IF(COUNTIF('Stats import'!E:E,F34)>1,1,0) -> 0 | H34: 3300 | I34: MARQ | J34: =CONCATENATE(A34," ",INDEX(mascotCol,MATCH(A34,bpiTeams,0)),I34) -> #N/A | K34: =CONCATENATE(A34," ",INDEX(mascotCol,MATCH(A34,bpiTeams,0)),A34," ",INDEX(mascotCol,MATCH(A34,bpiTeams,0))) -> #N/A | L34: =COUNTIF(bpiImportCol,J34) -> 0
A35: Princeton | B35: Princeton | C35: =COUNTIF('Net Import'!B:B,B35) -> 1 | D35: Princeton | E35: =COUNTIF('KenPom import'!B:B,D35) -> 1 | F35: Princeton | G35: =IF(COUNTIF('Stats import'!E:E,F35)>1,1,0) -> 0 | H35: 3400 | I35: PRIN | J35: =CONCATENATE(A35," ",INDEX(mascotCol,MATCH(A35,bpiTeams,0)),I35) -> #N/A | K35: =CONCATENATE(A35," ",INDEX(mascotCol,MATCH(A35,bpiTeams,0)),A35," ",INDEX(mascotCol,MATCH(A35,bpiTeams,0))) -> #N/A | L35: =COUNTIF(bpiImportCol,J35) -> 0
A36: Tennessee | B36: Tennessee | C36: =COUNTIF('Net Import'!B:B,B36) -> 1 | D36: Tennessee | E36: =COUNTIF('KenPom import'!B:B,D36) -> 1 | F36: Tennessee | G36: =IF(COUNTIF('Stats import'!E:E,F36)>1,1,0) -> 1 | H36: 3500 | I36: TENN | J36: =CONCATENATE(A36," ",INDEX(mascotCol,MATCH(A36,bpiTeams,0)),I36) -> Tennessee VolunteersTENN | K36: =CONCATENATE(A36," ",INDEX(mascotCol,MATCH(A36,bpiTeams,0)),A36," ",INDEX(mascotCol,MATCH(A36,bpiTeams,0))) -> Tennessee VolunteersTennessee Volunteers | L36: =COUNTIF(bpiImportCol,J36) -> 1
A37: Texas A&M | B37: Texas A&M | C37: =COUNTIF('Net Import'!B:B,B37) -> 1 | D37: Texas A&M | E37: =COUNTIF('KenPom import'!B:B,D37) -> 1 | F37: Texas A&M | G37: =IF(COUNTIF('Stats import'!E:E,F37)>1,1,0) -> 1 | H37: 3600 | I37: TA&M | J37: =CONCATENATE(A37," ",INDEX(mascotCol,MATCH(A37,bpiTeams,0)),I37) -> Texas A&M AggiesTA&M | K37: =CONCATENATE(A37," ",INDEX(mascotCol,MATCH(A37,bpiTeams,0)),A37," ",INDEX(mascotCol,MATCH(A37,bpiTeams,0))) -> Texas A&M AggiesTexas A&M Aggies | L37: =COUNTIF(bpiImportCol,J37) -> 1
A38: Alabama | B38: Alabama | C38: =COUNTIF('Net Import'!B:B,B38) -> 1 | D38: Alabama | E38: =COUNTIF('KenPom import'!B:B,D38) -> 1 | F38: Alabama | G38: =IF(COUNTIF('Stats import'!E:E,F38)>1,1,0) -> 1 | H38: 3700 | I38: ALA | J38: =CONCATENATE(A38," ",INDEX(mascotCol,MATCH(A38,bpiTeams,0)),I38) -> Alabama Crimson TideALA | K38: =CONCATENATE(A38," ",INDEX(mascotCol,MATCH(A38,bpiTeams,0)),A38," ",INDEX(mascotCol,MATCH(A38,bpiTeams,0))) -> Alabama Crimson TideAlabama Crimson Tide | L38: =COUNTIF(bpiImportCol,J38) -> 1
A39: Oklahoma | B39: Oklahoma | C39: =COUNTIF('Net Import'!B:B,B39) -> 1 | D39: Oklahoma | E39: =COUNTIF('KenPom import'!B:B,D39) -> 1 | F39: Oklahoma | G39: =IF(COUNTIF('Stats import'!E:E,F39)>1,1,0) -> 1 | H39: 3800 | I39: OU | J39: =CONCATENATE(A39," ",INDEX(mascotCol,MATCH(A39,bpiTeams,0)),I39) -> Oklahoma SoonersOU | K39: =CONCATENATE(A39," ",INDEX(mascotCol,MATCH(A39,bpiTeams,0)),A39," ",INDEX(mascotCol,MATCH(A39,bpiTeams,0))) -> Oklahoma SoonersOklahoma Sooners | L39: =COUNTIF(bpiImportCol,J39) -> 1
A40: Kansas | B40: Kansas | C40: =COUNTIF('Net Import'!B:B,B40) -> 1 | D40: Kansas | E40: =COUNTIF('KenPom import'!B:B,D40) -> 1 | F40: Kansas | G40: =IF(COUNTIF('Stats import'!E:E,F40)>1,1,0) -> 1 | H40: 3900 | I40: KU | J40: =CONCATENATE(A40," ",INDEX(mascotCol,MATCH(A40,bpiTeams,0)),I40) -> Kansas JayhawksKU | K40: =CONCATENATE(A40," ",INDEX(mascotCol,MATCH(A40,bpiTeams,0)),A40," ",INDEX(mascotCol,MATCH(A40,bpiTeams,0))) -> Kansas JayhawksKansas Jayhawks | L40: =COUNTIF(bpiImportCol,J40) -> 1
A41: Clemson | B41: Clemson | C41: =COUNTIF('Net Import'!B:B,B41) -> 1 | D41: Clemson | E41: =COUNTIF('KenPom import'!B:B,D41) -> 1 | F41: Clemson | G41: =IF(COUNTIF('Stats import'!E:E,F41)>1,1,0) -> 1 | H41: 4000 | I41: CLEM | J41: =CONCATENATE(A41," ",INDEX(mascotCol,MATCH(A41,bpiTeams,0)),I41) -> Clemson TigersCLEM | K41: =CONCATENATE(A41," ",INDEX(mascotCol,MATCH(A41,bpiTeams,0)),A41," ",INDEX(mascotCol,MATCH(A41,bpiTeams,0))) -> Clemson TigersClemson Tigers | L41: =COUNTIF(bpiImportCol,J41) -> 1
A42: Cincinnati | B42: Cincinnati | C42: =COUNTIF('Net Import'!B:B,B42) -> 1 | D42: Cincinnati | E42: =COUNTIF('KenPom import'!B:B,D42) -> 1 | F42: Cincinnati | G42: =IF(COUNTIF('Stats import'!E:E,F42)>1,1,0) -> 1 | H42: 4100 | I42: CIN | J42: =CONCATENATE(A42," ",INDEX(mascotCol,MATCH(A42,bpiTeams,0)),I42) -> Cincinnati BearcatsCIN | K42: =CONCATENATE(A42," ",INDEX(mascotCol,MATCH(A42,bpiTeams,0)),A42," ",INDEX(mascotCol,MATCH(A42,bpiTeams,0))) -> Cincinnati BearcatsCincinnati Bearcats | L42: =COUNTIF(bpiImportCol,J42) -> 1
... A110: Oakland | B110: Oakland | C110: =COUNTIF('Net Import'!B:B,B110) -> 1 | D110: Oakland | E110: =COUNTIF('KenPom import'!B:B,D110) -> 1 | F110: Oakland | G110: =IF(COUNTIF('Stats import'!E:E,F110)>1,1,0) -> 0 | H110: 10900 | I110: OAK | J110: =CONCATENATE(A110," ",INDEX(mascotCol,MATCH(A110,bpiTeams,0)),I110) -> #N/A | K110: =CONCATENATE(A110," ",INDEX(mascotCol,MATCH(A110,bpiTeams,0)),A110," ",INDEX(mascotCol,MATCH(A110,bpiTeams,0))) -> #N/A | L110: =COUNTIF(bpiImportCol,J110) -> 0
A111: Quinnipiac | B111: =A111 -> Quinnipiac | C111: =COUNTIF('Net Import'!B:B,B111) -> 1 | D111: =A111 -> Quinnipiac | E111: =COUNTIF('KenPom import'!B:B,D111) -> 1 | F111: =A111 -> Quinnipiac | G111: =IF(COUNTIF('Stats import'!E:E,F111)>1,1,0) -> 0 | H111: =H110+100 -> 11000 | I111: QUIN | J111: =CONCATENATE(A111," ",INDEX(mascotCol,MATCH(A111,bpiTeams,0)),I111) -> #N/A | K111: =CONCATENATE(A111," ",INDEX(mascotCol,MATCH(A111,bpiTeams,0)),A111," ",INDEX(mascotCol,MATCH(A111,bpiTeams,0))) -> #N/A | L111: =COUNTIF(bpiImportCol,J111) -> 0
A112: Maryland | B112: =A112 -> Maryland | C112: =COUNTIF('Net Import'!B:B,B112) -> 1 | D112: =A112 -> Maryland | E112: =COUNTIF('KenPom import'!B:B,D112) -> 1 | F112: =A112 -> Maryland | G112: =IF(COUNTIF('Stats import'!E:E,F112)>1,1,0) -> 0 | H112: =H111+100 -> 11100 | I112: MD | J112: =CONCATENATE(A112," ",INDEX(mascotCol,MATCH(A112,bpiTeams,0)),I112) -> #N/A | K112: =CONCATENATE(A112," ",INDEX(mascotCol,MATCH(A112,bpiTeams,0)),A112," ",INDEX(mascotCol,MATCH(A112,bpiTeams,0))) -> #N/A | L112: =COUNTIF(bpiImportCol,J112) -> 0
A113: USF | B113: South Fla. | C113: =COUNTIF('Net Import'!B:B,B113) -> 1 | D113: South Florida | E113: =COUNTIF('KenPom import'!B:B,D113) -> 1 | F113: South Fla. | G113: =IF(COUNTIF('Stats import'!E:E,F113)>1,1,0) -> 1 | H113: =H112+100 -> 11200 | I113: USF | J113: South Florida BullsUSF | K113: =CONCATENATE("South Florida"," ",INDEX(mascotCol,MATCH(A113,bpiTeams,0)),"South Florida"," ",INDEX(mascotCol,MATCH(A113,bpiTeams,0))) -> South Florida BullsSouth Florida Bulls | L113: =COUNTIF(bpiImportCol,J113) -> 1
A114: Stetson | B114: =A114 -> Stetson | C114: =COUNTIF('Net Import'!B:B,B114) -> 1 | D114: =A114 -> Stetson | E114: =COUNTIF('KenPom import'!B:B,D114) -> 1 | F114: =A114 -> Stetson | G114: =IF(COUNTIF('Stats import'!E:E,F114)>1,1,0) -> 0 | H114: =H113+100 -> 11300 | I114: STET | J114: =CONCATENATE(A114," ",INDEX(mascotCol,MATCH(A114,bpiTeams,0)),I114) -> #N/A | K114: =CONCATENATE(A114," ",INDEX(mascotCol,MATCH(A114,bpiTeams,0)),A114," ",INDEX(mascotCol,MATCH(A114,bpiTeams,0))) -> #N/A | L114: =COUNTIF(bpiImportCol,J114) -> 0
A115: Longwood | B115: =A115 -> Longwood | C115: =COUNTIF('Net Import'!B:B,B115) -> 1 | D115: =A115 -> Longwood | E115: =COUNTIF('KenPom import'!B:B,D115) -> 1 | F115: =A115 -> Longwood | G115: =IF(COUNTIF('Stats import'!E:E,F115)>1,1,0) -> 0 | H115: =H114+100 -> 11400 | I115: LONG | J115: =CONCATENATE(A115," ",INDEX(mascotCol,MATCH(A115,bpiTeams,0)),I115) -> #N/A | K115: =CONCATENATE(A115," ",INDEX(mascotCol,MATCH(A115,bpiTeams,0)),A115," ",INDEX(mascotCol,MATCH(A115,bpiTeams,0))) -> #N/A | L115: =COUNTIF(bpiImportCol,J115) -> 0
A116: Charleston | B116: Col. of Charleston | C116: =COUNTIF('Net Import'!B:B,B116) -> 1 | D116: =A116 -> Charleston | E116: =COUNTIF('KenPom import'!B:B,D116) -> 1 | F116: Col. of Charleston | G116: =IF(COUNTIF('Stats import'!E:E,F116)>1,1,0) -> 0 | H116: =H115+100 -> 11500 | I116: COFC | J116: =CONCATENATE(A116," ",INDEX(mascotCol,MATCH(A116,bpiTeams,0)),I116) -> #N/A | K116: =CONCATENATE(A116," ",INDEX(mascotCol,MATCH(A116,bpiTeams,0)),A116," ",INDEX(mascotCol,MATCH(A116,bpiTeams,0))) -> #N/A | L116: =COUNTIF(bpiImportCol,J116) -> 0
A117: Wagner | B117: =A117 -> Wagner | C117: =COUNTIF('Net Import'!B:B,B117) -> 1 | D117: =A117 -> Wagner | E117: =COUNTIF('KenPom import'!B:B,D117) -> 1 | F117: =A117 -> Wagner | G117: =IF(COUNTIF('Stats import'!E:E,F117)>1,1,0) -> 0 | H117: =H116+100 -> 11600 | I117: WAG | J117: =CONCATENATE(A117," ",INDEX(mascotCol,MATCH(A117,bpiTeams,0)),I117) -> #N/A | K117: =CONCATENATE(A117," ",INDEX(mascotCol,MATCH(A117,bpiTeams,0)),A117," ",INDEX(mascotCol,MATCH(A117,bpiTeams,0))) -> #N/A | L117: =COUNTIF(bpiImportCol,J117) -> 0
A118: Montana | B118: =A118 -> Montana | C118: =COUNTIF('Net Import'!B:B,B118) -> 1 | D118: =A118 -> Montana | E118: =COUNTIF('KenPom import'!B:B,D118) -> 1 | F118: =A118 -> Montana | G118: =IF(COUNTIF('Stats import'!E:E,F118)>1,1,0) -> 0 | H118: =H117+100 -> 11700 | I118: MONT | J118: =CONCATENATE(A118," ",INDEX(mascotCol,MATCH(A118,bpiTeams,0)),I118) -> #N/A | K118: =CONCATENATE(A118," ",INDEX(mascotCol,MATCH(A118,bpiTeams,0)),A118," ",INDEX(mascotCol,MATCH(A118,bpiTeams,0))) -> #N/A | L118: =COUNTIF(bpiImportCol,J118) -> 0
A119: Texas Southern | B119: =A119 -> Texas Southern | C119: =COUNTIF('Net Import'!B:B,B119) -> 1 | D119: =A119 -> Texas Southern | E119: =COUNTIF('KenPom import'!B:B,D119) -> 1 | F119: =A119 -> Texas Southern | G119: =IF(COUNTIF('Stats import'!E:E,F119)>1,1,0) -> 0 | H119: =H118+100 -> 11800 | I119: TXSO | J119: =CONCATENATE(A119," ",INDEX(mascotCol,MATCH(A119,bpiTeams,0)),I119) -> #N/A | K119: =CONCATENATE(A119," ",INDEX(mascotCol,MATCH(A119,bpiTeams,0)),A119," ",INDEX(mascotCol,MATCH(A119,bpiTeams,0))) -> #N/A | L119: =COUNTIF(bpiImportCol,J119) -> 0
A120: Grambling | B120: =A120 -> Grambling | C120: =COUNTIF('Net Import'!B:B,B120) -> 1 | D120: Grambling St. | E120: =COUNTIF('KenPom import'!B:B,D120) -> 1 | F120: Grambling | G120: =IF(COUNTIF('Stats import'!E:E,F120)>1,1,0) -> 0 | H120: =H119+100 -> 11900 | I120: GRAM | J120: =CONCATENATE(A120," ",INDEX(mascotCol,MATCH(A120,bpiTeams,0)),I120) -> #N/A | K120: =CONCATENATE(A120," ",INDEX(mascotCol,MATCH(A120,bpiTeams,0)),A120," ",INDEX(mascotCol,MATCH(A120,bpiTeams,0))) -> #N/A | L120: =COUNTIF(bpiImportCol,J120) -> 0
A121: Montana State | B121: Montana St. | C121: =COUNTIF('Net Import'!B:B,B121) -> 1 | D121: Montana St. | E121: =COUNTIF('KenPom import'!B:B,D121) -> 1 | F121: Montana St. | G121: =IF(COUNTIF('Stats import'!E:E,F121)>1,1,0) -> 0 | H121: =H120+100 -> 12000 | I121: MTST | J121: =CONCATENATE(A121," ",INDEX(mascotCol,MATCH(A121,bpiTeams,0)),I121) -> #N/A | K121: =CONCATENATE(A121," ",INDEX(mascotCol,MATCH(A121,bpiTeams,0)),A121," ",INDEX(mascotCol,MATCH(A121,bpiTeams,0))) -> #N/A | L121: =COUNTIF(bpiImportCol,J121) -> 0
A122: Western Kentucky | B122: Western Ky. | C122: =COUNTIF('Net Import'!B:B,B122) -> 1 | D122: =A122 -> Western Kentucky | E122: =COUNTIF('KenPom import'!B:B,D122) -> 1 | F122: Western Ky. | G122: =IF(COUNTIF('Stats import'!E:E,F122)>1,1,0) -> 0 | H122: =H121+100 -> 12100 | I122: WKU | J122: =CONCATENATE(A122," ",INDEX(mascotCol,MATCH(A122,bpiTeams,0)),I122) -> #N/A | K122: =CONCATENATE(A122," ",INDEX(mascotCol,MATCH(A122,bpiTeams,0)),A122," ",INDEX(mascotCol,MATCH(A122,bpiTeams,0))) -> #N/A | L122: =COUNTIF(bpiImportCol,J122) -> 0
A123: VCU | B123: =A123 -> VCU | C123: =COUNTIF('Net Import'!B:B,B123) -> 1 | D123: =A123 -> VCU | E123: =COUNTIF('KenPom import'!B:B,D123) -> 1 | F123: =A123 -> VCU | G123: =IF(COUNTIF('Stats import'!E:E,F123)>1,1,0) -> 1 | H123: =H122+100 -> 12200 | I123: VCU | J123: =CONCATENATE(A123," ",INDEX(mascotCol,MATCH(A123,bpiTeams,0)),I123) -> VCU RamsVCU | K123: =CONCATENATE(A123," ",INDEX(mascotCol,MATCH(A123,bpiTeams,0)),A123," ",INDEX(mascotCol,MATCH(A123,bpiTeams,0))) -> VCU RamsVCU Rams | L123: =COUNTIF(bpiImportCol,J123) -> 1
A124: Fairfield | B124: =A124 -> Fairfield | C124: =COUNTIF('Net Import'!B:B,B124) -> 1 | D124: =A124 -> Fairfield | E124: =COUNTIF('KenPom import'!B:B,D124) -> 1 | F124: =A124 -> Fairfield | G124: =IF(COUNTIF('Stats import'!E:E,F124)>1,1,0) -> 0 | H124: =H123+100 -> 12300 | I124: FAIR | J124: =CONCATENATE(A124," ",INDEX(mascotCol,MATCH(A124,bpiTeams,0)),I124) -> #N/A | K124: =CONCATENATE(A124," ",INDEX(mascotCol,MATCH(A124,bpiTeams,0)),A124," ",INDEX(mascotCol,MATCH(A124,bpiTeams,0))) -> #N/A | L124: =COUNTIF(bpiImportCol,J124) -> 0
A125: Long Beach State | B125: Long Beach St. | C125: =COUNTIF('Net Import'!B:B,B125) -> 1 | D125: Long Beach St. | E125: =COUNTIF('KenPom import'!B:B,D125) -> 1 | F125: Long Beach St. | G125: =IF(COUNTIF('Stats import'!E:E,F125)>1,1,0) -> 0 | H125: =H124+100 -> 12400 | I125: LBSU | J125: =CONCATENATE(A125," ",INDEX(mascotCol,MATCH(A125,bpiTeams,0)),I125) -> #N/A | K125: =CONCATENATE(A125," ",INDEX(mascotCol,MATCH(A125,bpiTeams,0)),A125," ",INDEX(mascotCol,MATCH(A125,bpiTeams,0))) -> #N/A | L125: =COUNTIF(bpiImportCol,J125) -> 0
A126: Yale | B126: =A126 -> Yale | C126: =COUNTIF('Net Import'!B:B,B126) -> 1 | D126: =A126 -> Yale | E126: =COUNTIF('KenPom import'!B:B,D126) -> 1 | F126: =A126 -> Yale | G126: =IF(COUNTIF('Stats import'!E:E,F126)>1,1,0) -> 1 | H126: =H125+100 -> 12500 | I126: YALE | J126: =CONCATENATE(A126," ",INDEX(mascotCol,MATCH(A126,bpiTeams,0)),I126) -> #N/A | K126: =CONCATENATE(A126," ",INDEX(mascotCol,MATCH(A126,bpiTeams,0)),A126," ",INDEX(mascotCol,MATCH(A126,bpiTeams,0))) -> #N/A | L126: =COUNTIF(bpiImportCol,J126) -> 0
A127: Brown | B127: =A127 -> Brown | C127: =COUNTIF('Net Import'!B:B,B127) -> 1 | D127: =A127 -> Brown | E127: =COUNTIF('KenPom import'!B:B,D127) -> 1 | F127: =A127 -> Brown | G127: =IF(COUNTIF('Stats import'!E:E,F127)>1,1,0) -> 0 | H127: =H126+100 -> 12600 | I127: BRWN | J127: =CONCATENATE(A127," ",INDEX(mascotCol,MATCH(A127,bpiTeams,0)),I127) -> #N/A | K127: =CONCATENATE(A127," ",INDEX(mascotCol,MATCH(A127,bpiTeams,0)),A127," ",INDEX(mascotCol,MATCH(A127,bpiTeams,0))) -> #N/A | L127: =COUNTIF(bpiImportCol,J127) -> 0
A128: UAB | B128: =A128 -> UAB | C128: =COUNTIF('Net Import'!B:B,B128) -> 1 | D128: =A128 -> UAB | E128: =COUNTIF('KenPom import'!B:B,D128) -> 1 | F128: =A128 -> UAB | G128: =IF(COUNTIF('Stats import'!E:E,F128)>1,1,0) -> 0 | H128: =H127+100 -> 12700 | I128: UAB | J128: =CONCATENATE(A128," ",INDEX(mascotCol,MATCH(A128,bpiTeams,0)),I128) -> #N/A | K128: =CONCATENATE(A128," ",INDEX(mascotCol,MATCH(A128,bpiTeams,0)),A128," ",INDEX(mascotCol,MATCH(A128,bpiTeams,0))) -> #N/A | L128: =COUNTIF(bpiImportCol,J128) -> 0
A129: Saint Peter's | B129: =A129 -> Saint Peter's | C129: =COUNTIF('Net Import'!B:B,B129) -> 1 | D129: =A129 -> Saint Peter's | E129: =COUNTIF('KenPom import'!B:B,D129) -> 1 | F129: =A129 -> Saint Peter's | G129: =IF(COUNTIF('Stats import'!E:E,F129)>1,1,0) -> 0 | H129: =H128+100 -> 12800 | I129: SPU | J129: =CONCATENATE(A129," ",INDEX(mascotCol,MATCH(A129,bpiTeams,0)),I129) -> #N/A | K129: =CONCATENATE(A129," ",INDEX(mascotCol,MATCH(A129,bpiTeams,0)),A129," ",INDEX(mascotCol,MATCH(A129,bpiTeams,0))) -> #N/A | L129: =COUNTIF(bpiImportCol,J129) -> 0
A130: Duquesne | B130: =A130 -> Duquesne | C130: =COUNTIF('Net Import'!B:B,B130) -> 1 | D130: =A130 -> Duquesne | E130: =COUNTIF('KenPom import'!B:B,D130) -> 1 | F130: =A130 -> Duquesne | G130: =IF(COUNTIF('Stats import'!E:E,F130)>1,1,0) -> 0 | H130: =H129+100 -> 12900 | I130: DUQ | J130: =CONCATENATE(A130," ",INDEX(mascotCol,MATCH(A130,bpiTeams,0)),I130) -> #N/A | K130: =CONCATENATE(A130," ",INDEX(mascotCol,MATCH(A130,bpiTeams,0)),A130," ",INDEX(mascotCol,MATCH(A130,bpiTeams,0))) -> #N/A | L130: =COUNTIF(bpiImportCol,J130) -> 0
A131: George Mason | B131: George Mason | C131: =COUNTIF('Net Import'!B:B,B131) -> 1 | D131: =A131 -> George Mason | E131: =COUNTIF('KenPom import'!B:B,D131) -> 1 | F131: =A131 -> George Mason | G131: =IF(COUNTIF('Stats import'!E:E,F131)>1,1,0) -> 0 | H131: =H130+100 -> 13000 | I131: GMU | J131: =CONCATENATE(A131," ",INDEX(mascotCol,MATCH(A131,bpiTeams,0)),I131) -> #N/A | K131: =CONCATENATE(A131," ",INDEX(mascotCol,MATCH(A131,bpiTeams,0)),A131," ",INDEX(mascotCol,MATCH(A131,bpiTeams,0))) -> #N/A | L131: =COUNTIF(bpiImportCol,J131) -> 0
A132: Louisville | B132: Louisville | C132: =COUNTIF('Net Import'!B:B,B132) -> 1 | D132: =A132 -> Louisville | E132: =COUNTIF('KenPom import'!B:B,D132) -> 1 | F132: =A132 -> Louisville | G132: =IF(COUNTIF('Stats import'!E:E,F132)>1,1,0) -> 1 | H132: =H131+100 -> 13100 | I132: LOU | J132: =CONCATENATE(A132," ",INDEX(mascotCol,MATCH(A132,bpiTeams,0)),I132) -> Louisville CardinalsLOU | K132: =CONCATENATE(A132," ",INDEX(mascotCol,MATCH(A132,bpiTeams,0)),A132," ",INDEX(mascotCol,MATCH(A132,bpiTeams,0))) -> Louisville CardinalsLouisville Cardinals | L132: =COUNTIF(bpiImportCol,J132) -> 1
A133: UMass Lowell | B133: UMass Lowell | C133: =COUNTIF('Net Import'!B:B,B133) -> 1 | D133: UMass Lowell | E133: =COUNTIF('KenPom import'!B:B,D133) -> 1 | F133: UMass Lowell | G133: =IF(COUNTIF('Stats import'!E:E,F133)>1,1,0) -> 0 | H133: =H132+100 -> 13200 | I133: UML | J133: =CONCATENATE(A133," ",INDEX(mascotCol,MATCH(A133,bpiTeams,0)),I133) -> #N/A | K133: =CONCATENATE(A133," ",INDEX(mascotCol,MATCH(A133,bpiTeams,0)),A133," ",INDEX(mascotCol,MATCH(A133,bpiTeams,0))) -> #N/A | L133: =COUNTIF(bpiImportCol,J133) -> 0
A134: West Virginia | B134: West Virginia | C134: =COUNTIF('Net Import'!B:B,B134) -> 1 | D134: =B134 -> West Virginia | E134: =COUNTIF('KenPom import'!B:B,D134) -> 1 | F134: =D134 -> West Virginia | G134: =IF(COUNTIF('Stats import'!E:E,F134)>1,1,0) -> 1 | H134: =H133+100 -> 13300 | I134: WVU | J134: =CONCATENATE(A134," ",INDEX(mascotCol,MATCH(A134,bpiTeams,0)),I134) -> West Virginia MountaineersWVU | K134: =CONCATENATE(A134," ",INDEX(mascotCol,MATCH(A134,bpiTeams,0)),A134," ",INDEX(mascotCol,MATCH(A134,bpiTeams,0))) -> West Virginia MountaineersWest Virginia Mountaineers | L134: =COUNTIF(bpiImportCol,J134) -> 1
A135: Kent State | B135: Kent St. | C135: =COUNTIF('Net Import'!B:B,B135) -> 1 | D135: Kent St. | E135: =COUNTIF('KenPom import'!B:B,D135) -> 1 | F135: =D135 -> Kent St. | G135: =IF(COUNTIF('Stats import'!E:E,F135)>1,1,0) -> 0 | H135: =H134+100 -> 13400 | I135: KENT | J135: =CONCATENATE(A135," ",INDEX(mascotCol,MATCH(A135,bpiTeams,0)),I135) -> #N/A | K135: =CONCATENATE(A135," ",INDEX(mascotCol,MATCH(A135,bpiTeams,0)),A135," ",INDEX(mascotCol,MATCH(A135,bpiTeams,0))) -> #N/A | L135: =COUNTIF(bpiImportCol,J135) -> 0
A136: Bradley | B136: Bradley | C136: =COUNTIF('Net Import'!B:B,B136) -> 1 | D136: Bradley | E136: =COUNTIF('KenPom import'!B:B,D136) -> 1 | F136: =D136 -> Bradley | G136: =IF(COUNTIF('Stats import'!E:E,F136)>1,1,0) -> 0 | H136: =H135+100 -> 13500 | I136: BRAD | J136: =CONCATENATE(A136," ",INDEX(mascotCol,MATCH(A136,bpiTeams,0)),I136) -> #N/A | K136: =CONCATENATE(A136," ",INDEX(mascotCol,MATCH(A136,bpiTeams,0)),A136," ",INDEX(mascotCol,MATCH(A136,bpiTeams,0))) -> #N/A | L136: =COUNTIF(bpiImportCol,J136) -> 0
A137: Murray State | B137: Murray St. | C137: =COUNTIF('Net Import'!B:B,B137) -> 1 | D137: Murray St. | E137: =COUNTIF('KenPom import'!B:B,D137) -> 1 | F137: =D137 -> Murray St. | G137: =IF(COUNTIF('Stats import'!E:E,F137)>1,1,0) -> 0 | H137: =H136+100 -> 13600 | I137: MUR | J137: =CONCATENATE(A137," ",INDEX(mascotCol,MATCH(A137,bpiTeams,0)),I137) -> #N/A | K137: =CONCATENATE(A137," ",INDEX(mascotCol,MATCH(A137,bpiTeams,0)),A137," ",INDEX(mascotCol,MATCH(A137,bpiTeams,0))) -> #N/A | L137: =COUNTIF(bpiImportCol,J137) -> 0
A138: Central Connecticut | B138: Central Conn. St. | C138: =COUNTIF('Net Import'!B:B,B138) -> 1 | D138: Central Connecticut | E138: =COUNTIF('KenPom import'!B:B,D138) -> 1 | F138: Central Conn. St. | G138: =IF(COUNTIF('Stats import'!E:E,F138)>1,1,0) -> 0 | H138: =H137+100 -> 13700 | I138: CCSU | J138: =CONCATENATE(A138," ",INDEX(mascotCol,MATCH(A138,bpiTeams,0)),I138) -> #N/A | K138: =CONCATENATE(A138," ",INDEX(mascotCol,MATCH(A138,bpiTeams,0)),A138," ",INDEX(mascotCol,MATCH(A138,bpiTeams,0))) -> #N/A | L138: =COUNTIF(bpiImportCol,J138) -> 0
A139: Little Rock | B139: =A139 -> Little Rock | C139: =COUNTIF('Net Import'!B:B,B139) -> 1 | D139: =A139 -> Little Rock | E139: =COUNTIF('KenPom import'!B:B,D139) -> 1 | F139: =A139 -> Little Rock | G139: =IF(COUNTIF('Stats import'!E:E,F139)>1,1,0) -> 0 | H139: =H138+100 -> 13800 | I139: LR | J139: =CONCATENATE(A139," ",INDEX(mascotCol,MATCH(A139,bpiTeams,0)),I139) -> #N/A | K139: =CONCATENATE(A139," ",INDEX(mascotCol,MATCH(A139,bpiTeams,0)),A139," ",INDEX(mascotCol,MATCH(A139,bpiTeams,0))) -> #N/A | L139: =COUNTIF(bpiImportCol,J139) -> 0
A140: Georgia | B140: =A140 -> Georgia | C140: =COUNTIF('Net Import'!B:B,B140) -> 1 | D140: =A140 -> Georgia | E140: =COUNTIF('KenPom import'!B:B,D140) -> 1 | F140: =A140 -> Georgia | G140: =IF(COUNTIF('Stats import'!E:E,F140)>1,1,0) -> 1 | H140: =H139+100 -> 13900 | I140: UGA | J140: =CONCATENATE(A140," ",INDEX(mascotCol,MATCH(A140,bpiTeams,0)),I140) -> Georgia BulldogsUGA | K140: =CONCATENATE(A140," ",INDEX(mascotCol,MATCH(A140,bpiTeams,0)),A140," ",INDEX(mascotCol,MATCH(A140,bpiTeams,0))) -> Georgia BulldogsGeorgia Bulldogs | L140: =COUNTIF(bpiImportCol,J140) -> 1
A141: LSU | B141: =A141 -> LSU | C141: =COUNTIF('Net Import'!B:B,B141) -> 1 | D141: =A141 -> LSU | E141: =COUNTIF('KenPom import'!B:B,D141) -> 1 | F141: =A141 -> LSU | G141: =IF(COUNTIF('Stats import'!E:E,F141)>1,1,0) -> 0 | H141: =H140+100 -> 14000 | I141: LSU | J141: =CONCATENATE(A141," ",INDEX(mascotCol,MATCH(A141,bpiTeams,0)),I141) -> #N/A | K141: =CONCATENATE(A141," ",INDEX(mascotCol,MATCH(A141,bpiTeams,0)),A141," ",INDEX(mascotCol,MATCH(A141,bpiTeams,0))) -> #N/A | L141: =COUNTIF(bpiImportCol,J141) -> 0
A142: Missouri | B142: =A142 -> Missouri | C142: =COUNTIF('Net Import'!B:B,B142) -> 1 | D142: =A142 -> Missouri | E142: =COUNTIF('KenPom import'!B:B,D142) -> 1 | F142: =A142 -> Missouri | G142: =IF(COUNTIF('Stats import'!E:E,F142)>1,1,0) -> 1 | H142: =H141+100 -> 14100 | I142: MIZ | J142: =CONCATENATE(A142," ",INDEX(mascotCol,MATCH(A142,bpiTeams,0)),I142) -> Missouri TigersMIZ | K142: =CONCATENATE(A142," ",INDEX(mascotCol,MATCH(A142,bpiTeams,0)),A142," ",INDEX(mascotCol,MATCH(A142,bpiTeams,0))) -> Missouri TigersMissouri Tigers | L142: =COUNTIF(bpiImportCol,J142) -> 1
A143: Arkansas State | B143: Arkansas St. | C143: =COUNTIF('Net Import'!B:B,B143) -> 1 | D143: Arkansas St. | E143: =COUNTIF('KenPom import'!B:B,D143) -> 1 | F143: Arkansas St. | G143: =IF(COUNTIF('Stats import'!E:E,F143)>1,1,0) -> 0 | H143: =H142+100 -> 14200 | I143: ARST | J143: =CONCATENATE(A143," ",INDEX(mascotCol,MATCH(A143,bpiTeams,0)),I143) -> #N/A | K143: =CONCATENATE(A143," ",INDEX(mascotCol,MATCH(A143,bpiTeams,0)),A143," ",INDEX(mascotCol,MATCH(A143,bpiTeams,0))) -> #N/A | L143: =COUNTIF(bpiImportCol,J143) -> 0
A144: Penn State | B144: Penn St. | C144: =COUNTIF('Net Import'!B:B,B144) -> 1 | D144: Penn St. | E144: =COUNTIF('KenPom import'!B:B,D144) -> 1 | F144: Penn St. | G144: =IF(COUNTIF('Stats import'!E:E,F144)>1,1,0) -> 0 | H144: =H143+100 -> 14300 | I144: PSU | J144: =CONCATENATE(A144," ",INDEX(mascotCol,MATCH(A144,bpiTeams,0)),I144) -> #N/A | K144: =CONCATENATE(A144," ",INDEX(mascotCol,MATCH(A144,bpiTeams,0)),A144," ",INDEX(mascotCol,MATCH(A144,bpiTeams,0))) -> #N/A | L144: =COUNTIF(bpiImportCol,J144) -> 0
A145: Vanderbilt | B145: =A145 -> Vanderbilt | C145: =COUNTIF('Net Import'!B:B,B145) -> 1 | D145: =A145 -> Vanderbilt | E145: =COUNTIF('KenPom import'!B:B,D145) -> 1 | F145: =A145 -> Vanderbilt | G145: =IF(COUNTIF('Stats import'!E:E,F145)>1,1,0) -> 1 | H145: =H144+100 -> 14400 | I145: VAN | J145: =CONCATENATE(A145," ",INDEX(mascotCol,MATCH(A145,bpiTeams,0)),I145) -> Vanderbilt CommodoresVAN | K145: =CONCATENATE(A145," ",INDEX(mascotCol,MATCH(A145,bpiTeams,0)),A145," ",INDEX(mascotCol,MATCH(A145,bpiTeams,0))) -> Vanderbilt CommodoresVanderbilt Commodores | L145: =COUNTIF(bpiImportCol,J145) -> 1
A146: Arizona State | B146: Arizona St. | C146: =COUNTIF('Net Import'!B:B,B146) -> 1 | D146: Arizona St. | E146: =COUNTIF('KenPom import'!B:B,D146) -> 1 | F146: =D146 -> Arizona St. | G146: =IF(COUNTIF('Stats import'!E:E,F146)>1,1,0) -> 0 | H146: =H145+100 -> 14500 | I146: ASU | J146: =CONCATENATE(A146," ",INDEX(mascotCol,MATCH(A146,bpiTeams,0)),I146) -> #N/A | K146: =CONCATENATE(A146," ",INDEX(mascotCol,MATCH(A146,bpiTeams,0)),A146," ",INDEX(mascotCol,MATCH(A146,bpiTeams,0))) -> #N/A | L146: =COUNTIF(bpiImportCol,J146) -> 0
A147: North Texas | B147: =A147 -> North Texas | C147: =COUNTIF('Net Import'!B:B,B147) -> 1 | D147: =A147 -> North Texas | E147: =COUNTIF('KenPom import'!B:B,D147) -> 1 | F147: =A147 -> North Texas | G147: =IF(COUNTIF('Stats import'!E:E,F147)>1,1,0) -> 0 | H147: =H146+100 -> 14600 | I147: UNT | J147: =CONCATENATE(A147," ",INDEX(mascotCol,MATCH(A147,bpiTeams,0)),I147) -> #N/A | K147: =CONCATENATE(A147," ",INDEX(mascotCol,MATCH(A147,bpiTeams,0)),A147," ",INDEX(mascotCol,MATCH(A147,bpiTeams,0))) -> #N/A | L147: =COUNTIF(bpiImportCol,J147) -> 0
A148: Milwaukee | B148: =A148 -> Milwaukee | C148: =COUNTIF('Net Import'!B:B,B148) -> 1 | D148: =A148 -> Milwaukee | E148: =COUNTIF('KenPom import'!B:B,D148) -> 1 | F148: =A148 -> Milwaukee | G148: =IF(COUNTIF('Stats import'!E:E,F148)>1,1,0) -> 0 | H148: =H147+100 -> 14700 | I148: MILW | J148: =CONCATENATE(A148," ",INDEX(mascotCol,MATCH(A148,bpiTeams,0)),I148) -> #N/A | K148: =CONCATENATE(A148," ",INDEX(mascotCol,MATCH(A148,bpiTeams,0)),A148," ",INDEX(mascotCol,MATCH(A148,bpiTeams,0))) -> #N/A | L148: =COUNTIF(bpiImportCol,J148) -> 0
A149: Northern Colorado | B149: Northern Colo. | C149: =COUNTIF('Net Import'!B:B,B149) -> 1 | D149: =A149 -> Northern Colorado | E149: =COUNTIF('KenPom import'!B:B,D149) -> 1 | F149: Northern Colo. | G149: =IF(COUNTIF('Stats import'!E:E,F149)>1,1,0) -> 0 | H149: =H148+100 -> 14800 | I149: UNCO | J149: =CONCATENATE(A149," ",INDEX(mascotCol,MATCH(A149,bpiTeams,0)),I149) -> #N/A | K149: =CONCATENATE(A149," ",INDEX(mascotCol,MATCH(A149,bpiTeams,0)),A149," ",INDEX(mascotCol,MATCH(A149,bpiTeams,0))) -> #N/A | L149: =COUNTIF(bpiImportCol,J149) -> 0
A150: Bryant | B150: =A150 -> Bryant | C150: =COUNTIF('Net Import'!B:B,B150) -> 1 | D150: =A150 -> Bryant | E150: =COUNTIF('KenPom import'!B:B,D150) -> 1 | F150: =A150 -> Bryant | G150: =IF(COUNTIF('Stats import'!E:E,F150)>1,1,0) -> 0 | H150: =H149+100 -> 14900 | I150: BRY | J150: =CONCATENATE(A150," ",INDEX(mascotCol,MATCH(A150,bpiTeams,0)),I150) -> #N/A | K150: =CONCATENATE(A150," ",INDEX(mascotCol,MATCH(A150,bpiTeams,0)),A150," ",INDEX(mascotCol,MATCH(A150,bpiTeams,0))) -> #N/A | L150: =COUNTIF(bpiImportCol,J150) -> 0
A151: UC San Diego | B151: =A151 -> UC San Diego | C151: =COUNTIF('Net Import'!B:B,B151) -> 1 | D151: =A151 -> UC San Diego | E151: =COUNTIF('KenPom import'!B:B,D151) -> 1 | F151: UC San Diego | G151: =IF(COUNTIF('Stats import'!E:E,F151)>1,1,0) -> 0 | H151: =H150+100 -> 15000 | I151: UCSD | J151: =CONCATENATE(A151," ",INDEX(mascotCol,MATCH(A151,bpiTeams,0)),I151) -> #N/A | K151: =CONCATENATE(A151," ",INDEX(mascotCol,MATCH(A151,bpiTeams,0)),A151," ",INDEX(mascotCol,MATCH(A151,bpiTeams,0))) -> #N/A | L151: =COUNTIF(bpiImportCol,J151) -> 0
A152: Robert Morris | B152: =A152 -> Robert Morris | C152: =COUNTIF('Net Import'!B:B,B152) -> 1 | D152: =A152 -> Robert Morris | E152: =COUNTIF('KenPom import'!B:B,D152) -> 1 | F152: =D152 -> Robert Morris | G152: =IF(COUNTIF('Stats import'!E:E,F152)>1,1,0) -> 1 | H152: =H151+100 -> 15100 | I152: RMU | J152: =CONCATENATE(A152," ",INDEX(mascotCol,MATCH(A152,bpiTeams,0)),I152) -> #N/A | K152: =CONCATENATE(A152," ",INDEX(mascotCol,MATCH(A152,bpiTeams,0)),A152," ",INDEX(mascotCol,MATCH(A152,bpiTeams,0))) -> #N/A | L152: =COUNTIF(bpiImportCol,J152) -> 0
A153: Southeast Missouri | B153: Southeast Mo. St. | C153: =COUNTIF('Net Import'!B:B,B153) -> 1 | D153: =A153 -> Southeast Missouri | E153: =COUNTIF('KenPom import'!B:B,D153) -> 1 | F153: =B153 -> Southeast Mo. St. | G153: =IF(COUNTIF('Stats import'!E:E,F153)>1,1,0) -> 0 | H153: =H152+100 -> 15200 | I153: SEMO | J153: =CONCATENATE(A153," ",INDEX(mascotCol,MATCH(A153,bpiTeams,0)),I153) -> #N/A | K153: =CONCATENATE(A153," ",INDEX(mascotCol,MATCH(A153,bpiTeams,0)),A153," ",INDEX(mascotCol,MATCH(A153,bpiTeams,0))) -> #N/A | L153: =COUNTIF(bpiImportCol,J153) -> 0
A154: Omaha | B154: Omaha | C154: =COUNTIF('Net Import'!B:B,B154) -> 1 | D154: Nebraska Omaha | E154: =COUNTIF('KenPom import'!B:B,D154) -> 1 | F154: =B154 -> Omaha | G154: =IF(COUNTIF('Stats import'!E:E,F154)>1,1,0) -> 0 | H154: =H153+100 -> 15300 | I154: OMA | J154: =CONCATENATE(A154," ",INDEX(mascotCol,MATCH(A154,bpiTeams,0)),I154) -> #N/A | K154: =CONCATENATE(A154," ",INDEX(mascotCol,MATCH(A154,bpiTeams,0)),A154," ",INDEX(mascotCol,MATCH(A154,bpiTeams,0))) -> #N/A | L154: =COUNTIF(bpiImportCol,J154) -> 0
A155: SIU Edwardsville | B155: SIUE | C155: =COUNTIF('Net Import'!B:B,B155) -> 1 | D155: SIUE | E155: =COUNTIF('KenPom import'!B:B,D155) -> 1 | F155: =B155 -> SIUE | G155: =IF(COUNTIF('Stats import'!E:E,F155)>1,1,0) -> 0 | H155: =H154+100 -> 15400 | I155: SIUE | J155: =CONCATENATE(A155," ",INDEX(mascotCol,MATCH(A155,bpiTeams,0)),I155) -> #N/A | K155: =CONCATENATE(A155," ",INDEX(mascotCol,MATCH(A155,bpiTeams,0)),A155," ",INDEX(mascotCol,MATCH(A155,bpiTeams,0))) -> #N/A | L155: =COUNTIF(bpiImportCol,J155) -> 0
A156: Chattanooga | B156: =A156 -> Chattanooga | C156: =COUNTIF('Net Import'!B:B,B156) -> 1 | D156: =A156 -> Chattanooga | E156: =COUNTIF('KenPom import'!B:B,D156) -> 1 | F156: =D156 -> Chattanooga | G156: =IF(COUNTIF('Stats import'!E:E,F156)>1,1,0) -> 0 | H156: =H155+100 -> 15500 | I156: UTC | J156: =CONCATENATE(A156," ",INDEX(mascotCol,MATCH(A156,bpiTeams,0)),I156) -> #N/A | K156: =CONCATENATE(A156," ",INDEX(mascotCol,MATCH(A156,bpiTeams,0)),A156," ",INDEX(mascotCol,MATCH(A156,bpiTeams,0))) -> #N/A | L156: =COUNTIF(bpiImportCol,J156) -> 0
A157: American | B157: =A157 -> American | C157: =COUNTIF('Net Import'!B:B,B157) -> 1 | D157: =A157 -> American | E157: =COUNTIF('KenPom import'!B:B,D157) -> 1 | F157: =D157 -> American | G157: =IF(COUNTIF('Stats import'!E:E,F157)>1,1,0) -> 0 | H157: =H156+100 -> 15600 | I157: AMER | J157: =CONCATENATE(A157," ",INDEX(mascotCol,MATCH(A157,bpiTeams,0)),I157) -> #N/A | K157: =CONCATENATE(A157," ",INDEX(mascotCol,MATCH(A157,bpiTeams,0)),A157," ",INDEX(mascotCol,MATCH(A157,bpiTeams,0))) -> #N/A | L157: =COUNTIF(bpiImportCol,J157) -> 0
A158: Troy | B158: =A158 -> Troy | C158: =COUNTIF('Net Import'!B:B,B158) -> 1 | D158: =A158 -> Troy | E158: =COUNTIF('KenPom import'!B:B,D158) -> 1 | F158: =D158 -> Troy | G158: =IF(COUNTIF('Stats import'!E:E,F158)>1,1,0) -> 1 | H158: =H157+100 -> 15700 | I158: TROY | J158: =CONCATENATE(A158," ",INDEX(mascotCol,MATCH(A158,bpiTeams,0)),I158) -> Troy TrojansTROY | K158: =CONCATENATE(A158," ",INDEX(mascotCol,MATCH(A158,bpiTeams,0)),A158," ",INDEX(mascotCol,MATCH(A158,bpiTeams,0))) -> Troy TrojansTroy Trojans | L158: =COUNTIF(bpiImportCol,J158) -> 1
A159: Wofford | B159: =A159 -> Wofford | C159: =COUNTIF('Net Import'!B:B,B159) -> 1 | D159: =A159 -> Wofford | E159: =COUNTIF('KenPom import'!B:B,D159) -> 1 | F159: =D159 -> Wofford | G159: =IF(COUNTIF('Stats import'!E:E,F159)>1,1,0) -> 0 | H159: =H158+100 -> 15800 | I159: WOF | J159: =CONCATENATE(A159," ",INDEX(mascotCol,MATCH(A159,bpiTeams,0)),I159) -> #N/A | K159: =CONCATENATE(A159," ",INDEX(mascotCol,MATCH(A159,bpiTeams,0)),A159," ",INDEX(mascotCol,MATCH(A159,bpiTeams,0))) -> #N/A | L159: =COUNTIF(bpiImportCol,J159) -> 0
A160: St. Francis (PA) | B160: Saint Francis | C160: =COUNTIF('Net Import'!B:B,B160) -> 1 | D160: Saint Francis | E160: =COUNTIF('KenPom import'!B:B,D160) -> 1 | F160: Saint Francis | G160: =IF(COUNTIF('Stats import'!E:E,F160)>1,1,0) -> 0 | H160: =H159+100 -> 15900 | I160: SFPA | J160: =CONCATENATE(A160," ",INDEX(mascotCol,MATCH(A160,bpiTeams,0)),I160) -> #N/A | K160: =CONCATENATE(A160," ",INDEX(mascotCol,MATCH(A160,bpiTeams,0)),A160," ",INDEX(mascotCol,MATCH(A160,bpiTeams,0))) -> #N/A | L160: =COUNTIF(bpiImportCol,J160) -> 0
A161: Jackson State | B161: Jackson St. | C161: =COUNTIF('Net Import'!B:B,B161) -> 1 | D161: Jackson St. | E161: =COUNTIF('KenPom import'!B:B,D161) -> 1 | F161: Jackson St. | G161: =IF(COUNTIF('Stats import'!E:E,F161)>1,1,0) -> 0 | H161: =H160+100 -> 16000 | I161: JKST | J161: =CONCATENATE(A161," ",INDEX(mascotCol,MATCH(A161,bpiTeams,0)),I161) -> #N/A | K161: =CONCATENATE(A161," ",INDEX(mascotCol,MATCH(A161,bpiTeams,0)),A161," ",INDEX(mascotCol,MATCH(A161,bpiTeams,0))) -> #N/A | L161: =COUNTIF(bpiImportCol,J161) -> 0
A162: Mount St. Mary's | B162: Mount St. Mary's | C162: =COUNTIF('Net Import'!B:B,B162) -> 1 | D162: Mount St. Mary's | E162: =COUNTIF('KenPom import'!B:B,D162) -> 1 | F162: Mount St. Mary's | G162: =IF(COUNTIF('Stats import'!E:E,F162)>1,1,0) -> 0 | H162: =H161+100 -> 16100 | I162: MSM | J162: =CONCATENATE(A162," ",INDEX(mascotCol,MATCH(A162,bpiTeams,0)),I162) -> #N/A | K162: =CONCATENATE(A162," ",INDEX(mascotCol,MATCH(A162,bpiTeams,0)),A162," ",INDEX(mascotCol,MATCH(A162,bpiTeams,0))) -> #N/A | L162: =COUNTIF(bpiImportCol,J162) -> 0
A163: Alabama State | B163: Alabama St. | C163: =COUNTIF('Net Import'!B:B,B163) -> 1 | D163: Alabama St. | E163: =COUNTIF('KenPom import'!B:B,D163) -> 1 | F163: Alabama St. | G163: =IF(COUNTIF('Stats import'!E:E,F163)>1,1,0) -> 0 | H163: =H162+100 -> 16200 | I163: ALST | J163: =CONCATENATE(A163," ",INDEX(mascotCol,MATCH(A163,bpiTeams,0)),I163) -> #N/A | K163: =CONCATENATE(A163," ",INDEX(mascotCol,MATCH(A163,bpiTeams,0)),A163," ",INDEX(mascotCol,MATCH(A163,bpiTeams,0))) -> #N/A | L163: =COUNTIF(bpiImportCol,J163) -> 0
A164: Saint Louis | B164: =A164 -> Saint Louis | C164: =COUNTIF('Net Import'!B:B,B164) -> 1 | D164: =A164 -> Saint Louis | E164: =COUNTIF('KenPom import'!B:B,D164) -> 1 | F164: =A164 -> Saint Louis | G164: =IF(COUNTIF('Stats import'!E:E,F164)>1,1,0) -> 1 | H164: =H163+100 -> 16300 | I164: SLU | J164: =CONCATENATE(A164," ",INDEX(mascotCol,MATCH(A164,bpiTeams,0)),I164) -> Saint Louis BillikensSLU | K164: =CONCATENATE(A164," ",INDEX(mascotCol,MATCH(A164,bpiTeams,0)),A164," ",INDEX(mascotCol,MATCH(A164,bpiTeams,0))) -> Saint Louis BillikensSaint Louis Billikens | L164: =COUNTIF(bpiImportCol,J164) -> 1
A165: Notre Dame | B165: =A165 -> Notre Dame | C165: =COUNTIF('Net Import'!B:B,B165) -> 1 | D165: =A165 -> Notre Dame | E165: =COUNTIF('KenPom import'!B:B,D165) -> 1 | F165: =A165 -> Notre Dame | G165: =IF(COUNTIF('Stats import'!E:E,F165)>1,1,0) -> 0 | H165: =H164+100 -> 16400 | I165: ND | J165: =CONCATENATE(A165," ",INDEX(mascotCol,MATCH(A165,bpiTeams,0)),I165) -> #N/A | K165: =CONCATENATE(A165," ",INDEX(mascotCol,MATCH(A165,bpiTeams,0)),A165," ",INDEX(mascotCol,MATCH(A165,bpiTeams,0))) -> #N/A | L165: =COUNTIF(bpiImportCol,J165) -> 0
A166: Wright State | B166: Wright St. | C166: =COUNTIF('Net Import'!B:B,B166) -> 1 | D166: Wright St. | E166: =COUNTIF('KenPom import'!B:B,D166) -> 1 | F166: =D166 -> Wright St. | G166: =IF(COUNTIF('Stats import'!E:E,F166)>1,1,0) -> 1 | H166: =H165+100 -> 16500 | I166: WRST | J166: =CONCATENATE(A166," ",INDEX(mascotCol,MATCH(A166,bpiTeams,0)),I166) -> Wright State RaidersWRST | K166: =CONCATENATE(A166," ",INDEX(mascotCol,MATCH(A166,bpiTeams,0)),A166," ",INDEX(mascotCol,MATCH(A166,bpiTeams,0))) -> Wright State RaidersWright State Raiders | L166: =COUNTIF(bpiImportCol,J166) -> 1
A167: Northern Iowa | B167: UNI | C167: =COUNTIF('Net Import'!B:B,B167) -> 1 | D167: =A167 -> Northern Iowa | E167: =COUNTIF('KenPom import'!B:B,D167) -> 1 | F167: UNI | G167: =IF(COUNTIF('Stats import'!E:E,F167)>1,1,0) -> 1 | H167: =H166+100 -> 16600 | I167: UNI | J167: =CONCATENATE(A167," ",INDEX(mascotCol,MATCH(A167,bpiTeams,0)),I167) -> Northern Iowa PanthersUNI | K167: =CONCATENATE(A167," ",INDEX(mascotCol,MATCH(A167,bpiTeams,0)),A167," ",INDEX(mascotCol,MATCH(A167,bpiTeams,0))) -> Northern Iowa PanthersNorthern Iowa Panthers | L167: =COUNTIF(bpiImportCol,J167) -> 1
A168: Lindenwood | B168: =A168 -> Lindenwood | C168: =COUNTIF('Net Import'!B:B,B168) -> 1 | D168: =A168 -> Lindenwood | E168: =COUNTIF('KenPom import'!B:B,D168) -> 1 | F168: =A168 -> Lindenwood | G168: =IF(COUNTIF('Stats import'!E:E,F168)>1,1,0) -> 0 | H168: =H167+100 -> 16700 | I168: LIN | J168: =CONCATENATE(A168," ",INDEX(mascotCol,MATCH(A168,bpiTeams,0)),I168) -> #N/A | K168: =CONCATENATE(A168," ",INDEX(mascotCol,MATCH(A168,bpiTeams,0)),A168," ",INDEX(mascotCol,MATCH(A168,bpiTeams,0))) -> #N/A | L168: =COUNTIF(bpiImportCol,J168) -> 0
A169: ETSU | B169: =A169 -> ETSU | C169: =COUNTIF('Net Import'!B:B,B169) -> 1 | D169: East Tennessee St. | E169: =COUNTIF('KenPom import'!B:B,D169) -> 1 | F169: =A169 -> ETSU | G169: =IF(COUNTIF('Stats import'!E:E,F169)>1,1,0) -> 0 | H169: =H168+100 -> 16800 | I169: ETSU | J169: East Tennessee State BuccaneersETSU | K169: East Tennessee State BuccaneersEast Tennessee State Buccaneers | L169: =COUNTIF(bpiImportCol,J169) -> 1
A170: North Dakota State | B170: North Dakota St. | C170: =COUNTIF('Net Import'!B:B,B170) -> 1 | D170: =B170 -> North Dakota St. | E170: =COUNTIF('KenPom import'!B:B,D170) -> 1 | F170: =D170 -> North Dakota St. | G170: =IF(COUNTIF('Stats import'!E:E,F170)>1,1,0) -> 1 | H170: =H169+100 -> 16900 | I170: NDSU | J170: =CONCATENATE(A170," ",INDEX(mascotCol,MATCH(A170,bpiTeams,0)),I170) -> North Dakota State BisonNDSU | K170: =CONCATENATE(A170," ",INDEX(mascotCol,MATCH(A170,bpiTeams,0)),A170," ",INDEX(mascotCol,MATCH(A170,bpiTeams,0))) -> North Dakota State BisonNorth Dakota State Bison | L170: =COUNTIF(bpiImportCol,J170) -> 1
A171: Utah Valley | B171: =A171 -> Utah Valley | C171: =COUNTIF('Net Import'!B:B,B171) -> 1 | D171: =B171 -> Utah Valley | E171: =COUNTIF('KenPom import'!B:B,D171) -> 1 | F171: =D171 -> Utah Valley | G171: =IF(COUNTIF('Stats import'!E:E,F171)>1,1,0) -> 1 | H171: =H170+100 -> 17000 | I171: UVU | J171: =CONCATENATE(A171," ",INDEX(mascotCol,MATCH(A171,bpiTeams,0)),I171) -> #N/A | K171: =CONCATENATE(A171," ",INDEX(mascotCol,MATCH(A171,bpiTeams,0)),A171," ",INDEX(mascotCol,MATCH(A171,bpiTeams,0))) -> #N/A | L171: =COUNTIF(bpiImportCol,J171) -> 0
A172: Oklahoma State | B172: Oklahoma St. | C172: =COUNTIF('Net Import'!B:B,B172) -> 1 | D172: =B172 -> Oklahoma St. | E172: =COUNTIF('KenPom import'!B:B,D172) -> 1 | F172: =D172 -> Oklahoma St. | G172: =IF(COUNTIF('Stats import'!E:E,F172)>1,1,0) -> 0 | H172: =H171+100 -> 17100 | I172: OKST | J172: =CONCATENATE(A172," ",INDEX(mascotCol,MATCH(A172,bpiTeams,0)),I172) -> #N/A | K172: =CONCATENATE(A172," ",INDEX(mascotCol,MATCH(A172,bpiTeams,0)),A172," ",INDEX(mascotCol,MATCH(A172,bpiTeams,0))) -> #N/A | L172: =COUNTIF(bpiImportCol,J172) -> 0
...

Sheet BPI+
A1: Rank* | B1: Conf* | C1: Team* | D1: Mascot* | E1: Seed* | F1: Conf* | G1: Next* | H1: BPI | I1: NET | J1: SOR | K1: AP* | L1: BKTLGY* | M1: OVR | N1: In 50 | O1: BPI Val | P1: KP Off | Q1: KP Def | R1: Res. | S1: L8 W | T1: L8 L | U1: QW | V1: QL | W1: TL | X1: FILL | Y1: RW | Z1: RW | AA1: RW | AB1: RW | AC1: RW | AD1: RW | AE1: RW | AF1: RW | AG1: RW | AH1: RW | AI1: RW | AJ1: RW | AK1: RL | AL1: RL | AM1: RL | AN1: RL | AO1: RL | AP1: RL | AQ1: RL | AR1: RL | AS1: RL | AT1: RL | AU1: RL | AV1: RL | AW1: QW | AX1: QW | AY1: QW | AZ1: QW | BA1: QW | BB1: QW | BC1: QW | BD1: QW | BE1: QW | BF1: QW | BG1: QW | BH1: QW | BI1: QW | BJ1: QW | BK1: QW | BL1: QL | BM1: QL | BN1: QL | BO1: QL | BP1: QL | BQ1: QL | BR1: QL | BS1: QL | BT1: QL | BU1: QL | BV1: QL | BW1: QL | BX1: QL | BY1: NL | BZ1: NL | CA1: NL | CB1: NL | CC1: NL | CD1: NL | CE1: NL | CF1: NL | CG1: NL | CH1: NL | CI1: NL | CJ1: NL | CK1: NL | CL1: NL | CM1: NL | CN1: NL | CO1: NL | CP1: NL | CQ1: NL | CR1: NL | CS1: NL | CT1: BSR | CU1: Part 1 | CV1: SoD | CW1: Part 2 | CX1: A:T | CY1: APG | CZ1: Bench | DA1: BPG | DB1: EFG% | DC1: FB | DD1: FG% | DE1: DFG% | DF1: FPG | DG1: FTA | DH1: FT% | DI1: FTPG | DJ1: RM | DK1: DRPG | DL1: ORPG | DM1: RPG | DN1: OPPG | DO1: SM | DP1: PPG | DQ1: SPG | DR1: 3PTA | DS1: 3PT% | DT1: 3PD% | DU1: 3PPG | DV1: TM | DW1: TOF | DX1: TPG | DY1: Blank | DZ1: Res | EA1: BPI | EB1: Tempo | EC1: A:T | ED1: APG | EE1: Bench | EF1: BPG | EG1: EFG% | EH1: FB | EI1: FG% | EJ1: DFG% | EK1: FPG | EL1: FTA | EM1: FT% | EN1: FTPG | EO1: RM | EP1: DRPG | EQ1: ORPG | ER1: RPG | ES1: OPPG | ET1: SM | EU1: PPG | EV1: SPG | EW1: 3PTA | EX1: 3PT% | EY1: 3PD% | EZ1: 3PPG | FA1: TM | FB1: TOF | FC1: TPG | FD1: Res | FE1: BPI | FF1: Tempo | FG1: 2PTA | FH1: %3PTA | GQ1: Up to: | GR1: 46093
A2: 1 | B2: Big 12 | C2: Arizona | D2: Wildcats | E2: 1 | F2: WIN | H2: =_xlfn.IFNA(INDEX(importBPIRkCol,MATCH(INDEX(espnMap,MATCH(C2,valCol,0)),bpiImportCol,0)+rowOffset),INDEX(importBPIRkCol,MATCH(INDEX(espnMap2,MATCH(C2,valCol,0)),bpiImportCol,0)+rowOffset)) -> 3 | I2: =IFERROR(INDEX('Net Import'!A:A,MATCH(INDEX(mapping!B:B,MATCH(C2,mapping!A:A,0),1),'Net Import'!B:B,0),1),0) -> 3 | J2: =_xlfn.IFNA(INDEX(sorRkCol,MATCH(INDEX(espnMap,MATCH(C2,valCol,0)),sorTeamCol,0)+sorRowOffset),INDEX(sorRkCol,MATCH(INDEX(espnMap2,MATCH(C2,valCol,0)),sorTeamCol,0)+sorRowOffset)) -> 1 | K2: 2 | L2: 1.5 | M2: =CW2+R2*1.8+IF(K2>0,K2-26,0)/2+IF(CV2>0.5,0,10)-0.5*O2-IF(F2="WIN",1,IF(F2="IN",0.5,0))-S2+IF(W2>13.5,2,0)-IF(W2<6,6-W2,0) -> -73.058308 | N2: =IF(COUNTIF(H2:J2,"<50.5")>1.5,1,0) -> 1 | O2: =_xlfn.IFNA(INDEX(importBPICol,MATCH(INDEX(espnMap,MATCH(C2,valCol,0)),bpiImportCol,0)+rowOffset), INDEX(importBPICol,MATCH(INDEX(espnMap2,MATCH(C2,valCol,0)),bpiImportCol,0)+rowOffset)) -> 23.7 | P2: =INDEX(kpOff,MATCH(INDEX(kpVal,MATCH(C2,valCol,0)),kpTeam,0)) -> 7 | Q2: =INDEX(kpDef,MATCH(INDEX(kpVal,MATCH(C2,valCol,0)),kpTeam,0)) -> 3 | R2: =-1*INDEX(calculatedResVal,MATCH(C2,resValueTeamCol,0)) -> -21.204615 | S2: 8 | T2: 0 | U2: =COUNTA(AW2:BK2)+COUNTA(Y2:AJ2) -> 18 | V2: =COUNTA(BL2:BX2)+COUNTA(AK2:AV2) -> 2 | W2: =COUNTA(AK2:AV2)+COUNTA(BL2:CS2) -> 2 | X2: =IF(SUM(S2:W2)>0,1,0) -> 1 | Y2: FLA | Z2: UCLA | AA2: CONN | AB2: AUB | AC2: ALA | AD2: BYU | AE2: BYU | AF2: HOU | AG2: KU | AH2: ISU | AI2: ISU | AJ2: HOU | AK2: KU | AL2: TTU | AW2: SDSU | AX2: TCU | AY2: UCF | AZ2: WVU | BA2: CIN | BB2: UCF | CT2: =H2*0.4+J2*1.2+I2*0.8 -> 4.8 | CU2: =CT2/2.4 -> 2 | CV2: =VLOOKUP(B2,'SODiv Index'!A:B,2,FALSE) -> 1 | CW2: =CU2*(10-CV2/5)/10 -> 1.96 | CX2: =INDEX('Stats import'!H:H,MATCH((INDEX(mapping!R:R,MATCH(INDEX(statsCategories,1,1),mapping!P:P,0),1)+INDEX(mapping!H:H,MATCH(C2,mapping!A:A,0),1)),'Stats import'!B:B,0),1) -> 1.57 | CY2: =INDEX('Stats import'!H:H,MATCH((INDEX(mapping!R:R,MATCH(INDEX(statsCategories,1,2),mapping!P:P,0),1)+INDEX(mapping!H:H,MATCH(C2,mapping!A:A,0),1)),'Stats import'!B:B,0),1) -> 16.9 | CZ2: =INDEX('Stats import'!H:H,MATCH((INDEX(mapping!R:R,MATCH(INDEX(statsCategories,1,3),mapping!P:P,0),1)+INDEX(mapping!H:H,MATCH(C2,mapping!A:A,0),1)),'Stats import'!B:B,0),1) -> 23.32 | DA2: =INDEX('Stats import'!H:H,MATCH((INDEX(mapping!R:R,MATCH(INDEX(statsCategories,1,4),mapping!P:P,0),1)+INDEX(mapping!H:H,MATCH(C2,mapping!A:A,0),1)),'Stats import'!B:B,0),1) -> 4.2 | DB2: =INDEX('Stats import'!H:H,MATCH((INDEX(mapping!R:R,MATCH(INDEX(statsCategories,1,5),mapping!P:P,0),1)+INDEX(mapping!H:H,MATCH(C2,mapping!A:A,0),1)),'Stats import'!B:B,0),1) -> 0.551 | DC2: =INDEX('Stats import'!H:H,MATCH((INDEX(mapping!R:R,MATCH(INDEX(statsCategories,1,6),mapping!P:P,0),1)+INDEX(mapping!H:H,MATCH(C2,mapping!A:A,0),1)),'Stats import'!B:B,0),1) -> 15.53 | DD2: =INDEX('Stats import'!H:H,MATCH((INDEX(mapping!R:R,MATCH(INDEX(statsCategories,1,7),mapping!P:P,0),1)+INDEX(mapping!H:H,MATCH(C2,mapping!A:A,0),1)),'Stats import'!B:B,0),1) -> 50.2 | DE2: =INDEX('Stats import'!H:H,MATCH((INDEX(mapping!R:R,MATCH(INDEX(statsCategories,1,8),mapping!P:P,0),1)+INDEX(mapping!H:H,MATCH(C2,mapping!A:A,0),1)),'Stats import'!B:B,0),1) -> 39.2 | DF2: =INDEX('Stats import'!H:H,MATCH((INDEX(mapping!R:R,MATCH(INDEX(statsCategories,1,9),mapping!P:P,0),1)+INDEX(mapping!H:H,MATCH(C2,mapping!A:A,0),1)),'Stats import'!B:B,0),1) -> 16 | DG2: =INDEX('Stats import'!H:H,MATCH((INDEX(mapping!R:R,MATCH(INDEX(statsCategories,1,10),mapping!P:P,0),1)+INDEX(mapping!H:H,MATCH(C2,mapping!A:A,0),1)),'Stats import'!B:B,0),1) -> 26.1 | DH2: =INDEX('Stats import'!H:H,MATCH((INDEX(mapping!R:R,MATCH(INDEX(statsCategories,1,11),mapping!P:P,0),1)+INDEX(mapping!H:H,MATCH(C2,mapping!A:A,0),1)),'Stats import'!B:B,0),1) -> 73.4 | DI2: =INDEX('Stats import'!H:H,MATCH((INDEX(mapping!R:R,MATCH(INDEX(statsCategories,1,12),mapping!P:P,0),1)+INDEX(mapping!H:H,MATCH(C2,mapping!A:A,0),1)),'Stats import'!B:B,0),1) -> 19.1 | DJ2: =INDEX('Stats import'!H:H,MATCH((INDEX(mapping!R:R,MATCH(INDEX(statsCategories,1,13),mapping!P:P,0),1)+INDEX(mapping!H:H,MATCH(C2,mapping!A:A,0),1)),'Stats import'!B:B,0),1) -> 10.8 | DK2: =INDEX('Stats import'!H:H,MATCH((INDEX(mapping!R:R,MATCH(INDEX(statsCategories,1,14),mapping!P:P,0),1)+INDEX(mapping!H:H,MATCH(C2,mapping!A:A,0),1)),'Stats import'!B:B,0),1) -> 29.76 | DL2: =INDEX('Stats import'!H:H,MATCH((INDEX(mapping!R:R,MATCH(INDEX(statsCategories,1,15),mapping!P:P,0),1)+INDEX(mapping!H:H,MATCH(C2,mapping!A:A,0),1)),'Stats import'!B:B,0),1) -> 12.76 | DM2: =INDEX('Stats import'!H:H,MATCH((INDEX(mapping!R:R,MATCH(INDEX(statsCategories,1,16),mapping!P:P,0),1)+INDEX(mapping!H:H,MATCH(C2,mapping!A:A,0),1)),'Stats import'!B:B,0),1) -> 42.53 | DN2: =INDEX('Stats import'!H:H,MATCH((INDEX(mapping!R:R,MATCH(INDEX(statsCategories,1,17),mapping!P:P,0),1)+INDEX(mapping!H:H,MATCH(C2,mapping!A:A,0),1)),'Stats import'!B:B,0),1) -> 68.8 | DO2: =INDEX('Stats import'!H:H,MATCH((INDEX(mapping!R:R,MATCH(INDEX(statsCategories,1,18),mapping!P:P,0),1)+INDEX(mapping!H:H,MATCH(C2,mapping!A:A,0),1)),'Stats import'!B:B,0),1) -> 17.4 | DP2: =INDEX('Stats import'!H:H,MATCH((INDEX(mapping!R:R,MATCH(INDEX(statsCategories,1,19),mapping!P:P,0),1)+INDEX(mapping!H:H,MATCH(C2,mapping!A:A,0),1)),'Stats import'!B:B,0),1) -> 86.1 | DQ2: =INDEX('Stats import'!H:H,MATCH((INDEX(mapping!R:R,MATCH(INDEX(statsCategories,1,20),mapping!P:P,0),1)+INDEX(mapping!H:H,MATCH(C2,mapping!A:A,0),1)),'Stats import'!B:B,0),1) -> 7.8 | DR2: =INDEX('Stats import'!H:H,MATCH((INDEX(mapping!R:R,MATCH(INDEX(statsCategories,1,21),mapping!P:P,0),1)+INDEX(mapping!H:H,MATCH(C2,mapping!A:A,0),1)),'Stats import'!B:B,0),1) -> 16.3 | DS2: =INDEX('Stats import'!H:H,MATCH((INDEX(mapping!R:R,MATCH(INDEX(statsCategories,1,22),mapping!P:P,0),1)+INDEX(mapping!H:H,MATCH(C2,mapping!A:A,0),1)),'Stats import'!B:B,0),1) -> 36 | DT2: =INDEX('Stats import'!H:H,MATCH((INDEX(mapping!R:R,MATCH(INDEX(statsCategories,1,23),mapping!P:P,0),1)+INDEX(mapping!H:H,MATCH(C2,mapping!A:A,0),1)),'Stats import'!B:B,0),1) -> 31.4 | DU2: =INDEX('Stats import'!H:H,MATCH((INDEX(mapping!R:R,MATCH(INDEX(statsCategories,1,24),mapping!P:P,0),1)+INDEX(mapping!H:H,MATCH(C2,mapping!A:A,0),1)),'Stats import'!B:B,0),1) -> 5.9 | DV2: =INDEX('Stats import'!H:H,MATCH((INDEX(mapping!R:R,MATCH(INDEX(statsCategories,1,25),mapping!P:P,0),1)+INDEX(mapping!H:H,MATCH(C2,mapping!A:A,0),1)),'Stats import'!B:B,0),1) -> 1.1 | DW2: =INDEX('Stats import'!H:H,MATCH((INDEX(mapping!R:R,MATCH(INDEX(statsCategories,1,26),mapping!P:P,0),1)+INDEX(mapping!H:H,MATCH(C2,mapping!A:A,0),1)),'Stats import'!B:B,0),1) -> 11.97 | DX2: =INDEX('Stats import'!H:H,MATCH((INDEX(mapping!R:R,MATCH(INDEX(statsCategories,1,27),mapping!P:P,0),1)+INDEX(mapping!H:H,MATCH(C2,mapping!A:A,0),1)),'Stats import'!B:B,0),1) -> 10.8 | DZ2: =R2 -> -21.204615 | EA2: =-O2 -> -23.7 | EB2: =INDEX('KenPom import'!J:J,MATCH(INDEX(kpVal,MATCH(C2,valCol,0)),kpTeam,0)) -> 70.1 | EC2: =(CX2-INDEX(FK:FK,4,1))/INDEX(FK:FK,3,1) -> 0.51975982 | ED2: =(CY2-INDEX(FL:FL,4,1))/INDEX(FL:FL,3,1) -> 0.80246063 | EE2: =(CZ2-INDEX(FM:FM,4,1))/INDEX(FM:FM,3,1) -> 0.25920915 | EF2: =(DA2-INDEX(FN:FN,4,1))/INDEX(FN:FN,3,1) -> 0.45710074 | EG2: =(DB2-INDEX(FO:FO,4,1))/INDEX(FO:FO,3,1) -> 0.41126913 | EH2: =(DC2-INDEX(FP:FP,4,1))/INDEX(FP:FP,3,1) -> 1.3167282 | EI2: =(DD2-INDEX(FQ:FQ,4,1))/INDEX(FQ:FQ,3,1) -> 1.6059508 | EJ2: =(DE2-INDEX(FR:FR,4,1))/INDEX(FR:FR,3,1)*-1 -> 1.6455587 | EK2: =(DF2-INDEX(FS:FS,4,1))/INDEX(FS:FS,3,1)*-1 -> 0.71319785 | EL2: =(DG2-INDEX(FT:FT,4,1))/INDEX(FT:FT,3,1) -> 1.6080803 | EM2: =(DH2-INDEX(FU:FU,4,1))/INDEX(FU:FU,3,1) -> -0.073142648 | EN2: =(DI2-INDEX(FV:FV,4,1))/INDEX(FV:FV,3,1) -> 1.4833657 | EO2: =(DJ2-INDEX(FW:FW,4,1))/INDEX(FW:FW,3,1) -> 1.9709141 | EP2: =(DK2-INDEX(FX:FX,4,1))/INDEX(FX:FX,3,1) -> 2.3297549 | EQ2: =(DL2-INDEX(FY:FY,4,1))/INDEX(FY:FY,3,1) -> 0.76767608 | ER2: =(DM2-INDEX(FZ:FZ,4,1))/INDEX(FZ:FZ,3,1) -> 2.0433399 | ES2: =(DN2-INDEX(GA:GA,4,1))/INDEX(GA:GA,3,1)*-1 -> 0.58531398 | ET2: =(DO2-INDEX(GB:GB,4,1))/INDEX(GB:GB,3,1) -> 1.8600473 | EU2: =(DP2-INDEX(GC:GC,4,1))/INDEX(GC:GC,3,1) -> 1.0806672 | EV2: =(DQ2-INDEX(GD:GD,4,1))/INDEX(GD:GD,3,1) -> 0.5807823 | EW2: =(DR2-INDEX(GE:GE,4,1))/INDEX(GE:GE,3,1) -> -1.9817705 | EX2: =(DS2-INDEX(GF:GF,4,1))/INDEX(GF:GF,3,1) -> 0.31312987 | EY2: =(DT2-INDEX(GG:GG,4,1))/INDEX(GG:GG,3,1)*-1 -> 0.63132928 | EZ2: =(DU2-INDEX(GH:GH,4,1))/INDEX(GH:GH,3,1) -> -1.7028449 | FA2: =(DV2-INDEX(GI:GI,4,1))/INDEX(GI:GI,3,1) -> -0.13666784 | FB2: =(DW2-INDEX(GJ:GJ,4,1))/INDEX(GJ:GJ,3,1) -> -0.090011201 | FC2: =(DX2-INDEX(GK:GK,4,1))/INDEX(GK:GK,3,1)*-1 -> -0.04227376 | FD2: =(DZ2-INDEX(GM:GM,4,1))/INDEX(GM:GM,3,1)*-1 -> 2.7974847 | FE2: =(EA2-INDEX(GN:GN,4,1))/INDEX(GN:GN,3,1)*-1 -> 1.6064764 | FF2: =(EB2-INDEX(GO:GO,4,1))/INDEX(GO:GO,3,1) -> 1.0147206 | FG2: =(((DP2-DI2-3*DU2)/2)+1.5*DU2)/DB2-DR2 -> 44.498548 | FH2: =DR2/(DR2+FG2) -> 0.26809851 | FK2: A:T | FL2: APG | FM2: Bench | FN2: BPG | FO2: EFG% | FP2: FB | FQ2: FG% | FR2: DFG% | FS2: FPG | FT2: FTA | FU2: FT% | FV2: FTPG | FW2: RM | FX2: DRPG | FY2: ORPG | FZ2: RPG | GA2: OPPG | GB2: SM | GC2: PPG | GD2: SPG | GE2: 3PTA | GF2: 3PT% | GG2: 3PD% | GH2: 3PPG | GI2: TM | GJ2: TOF | GK2: TPG | GL2: Blank | GM2: Res | GN2: BPI | GO2: Tempo
A3: 2 | B3: ACC | C3: Duke | D3: Blue Devils | E3: 1 | F3: WIN | H3: =_xlfn.IFNA(INDEX(importBPIRkCol,MATCH(INDEX(espnMap,MATCH(C3,valCol,0)),bpiImportCol,0)+rowOffset),INDEX(importBPIRkCol,MATCH(INDEX(espnMap2,MATCH(C3,valCol,0)),bpiImportCol,0)+rowOffset)) -> 1 | I3: =IFERROR(INDEX('Net Import'!A:A,MATCH(INDEX(mapping!B:B,MATCH(C3,mapping!A:A,0),1),'Net Import'!B:B,0),1),0) -> 1 | J3: =_xlfn.IFNA(INDEX(sorRkCol,MATCH(INDEX(espnMap,MATCH(C3,valCol,0)),sorTeamCol,0)+sorRowOffset),INDEX(sorRkCol,MATCH(INDEX(espnMap2,MATCH(C3,valCol,0)),sorTeamCol,0)+sorRowOffset)) -> 3 | K3: 1 | L3: 1 | M3: =CW3+R3*1.8+IF(K3>0,K3-26,0)/2+IF(CV3>0.5,0,10)-0.5*O3-IF(F3="WIN",1,IF(F3="IN",0.5,0))-S3+IF(W3>13.5,2,0)-IF(W3<6,6-W3,0) -> -70.972 | N3: =IF(COUNTIF(H3:J3,"<50.5")>1.5,1,0) -> 1 | O3: =_xlfn.IFNA(INDEX(importBPICol,MATCH(INDEX(espnMap,MATCH(C3,valCol,0)),bpiImportCol,0)+rowOffset), INDEX(importBPICol,MATCH(INDEX(espnMap2,MATCH(C3,valCol,0)),bpiImportCol,0)+rowOffset)) -> 25.6 | P3: =INDEX(kpOff,MATCH(INDEX(kpVal,MATCH(C3,valCol,0)),kpTeam,0)) -> 5 | Q3: =INDEX(kpDef,MATCH(INDEX(kpVal,MATCH(C3,valCol,0)),kpTeam,0)) -> 1 | R3: =-1*INDEX(calculatedResVal,MATCH(C3,resValueTeamCol,0)) -> -19.24 | S3: 8 | T3: 0 | U3: =COUNTA(AW3:BK3)+COUNTA(Y3:AJ3) -> 16 | V3: =COUNTA(BL3:BX3)+COUNTA(AK3:AV3) -> 2 | W3: =COUNTA(AK3:AV3)+COUNTA(BL3:CS3) -> 2 | X3: =IF(SUM(S3:W3)>0,1,0) -> 1 | Y3: KU | Z3: ARK | AA3: FLA | AB3: MSU | AC3: LOU | AD3: SMU | AE3: CLEM | AF3: MICH | AG3: UVA | AH3: UNC | AI3: UVA | AK3: TTU | AL3: UNC | AW3: TEX | AX3: CAL | AY3: VT | AZ3: NCSU | BA3: CLEM | CT3: =H3*0.4+J3*1.2+I3*0.8 -> 4.8 | CU3: =CT3/2.4 -> 2 | CV3: =VLOOKUP(B3,'SODiv Index'!A:B,2,FALSE) -> 1 | CW3: =CU3*(10-CV3/5)/10 -> 1.96 | CX3: =INDEX('Stats import'!H:H,MATCH((INDEX(mapping!R:R,MATCH(INDEX(statsCategories,1,1),mapping!P:P,0),1)+INDEX(mapping!H:H,MATCH(C3,mapping!A:A,0),1)),'Stats import'!B:B,0),1) -> 1.61 | CY3: =INDEX('Stats import'!H:H,MATCH((INDEX(mapping!R:R,MATCH(INDEX(statsCategories,1,2),mapping!P:P,0),1)+INDEX(mapping!H:H,MATCH(C3,mapping!A:A,0),1)),'Stats import'!B:B,0),1) -> 16.9 | CZ3: =INDEX('Stats import'!H:H,MATCH((INDEX(mapping!R:R,MATCH(INDEX(statsCategories,1,3),mapping!P:P,0),1)+INDEX(mapping!H:H,MATCH(C3,mapping!A:A,0),1)),'Stats import'!B:B,0),1) -> 20.21 | DA3: =INDEX('Stats import'!H:H,MATCH((INDEX(mapping!R:R,MATCH(INDEX(statsCategories,1,4),mapping!P:P,0),1)+INDEX(mapping!H:H,MATCH(C3,mapping!A:A,0),1)),'Stats import'!B:B,0),1) -> 3.3 | DB3: =INDEX('Stats import'!H:H,MATCH((INDEX(mapping!R:R,MATCH(INDEX(statsCategories,1,5),mapping!P:P,0),1)+INDEX(mapping!H:H,MATCH(C3,mapping!A:A,0),1)),'Stats import'!B:B,0),1) -> 0.568 | DC3: =INDEX('Stats import'!H:H,MATCH((INDEX(mapping!R:R,MATCH(INDEX(statsCategories,1,6),mapping!P:P,0),1)+INDEX(mapping!H:H,MATCH(C3,mapping!A:A,0),1)),'Stats import'!B:B,0),1) -> 10.09 | DD3: =INDEX('Stats import'!H:H,MATCH((INDEX(mapping!R:R,MATCH(INDEX(statsCategories,1,7),mapping!P:P,0),1)+INDEX(mapping!H:H,MATCH(C3,mapping!A:A,0),1)),'Stats import'!B:B,0),1) -> 49 | DE3: =INDEX('Stats import'!H:H,MATCH((INDEX(mapping!R:R,MATCH(INDEX(statsCategories,1,8),mapping!P:P,0),1)+INDEX(mapping!H:H,MATCH(C3,mapping!A:A,0),1)),'Stats import'!B:B,0),1) -> 39.2 | DF3: =INDEX('Stats import'!H:H,MATCH((INDEX(mapping!R:R,MATCH(INDEX(statsCategories,1,9),mapping!P:P,0),1)+INDEX(mapping!H:H,MATCH(C3,mapping!A:A,0),1)),'Stats import'!B:B,0),1) -> 15.7 | DG3: =INDEX('Stats import'!H:H,MATCH((INDEX(mapping!R:R,MATCH(INDEX(statsCategories,1,10),mapping!P:P,0),1)+INDEX(mapping!H:H,MATCH(C3,mapping!A:A,0),1)),'Stats import'!B:B,0),1) -> 22.1 | DH3: =INDEX('Stats import'!H:H,MATCH((INDEX(mapping!R:R,MATCH(INDEX(statsCategories,1,11),mapping!P:P,0),1)+INDEX(mapping!H:H,MATCH(C3,mapping!A:A,0),1)),'Stats import'!B:B,0),1) -> 72.4 | DI3: =INDEX('Stats import'!H:H,MATCH((INDEX(mapping!R:R,MATCH(INDEX(statsCategories,1,12),mapping!P:P,0),1)+INDEX(mapping!H:H,MATCH(C3,mapping!A:A,0),1)),'Stats import'!B:B,0),1) -> 16 | DJ3: =INDEX('Stats import'!H:H,MATCH((INDEX(mapping!R:R,MATCH(INDEX(statsCategories,1,13),mapping!P:P,0),1)+INDEX(mapping!H:H,MATCH(C3,mapping!A:A,0),1)),'Stats import'!B:B,0),1) -> 10.9 | DK3: =INDEX('Stats import'!H:H,MATCH((INDEX(mapping!R:R,MATCH(INDEX(statsCategories,1,14),mapping!P:P,0),1)+INDEX(mapping!H:H,MATCH(C3,mapping!A:A,0),1)),'Stats import'!B:B,0),1) -> 27.82 | DL3: =INDEX('Stats import'!H:H,MATCH((INDEX(mapping!R:R,MATCH(INDEX(statsCategories,1,15),mapping!P:P,0),1)+INDEX(mapping!H:H,MATCH(C3,mapping!A:A,0),1)),'Stats import'!B:B,0),1) -> 12.47 | DM3: =INDEX('Stats import'!H:H,MATCH((INDEX(mapping!R:R,MATCH(INDEX(statsCategories,1,16),mapping!P:P,0),1)+INDEX(mapping!H:H,MATCH(C3,mapping!A:A,0),1)),'Stats import'!B:B,0),1) -> 40.29 | DN3: =INDEX('Stats import'!H:H,MATCH((INDEX(mapping!R:R,MATCH(INDEX(statsCategories,1,17),mapping!P:P,0),1)+INDEX(mapping!H:H,MATCH(C3,mapping!A:A,0),1)),'Stats import'!B:B,0),1) -> 63.1 | DO3: =INDEX('Stats import'!H:H,MATCH((INDEX(mapping!R:R,MATCH(INDEX(statsCategories,1,18),mapping!P:P,0),1)+INDEX(mapping!H:H,MATCH(C3,mapping!A:A,0),1)),'Stats import'!B:B,0),1) -> 19.1 | DP3: =INDEX('Stats import'!H:H,MATCH((INDEX(mapping!R:R,MATCH(INDEX(statsCategories,1,19),mapping!P:P,0),1)+INDEX(mapping!H:H,MATCH(C3,mapping!A:A,0),1)),'Stats import'!B:B,0),1) -> 82.3 | DQ3: =INDEX('Stats import'!H:H,MATCH((INDEX(mapping!R:R,MATCH(INDEX(statsCategories,1,20),mapping!P:P,0),1)+INDEX(mapping!H:H,MATCH(C3,mapping!A:A,0),1)),'Stats import'!B:B,0),1) -> 7.8 | DR3: =INDEX('Stats import'!H:H,MATCH((INDEX(mapping!R:R,MATCH(INDEX(statsCategories,1,21),mapping!P:P,0),1)+INDEX(mapping!H:H,MATCH(C3,mapping!A:A,0),1)),'Stats import'!B:B,0),1) -> 25.9 | DS3: =INDEX('Stats import'!H:H,MATCH((INDEX(mapping!R:R,MATCH(INDEX(statsCategories,1,22),mapping!P:P,0),1)+INDEX(mapping!H:H,MATCH(C3,mapping!A:A,0),1)),'Stats import'!B:B,0),1) -> 35.1 | DT3: =INDEX('Stats import'!H:H,MATCH((INDEX(mapping!R:R,MATCH(INDEX(statsCategories,1,23),mapping!P:P,0),1)+INDEX(mapping!H:H,MATCH(C3,mapping!A:A,0),1)),'Stats import'!B:B,0),1) -> 30.4 | DU3: =INDEX('Stats import'!H:H,MATCH((INDEX(mapping!R:R,MATCH(INDEX(statsCategories,1,24),mapping!P:P,0),1)+INDEX(mapping!H:H,MATCH(C3,mapping!A:A,0),1)),'Stats import'!B:B,0),1) -> 9.1 | DV3: =INDEX('Stats import'!H:H,MATCH((INDEX(mapping!R:R,MATCH(INDEX(statsCategories,1,25),mapping!P:P,0),1)+INDEX(mapping!H:H,MATCH(C3,mapping!A:A,0),1)),'Stats import'!B:B,0),1) -> 1.6 | DW3: =INDEX('Stats import'!H:H,MATCH((INDEX(mapping!R:R,MATCH(INDEX(statsCategories,1,26),mapping!P:P,0),1)+INDEX(mapping!H:H,MATCH(C3,mapping!A:A,0),1)),'Stats import'!B:B,0),1) -> 12.18 | DX3: =INDEX('Stats import'!H:H,MATCH((INDEX(mapping!R:R,MATCH(INDEX(statsCategories,1,27),mapping!P:P,0),1)+INDEX(mapping!H:H,MATCH(C3,mapping!A:A,0),1)),'Stats import'!B:B,0),1) -> 10.5 | DZ3: =R3 -> -19.24 | EA3: =-O3 -> -25.6 | EB3: =INDEX('KenPom import'!J:J,MATCH(INDEX(kpVal,MATCH(C3,valCol,0)),kpTeam,0)) -> 65.4 | EC3: =(CX3-INDEX(FK:FK,4,1))/INDEX(FK:FK,3,1) -> 0.68827365 | ED3: =(CY3-INDEX(FL:FL,4,1))/INDEX(FL:FL,3,1) -> 0.80246063 | EE3: =(CZ3-INDEX(FM:FM,4,1))/INDEX(FM:FM,3,1) -> -0.24577273 | EF3: =(DA3-INDEX(FN:FN,4,1))/INDEX(FN:FN,3,1) -> -0.45964727 | EG3: =(DB3-INDEX(FO:FO,4,1))/INDEX(FO:FO,3,1) -> 1.1009436 | EH3: =(DC3-INDEX(FP:FP,4,1))/INDEX(FP:FP,3,1) -> -0.34845678 | EI3: =(DD3-INDEX(FQ:FQ,4,1))/INDEX(FQ:FQ,3,1) -> 1.0179596 | EJ3: =(DE3-INDEX(FR:FR,4,1))/INDEX(FR:FR,3,1)*-1 -> 1.6455587 | EK3: =(DF3-INDEX(FS:FS,4,1))/INDEX(FS:FS,3,1)*-1 -> 0.90466037 | EL3: =(DG3-INDEX(FT:FT,4,1))/INDEX(FT:FT,3,1) -> 0.23218271 | EM3: =(DH3-INDEX(FU:FU,4,1))/INDEX(FU:FU,3,1) -> -0.40003716 | EN3: =(DI3-INDEX(FV:FV,4,1))/INDEX(FV:FV,3,1) -> 0.10037813 | EO3: =(DJ3-INDEX(FW:FW,4,1))/INDEX(FW:FW,3,1) -> 1.9983069 | EP3: =(DK3-INDEX(FX:FX,4,1))/INDEX(FX:FX,3,1) -> 1.2792059 | EQ3: =(DL3-INDEX(FY:FY,4,1))/INDEX(FY:FY,3,1) -> 0.59639232 | ER3: =(DM3-INDEX(FZ:FZ,4,1))/INDEX(FZ:FZ,3,1) -> 1.2278606 | ES3: =(DN3-INDEX(GA:GA,4,1))/INDEX(GA:GA,3,1)*-1 -> 1.8181231 | ET3: =(DO3-INDEX(GB:GB,4,1))/INDEX(GB:GB,3,1) -> 2.2432717 | EU3: =(DP3-INDEX(GC:GC,4,1))/INDEX(GC:GC,3,1) -> 0.32717448 | EV3: =(DQ3-INDEX(GD:GD,4,1))/INDEX(GD:GD,3,1) -> 0.5807823 | EW3: =(DR3-INDEX(GE:GE,4,1))/INDEX(GE:GE,3,1) -> 0.41018258 | EX3: =(DS3-INDEX(GF:GF,4,1))/INDEX(GF:GF,3,1) -> -0.13777714 | EY3: =(DT3-INDEX(GG:GG,4,1))/INDEX(GG:GG,3,1)*-1 -> 1.2065724 | EZ3: =(DU3-INDEX(GH:GH,4,1))/INDEX(GH:GH,3,1) -> 0.31347468 | FA3: =(DV3-INDEX(GI:GI,4,1))/INDEX(GI:GI,3,1) -> 0.12241811 | FB3: =(DW3-INDEX(GJ:GJ,4,1))/INDEX(GJ:GJ,3,1) -> 0.031547334 | FC3: =(DX3-INDEX(GK:GK,4,1))/INDEX(GK:GK,3,1)*-1 -> 0.2395513 | FD3: =(DZ3-INDEX(GM:GM,4,1))/INDEX(GM:GM,3,1)*-1 -> 2.5946378 | FE3: =(EA3-INDEX(GN:GN,4,1))/INDEX(GN:GN,3,1)*-1 -> 1.8507341 | FF3: =(EB3-INDEX(GO:GO,4,1))/INDEX(GO:GO,3,1) -> -0.93387462 | FG3: =(((DP3-DI3-3*DU3)/2)+1.5*DU3)/DB3-DR3 -> 32.462676 | FH3: =DR3/(DR3+FG3) -> 0.44377677 | FJ3: STD | FK3: =_xlfn.STDEV.S(CX:CX) -> 0.23736925 | FL3: =_xlfn.STDEV.S(CY:CY) -> 1.8879431 | FM3: =_xlfn.STDEV.S(CZ:CZ) -> 6.1586369 | FN3: =_xlfn.STDEV.S(DA:DA) -> 0.98173107 | FO3: =_xlfn.STDEV.S(DB:DB) -> 0.024649309 | FP3: =_xlfn.STDEV.S(DC:DC) -> 3.2669044 | FQ3: =_xlfn.STDEV.S(DD:DD) -> 2.0408471 | FR3: =_xlfn.STDEV.S(DE:DE) -> 2.0768023 | FS3: =_xlfn.STDEV.S(DF:DF) -> 1.5668864 | FT3: =_xlfn.STDEV.S(DG:DG) -> 2.9071932 | FU3: =_xlfn.STDEV.S(DH:DH) -> 3.0590908 | FV3: =_xlfn.STDEV.S(DI:DI) -> 2.2415241 | FW3: =_xlfn.STDEV.S(DJ:DJ) -> 3.6505904 | FX3: =_xlfn.STDEV.S(DK:DK) -> 1.8466535 | FY3: =_xlfn.STDEV.S(DL:DL) -> 1.6930969 | FZ3: =_xlfn.STDEV.S(DM:DM) -> 2.7468509 | GA3: =_xlfn.STDEV.S(DN:DN) -> 4.6235869 | GB3: =_xlfn.STDEV.S(DO:DO) -> 4.4360432 | GC3: =_xlfn.STDEV.S(DP:DP) -> 5.0431806 | GD3: =_xlfn.STDEV.S(DQ:DQ) -> 1.3365593 | GE3: =_xlfn.STDEV.S(DR:DR) -> 4.0134566 | GF3: =_xlfn.STDEV.S(DS:DS) -> 1.995977 | GG3: =_xlfn.STDEV.S(DT:DT) -> 1.7383955 | GH3: =_xlfn.STDEV.S(DU:DU) -> 1.58705 | GI3: =_xlfn.STDEV.S(DV:DV) -> 1.9298615 | GJ3: =_xlfn.STDEV.S(DW:DW) -> 1.7275628 | GK3: =_xlfn.STDEV.S(DX:DX) -> 1.0644901 | GL3: =_xlfn.STDEV.S(DY:DY) -> #DIV/0! | GM3: =_xlfn.STDEV.S(DZ:DZ) -> 9.6852132 | GN3: =_xlfn.STDEV.S(EA:EA) -> 7.77867 | GO3: =_xlfn.STDEV.S(EB:EB) -> 2.411994
A4: 3 | B4: Big Ten | C4: Michigan | D4: Wolverines | E4: 1 | F4: OUT | H4: =_xlfn.IFNA(INDEX(importBPIRkCol,MATCH(INDEX(espnMap,MATCH(C4,valCol,0)),bpiImportCol,0)+rowOffset),INDEX(importBPIRkCol,MATCH(INDEX(espnMap2,MATCH(C4,valCol,0)),bpiImportCol,0)+rowOffset)) -> 2 | I4: =IFERROR(INDEX('Net Import'!A:A,MATCH(INDEX(mapping!B:B,MATCH(C4,mapping!A:A,0),1),'Net Import'!B:B,0),1),0) -> 2 | J4: =_xlfn.IFNA(INDEX(sorRkCol,MATCH(INDEX(espnMap,MATCH(C4,valCol,0)),sorTeamCol,0)+sorRowOffset),INDEX(sorRkCol,MATCH(INDEX(espnMap2,MATCH(C4,valCol,0)),sorTeamCol,0)+sorRowOffset)) -> 2 | K4: 3 | L4: 1.25 | M4: =CW4+R4*1.8+IF(K4>0,K4-26,0)/2+IF(CV4>0.5,0,10)-0.5*O4-IF(F4="WIN",1,IF(F4="IN",0.5,0))-S4+IF(W4>13.5,2,0)-IF(W4<6,6-W4,0) -> -63.201077 | N4: =IF(COUNTIF(H4:J4,"<50.5")>1.5,1,0) -> 1 | O4: =_xlfn.IFNA(INDEX(importBPICol,MATCH(INDEX(espnMap,MATCH(C4,valCol,0)),bpiImportCol,0)+rowOffset), INDEX(importBPICol,MATCH(INDEX(espnMap2,MATCH(C4,valCol,0)),bpiImportCol,0)+rowOffset)) -> 24.5 | P4: =INDEX(kpOff,MATCH(INDEX(kpVal,MATCH(C4,valCol,0)),kpTeam,0)) -> 4 | Q4: =INDEX(kpDef,MATCH(INDEX(kpVal,MATCH(C4,valCol,0)),kpTeam,0)) -> 2 | R4: =-1*INDEX(calculatedResVal,MATCH(C4,resValueTeamCol,0)) -> -18.006154 | S4: 6 | T4: 2 | U4: =COUNTA(AW4:BK4)+COUNTA(Y4:AJ4) -> 18 | V4: =COUNTA(BL4:BX4)+COUNTA(AK4:AV4) -> 3 | W4: =COUNTA(AK4:AV4)+COUNTA(BL4:CS4) -> 3 | X4: =IF(SUM(S4:W4)>0,1,0) -> 1 | Y4: AUB | Z4: GONZ | AA4: USC | AB4: NEB | AC4: MSU | AD4: PUR | AE4: ILL | AF4: MSU | AG4: WIS | AK4: DUKE | AL4: PUR | AW4: TCU | AX4: SDSU | AY4: VILL | AZ4: UCLA | BA4: IU | BB4: OSU | BC4: OSU | BD4: IOWA | BE4: OSU | BL4: WIS | CT4: =H4*0.4+J4*1.2+I4*0.8 -> 4.8 | CU4: =CT4/2.4 -> 2 | CV4: =VLOOKUP(B4,'SODiv Index'!A:B,2,FALSE) -> 1 | CW4: =CU4*(10-CV4/5)/10 -> 1.96 | CX4: =INDEX('Stats import'!H:H,MATCH((INDEX(mapping!R:R,MATCH(INDEX(statsCategories,1,1),mapping!P:P,0),1)+INDEX(mapping!H:H,MATCH(C4,mapping!A:A,0),1)),'Stats import'!B:B,0),1) -> 1.53 | CY4: =INDEX('Stats import'!H:H,MATCH((INDEX(mapping!R:R,MATCH(INDEX(statsCategories,1,2),mapping!P:P,0),1)+INDEX(mapping!H:H,MATCH(C4,mapping!A:A,0),1)),'Stats import'!B:B,0),1) -> 18.6 | CZ4: =INDEX('Stats import'!H:H,MATCH((INDEX(mapping!R:R,MATCH(INDEX(statsCategories,1,3),mapping!P:P,0),1)+INDEX(mapping!H:H,MATCH(C4,mapping!A:A,0),1)),'Stats import'!B:B,0),1) -> 29.85 | DA4: =INDEX('Stats import'!H:H,MATCH((INDEX(mapping!R:R,MATCH(INDEX(statsCategories,1,4),mapping!P:P,0),1)+INDEX(mapping!H:H,MATCH(C4,mapping!A:A,0),1)),'Stats import'!B:B,0),1) -> 6 | DB4: =INDEX('Stats import'!H:H,MATCH((INDEX(mapping!R:R,MATCH(INDEX(statsCategories,1,5),mapping!P:P,0),1)+INDEX(mapping!H:H,MATCH(C4,mapping!A:A,0),1)),'Stats import'!B:B,0),1) -> 0.582 | DC4: =INDEX('Stats import'!H:H,MATCH((INDEX(mapping!R:R,MATCH(INDEX(statsCategories,1,6),mapping!P:P,0),1)+INDEX(mapping!H:H,MATCH(C4,mapping!A:A,0),1)),'Stats import'!B:B,0),1) -> 12.58 | DD4: =INDEX('Stats import'!H:H,MATCH((INDEX(mapping!R:R,MATCH(INDEX(statsCategories,1,7),mapping!P:P,0),1)+INDEX(mapping!H:H,MATCH(C4,mapping!A:A,0),1)),'Stats import'!B:B,0),1) -> 50.7 | DE4: =INDEX('Stats import'!H:H,MATCH((INDEX(mapping!R:R,MATCH(INDEX(statsCategories,1,8),mapping!P:P,0),1)+INDEX(mapping!H:H,MATCH(C4,mapping!A:A,0),1)),'Stats import'!B:B,0),1) -> 38 | DF4: =INDEX('Stats import'!H:H,MATCH((INDEX(mapping!R:R,MATCH(INDEX(statsCategories,1,9),mapping!P:P,0),1)+INDEX(mapping!H:H,MATCH(C4,mapping!A:A,0),1)),'Stats import'!B:B,0),1) -> 15.5 | DG4: =INDEX('Stats import'!H:H,MATCH((INDEX(mapping!R:R,MATCH(INDEX(statsCategories,1,10),mapping!P:P,0),1)+INDEX(mapping!H:H,MATCH(C4,mapping!A:A,0),1)),'Stats import'!B:B,0),1) -> 23.2 | DH4: =INDEX('Stats import'!H:H,MATCH((INDEX(mapping!R:R,MATCH(INDEX(statsCategories,1,11),mapping!P:P,0),1)+INDEX(mapping!H:H,MATCH(C4,mapping!A:A,0),1)),'Stats import'!B:B,0),1) -> 74.6 | DI4: =INDEX('Stats import'!H:H,MATCH((INDEX(mapping!R:R,MATCH(INDEX(statsCategories,1,12),mapping!P:P,0),1)+INDEX(mapping!H:H,MATCH(C4,mapping!A:A,0),1)),'Stats import'!B:B,0),1) -> 17.3 | DJ4: =INDEX('Stats import'!H:H,MATCH((INDEX(mapping!R:R,MATCH(INDEX(statsCategories,1,13),mapping!P:P,0),1)+INDEX(mapping!H:H,MATCH(C4,mapping!A:A,0),1)),'Stats import'!B:B,0),1) -> 8.9 | DK4: =INDEX('Stats import'!H:H,MATCH((INDEX(mapping!R:R,MATCH(INDEX(statsCategories,1,14),mapping!P:P,0),1)+INDEX(mapping!H:H,MATCH(C4,mapping!A:A,0),1)),'Stats import'!B:B,0),1) -> 29.18 | DL4: =INDEX('Stats import'!H:H,MATCH((INDEX(mapping!R:R,MATCH(INDEX(statsCategories,1,15),mapping!P:P,0),1)+INDEX(mapping!H:H,MATCH(C4,mapping!A:A,0),1)),'Stats import'!B:B,0),1) -> 11 | DM4: =INDEX('Stats import'!H:H,MATCH((INDEX(mapping!R:R,MATCH(INDEX(statsCategories,1,16),mapping!P:P,0),1)+INDEX(mapping!H:H,MATCH(C4,mapping!A:A,0),1)),'Stats import'!B:B,0),1) -> 40.18 | DN4: =INDEX('Stats import'!H:H,MATCH((INDEX(mapping!R:R,MATCH(INDEX(statsCategories,1,17),mapping!P:P,0),1)+INDEX(mapping!H:H,MATCH(C4,mapping!A:A,0),1)),'Stats import'!B:B,0),1) -> 68.9 | DO4: =INDEX('Stats import'!H:H,MATCH((INDEX(mapping!R:R,MATCH(INDEX(statsCategories,1,18),mapping!P:P,0),1)+INDEX(mapping!H:H,MATCH(C4,mapping!A:A,0),1)),'Stats import'!B:B,0),1) -> 18.4 | DP4: =INDEX('Stats import'!H:H,MATCH((INDEX(mapping!R:R,MATCH(INDEX(statsCategories,1,19),mapping!P:P,0),1)+INDEX(mapping!H:H,MATCH(C4,mapping!A:A,0),1)),'Stats import'!B:B,0),1) -> 87.3 | DQ4: =INDEX('Stats import'!H:H,MATCH((INDEX(mapping!R:R,MATCH(INDEX(statsCategories,1,20),mapping!P:P,0),1)+INDEX(mapping!H:H,MATCH(C4,mapping!A:A,0),1)),'Stats import'!B:B,0),1) -> 5.8 | DR4: =INDEX('Stats import'!H:H,MATCH((INDEX(mapping!R:R,MATCH(INDEX(statsCategories,1,21),mapping!P:P,0),1)+INDEX(mapping!H:H,MATCH(C4,mapping!A:A,0),1)),'Stats import'!B:B,0),1) -> 25.2 | DS4: =INDEX('Stats import'!H:H,MATCH((INDEX(mapping!R:R,MATCH(INDEX(statsCategories,1,22),mapping!P:P,0),1)+INDEX(mapping!H:H,MATCH(C4,mapping!A:A,0),1)),'Stats import'!B:B,0),1) -> 36.2 | DT4: =INDEX('Stats import'!H:H,MATCH((INDEX(mapping!R:R,MATCH(INDEX(statsCategories,1,23),mapping!P:P,0),1)+INDEX(mapping!H:H,MATCH(C4,mapping!A:A,0),1)),'Stats import'!B:B,0),1) -> 30.2 | DU4: =INDEX('Stats import'!H:H,MATCH((INDEX(mapping!R:R,MATCH(INDEX(statsCategories,1,24),mapping!P:P,0),1)+INDEX(mapping!H:H,MATCH(C4,mapping!A:A,0),1)),'Stats import'!B:B,0),1) -> 9.1 | DV4: =INDEX('Stats import'!H:H,MATCH((INDEX(mapping!R:R,MATCH(INDEX(statsCategories,1,25),mapping!P:P,0),1)+INDEX(mapping!H:H,MATCH(C4,mapping!A:A,0),1)),'Stats import'!B:B,0),1) -> -0.8 | DW4: =INDEX('Stats import'!H:H,MATCH((INDEX(mapping!R:R,MATCH(INDEX(statsCategories,1,26),mapping!P:P,0),1)+INDEX(mapping!H:H,MATCH(C4,mapping!A:A,0),1)),'Stats import'!B:B,0),1) -> 11.36 | DX4: =INDEX('Stats import'!H:H,MATCH((INDEX(mapping!R:R,MATCH(INDEX(statsCategories,1,27),mapping!P:P,0),1)+INDEX(mapping!H:H,MATCH(C4,mapping!A:A,0),1)),'Stats import'!B:B,0),1) -> 12.1 | DZ4: =R4 -> -18.006154 | EA4: =-O4 -> -24.5 | EB4: =INDEX('KenPom import'!J:J,MATCH(INDEX(kpVal,MATCH(C4,valCol,0)),kpTeam,0)) -> 71.5 | EC4: =(CX4-INDEX(FK:FK,4,1))/INDEX(FK:FK,3,1) -> 0.351246 | ED4: =(CY4-INDEX(FL:FL,4,1))/INDEX(FL:FL,3,1) -> 1.7029115 | EE4: =(CZ4-INDEX(FM:FM,4,1))/INDEX(FM:FM,3,1) -> 1.3195087 | EF4: =(DA4-INDEX(FN:FN,4,1))/INDEX(FN:FN,3,1) -> 2.2905968 | EG4: =(DB4-INDEX(FO:FO,4,1))/INDEX(FO:FO,3,1) -> 1.6689109 | EH4: =(DC4-INDEX(FP:FP,4,1))/INDEX(FP:FP,3,1) -> 0.41373264 | EI4: =(DD4-INDEX(FQ:FQ,4,1))/INDEX(FQ:FQ,3,1) -> 1.8509471 | EJ4: =(DE4-INDEX(FR:FR,4,1))/INDEX(FR:FR,3,1)*-1 -> 2.2233701 | EK4: =(DF4-INDEX(FS:FS,4,1))/INDEX(FS:FS,3,1)*-1 -> 1.032302 | EL4: =(DG4-INDEX(FT:FT,4,1))/INDEX(FT:FT,3,1) -> 0.61055454 | EM4: =(DH4-INDEX(FU:FU,4,1))/INDEX(FU:FU,3,1) -> 0.31913077 | EN4: =(DI4-INDEX(FV:FV,4,1))/INDEX(FV:FV,3,1) -> 0.68034066 | EO4: =(DJ4-INDEX(FW:FW,4,1))/INDEX(FW:FW,3,1) -> 1.4504503 | EP4: =(DK4-INDEX(FX:FX,4,1))/INDEX(FX:FX,3,1) -> 2.0156732 | EQ4: =(DL4-INDEX(FY:FY,4,1))/INDEX(FY:FY,3,1) -> -0.27183914 | ER4: =(DM4-INDEX(FZ:FZ,4,1))/INDEX(FZ:FZ,3,1) -> 1.1878147 | ES4: =(DN4-INDEX(GA:GA,4,1))/INDEX(GA:GA,3,1)*-1 -> 0.56368575 | ET4: =(DO4-INDEX(GB:GB,4,1))/INDEX(GB:GB,3,1) -> 2.0854734 | EU4: =(DP4-INDEX(GC:GC,4,1))/INDEX(GC:GC,3,1) -> 1.3186123 | EV4: =(DQ4-INDEX(GD:GD,4,1))/INDEX(GD:GD,3,1) -> -0.91559722 | EW4: =(DR4-INDEX(GE:GE,4,1))/INDEX(GE:GE,3,1) -> 0.23576934 | EX4: =(DS4-INDEX(GF:GF,4,1))/INDEX(GF:GF,3,1) -> 0.41333142 | EY4: =(DT4-INDEX(GG:GG,4,1))/INDEX(GG:GG,3,1)*-1 -> 1.321621 | EZ4: =(DU4-INDEX(GH:GH,4,1))/INDEX(GH:GH,3,1) -> 0.31347468 | FA4: =(DV4-INDEX(GI:GI,4,1))/INDEX(GI:GI,3,1) -> -1.1211944 | FB4: =(DW4-INDEX(GJ:GJ,4,1))/INDEX(GJ:GJ,3,1) -> -0.4431098 | FC4: =(DX4-INDEX(GK:GK,4,1))/INDEX(GK:GK,3,1)*-1 -> -1.2635157 | FD4: =(DZ4-INDEX(GM:GM,4,1))/INDEX(GM:GM,3,1)*-1 -> 2.467243 | FE4: =(EA4-INDEX(GN:GN,4,1))/INDEX(GN:GN,3,1)*-1 -> 1.7093218 | FF4: =(EB4-INDEX(GO:GO,4,1))/INDEX(GO:GO,3,1) -> 1.5951532 | FG4: =(((DP4-DI4-3*DU4)/2)+1.5*DU4)/DB4-DR4 -> 34.937457 | FH4: =DR4/(DR4+FG4) -> 0.41904 | FJ4: AVG | FK4: =AVERAGE(CX:CX) -> 1.446625 | FL4: =AVERAGE(CY:CY) -> 15.385 | FM4: =AVERAGE(CZ:CZ) -> 21.723625 | FN4: =AVERAGE(DA:DA) -> 3.75125 | FO4: =AVERAGE(DB:DB) -> 0.5408625 | FP4: =AVERAGE(DC:DC) -> 11.228375 | FQ4: =AVERAGE(DD:DD) -> 46.9225 | FR4: =AVERAGE(DE:DE) -> 42.6175 | FS4: =AVERAGE(DF:DF) -> 17.1175 | FT4: =AVERAGE(DG:DG) -> 21.425 | FU4: =AVERAGE(DH:DH) -> 73.62375 | FV4: =AVERAGE(DI:DI) -> 15.775 | FW4: =AVERAGE(DJ:DJ) -> 3.605 | FX4: =AVERAGE(DK:DK) -> 25.45775 | FY4: =AVERAGE(DL:DL) -> 11.46025 | FZ4: =AVERAGE(DM:DM) -> 36.91725 | GA4: =AVERAGE(DN:DN) -> 71.50625 | GB4: =AVERAGE(DO:DO) -> 9.14875 | GC4: =AVERAGE(DP:DP) -> 80.65 | GD4: =AVERAGE(DQ:DQ) -> 7.02375 | GE4: =AVERAGE(DR:DR) -> 24.25375 | GF4: =AVERAGE(DS:DS) -> 35.375 | GG4: =AVERAGE(DT:DT) -> 32.4975 | GH4: =AVERAGE(DU:DU) -> 8.6025 | GI4: =AVERAGE(DV:DV) -> 1.36375 | GJ4: =AVERAGE(DW:DW) -> 12.1255 | GK4: =AVERAGE(DX:DX) -> 10.755 | GL4: =AVERAGE(DY:DY) -> #DIV/0! | GM4: =AVERAGE(DZ:DZ) -> 5.8896202 | GN4: =AVERAGE(EA:EA) -> -11.20375 | GO4: =AVERAGE(EB:EB) -> 67.6525
A5: 4 | B5: SEC | C5: Florida | D5: Gators | E5: 1 | F5: OUT | H5: =_xlfn.IFNA(INDEX(importBPIRkCol,MATCH(INDEX(espnMap,MATCH(C5,valCol,0)),bpiImportCol,0)+rowOffset),INDEX(importBPIRkCol,MATCH(INDEX(espnMap2,MATCH(C5,valCol,0)),bpiImportCol,0)+rowOffset)) -> 5 | I5: =IFERROR(INDEX('Net Import'!A:A,MATCH(INDEX(mapping!B:B,MATCH(C5,mapping!A:A,0),1),'Net Import'!B:B,0),1),0) -> 4 | J5: =_xlfn.IFNA(INDEX(sorRkCol,MATCH(INDEX(espnMap,MATCH(C5,valCol,0)),sorTeamCol,0)+sorRowOffset),INDEX(sorRkCol,MATCH(INDEX(espnMap2,MATCH(C5,valCol,0)),sorTeamCol,0)+sorRowOffset)) -> 5 | K5: 4 | L5: 1.75 | M5: =CW5+R5*1.8+IF(K5>0,K5-26,0)/2+IF(CV5>0.5,0,10)-0.5*O5-IF(F5="WIN",1,IF(F5="IN",0.5,0))-S5+IF(W5>13.5,2,0)-IF(W5<6,6-W5,0) -> -41.321051 | N5: =IF(COUNTIF(H5:J5,"<50.5")>1.5,1,0) -> 1 | O5: =_xlfn.IFNA(INDEX(importBPICol,MATCH(INDEX(espnMap,MATCH(C5,valCol,0)),bpiImportCol,0)+rowOffset), INDEX(importBPICol,MATCH(INDEX(espnMap2,MATCH(C5,valCol,0)),bpiImportCol,0)+rowOffset)) -> 22.3 | P5: =INDEX(kpOff,MATCH(INDEX(kpVal,MATCH(C5,valCol,0)),kpTeam,0)) -> 8 | Q5: =INDEX(kpDef,MATCH(INDEX(kpVal,MATCH(C5,valCol,0)),kpTeam,0)) -> 4 | R5: =-1*INDEX(calculatedResVal,MATCH(C5,resValueTeamCol,0)) -> -9.3024359 | S5: 7 | T5: 1 | U5: =COUNTA(AW5:BK5)+COUNTA(Y5:AJ5) -> 12 | V5: =COUNTA(BL5:BX5)+COUNTA(AK5:AV5) -> 7 | W5: =COUNTA(AK5:AV5)+COUNTA(BL5:CS5) -> 7 | X5: =IF(SUM(S5:W5)>0,1,0) -> 1 | Y5: UGA | Z5: TENN | AA5: VAN | AB5: ALA | AC5: UK | AD5: ARK | AK5: ARIZ | AL5: DUKE | AM5: CONN | AN5: VAN | AW5: MIA | AX5: UGA | AY5: TA&M | AZ5: TEX | BA5: UK | BB5: UK | BL5: TCU | BM5: MIZ | BN5: AUB | CT5: =H5*0.4+J5*1.2+I5*0.8 -> 11.2 | CU5: =CT5/2.4 -> 4.6666667 | CV5: =VLOOKUP(B5,'SODiv Index'!A:B,2,FALSE) -> 1 | CW5: =CU5*(10-CV5/5)/10 -> 4.5733333 | CX5: =INDEX('Stats import'!H:H,MATCH((INDEX(mapping!R:R,MATCH(INDEX(statsCategories,1,1),mapping!P:P,0),1)+INDEX(mapping!H:H,MATCH(C5,mapping!A:A,0),1)),'Stats import'!B:B,0),1) -> 1.39 | CY5: =INDEX('Stats import'!H:H,MATCH((INDEX(mapping!R:R,MATCH(INDEX(statsCategories,1,2),mapping!P:P,0),1)+INDEX(mapping!H:H,MATCH(C5,mapping!A:A,0),1)),'Stats import'!B:B,0),1) -> 16.6 | CZ5: =INDEX('Stats import'!H:H,MATCH((INDEX(mapping!R:R,MATCH(INDEX(statsCategories,1,3),mapping!P:P,0),1)+INDEX(mapping!H:H,MATCH(C5,mapping!A:A,0),1)),'Stats import'!B:B,0),1) -> 21.15 | DA5: =INDEX('Stats import'!H:H,MATCH((INDEX(mapping!R:R,MATCH(INDEX(statsCategories,1,4),mapping!P:P,0),1)+INDEX(mapping!H:H,MATCH(C5,mapping!A:A,0),1)),'Stats import'!B:B,0),1) -> 5.1 | DB5: =INDEX('Stats import'!H:H,MATCH((INDEX(mapping!R:R,MATCH(INDEX(statsCategories,1,5),mapping!P:P,0),1)+INDEX(mapping!H:H,MATCH(C5,mapping!A:A,0),1)),'Stats import'!B:B,0),1) -> 0.535 | DC5: =INDEX('Stats import'!H:H,MATCH((INDEX(mapping!R:R,MATCH(INDEX(statsCategories,1,6),mapping!P:P,0),1)+INDEX(mapping!H:H,MATCH(C5,mapping!A:A,0),1)),'Stats import'!B:B,0),1) -> 16.09 | DD5: =INDEX('Stats import'!H:H,MATCH((INDEX(mapping!R:R,MATCH(INDEX(statsCategories,1,7),mapping!P:P,0),1)+INDEX(mapping!H:H,MATCH(C5,mapping!A:A,0),1)),'Stats import'!B:B,0),1) -> 47.8 | DE5: =INDEX('Stats import'!H:H,MATCH((INDEX(mapping!R:R,MATCH(INDEX(statsCategories,1,8),mapping!P:P,0),1)+INDEX(mapping!H:H,MATCH(C5,mapping!A:A,0),1)),'Stats import'!B:B,0),1) -> 40.8 | DF5: =INDEX('Stats import'!H:H,MATCH((INDEX(mapping!R:R,MATCH(INDEX(statsCategories,1,9),mapping!P:P,0),1)+INDEX(mapping!H:H,MATCH(C5,mapping!A:A,0),1)),'Stats import'!B:B,0),1) -> 17.8 | DG5: =INDEX('Stats import'!H:H,MATCH((INDEX(mapping!R:R,MATCH(INDEX(statsCategories,1,10),mapping!P:P,0),1)+INDEX(mapping!H:H,MATCH(C5,mapping!A:A,0),1)),'Stats import'!B:B,0),1) -> 25.2 | DH5: =INDEX('Stats import'!H:H,MATCH((INDEX(mapping!R:R,MATCH(INDEX(statsCategories,1,11),mapping!P:P,0),1)+INDEX(mapping!H:H,MATCH(C5,mapping!A:A,0),1)),'Stats import'!B:B,0),1) -> 71 | DI5: =INDEX('Stats import'!H:H,MATCH((INDEX(mapping!R:R,MATCH(INDEX(statsCategories,1,12),mapping!P:P,0),1)+INDEX(mapping!H:H,MATCH(C5,mapping!A:A,0),1)),'Stats import'!B:B,0),1) -> 17.8 | DJ5: =INDEX('Stats import'!H:H,MATCH((INDEX(mapping!R:R,MATCH(INDEX(statsCategories,1,13),mapping!P:P,0),1)+INDEX(mapping!H:H,MATCH(C5,mapping!A:A,0),1)),'Stats import'!B:B,0),1) -> 14.5 | DK5: =INDEX('Stats import'!H:H,MATCH((INDEX(mapping!R:R,MATCH(INDEX(statsCategories,1,14),mapping!P:P,0),1)+INDEX(mapping!H:H,MATCH(C5,mapping!A:A,0),1)),'Stats import'!B:B,0),1) -> 29.3 | DL5: =INDEX('Stats import'!H:H,MATCH((INDEX(mapping!R:R,MATCH(INDEX(statsCategories,1,15),mapping!P:P,0),1)+INDEX(mapping!H:H,MATCH(C5,mapping!A:A,0),1)),'Stats import'!B:B,0),1) -> 16.12 | DM5: =INDEX('Stats import'!H:H,MATCH((INDEX(mapping!R:R,MATCH(INDEX(statsCategories,1,16),mapping!P:P,0),1)+INDEX(mapping!H:H,MATCH(C5,mapping!A:A,0),1)),'Stats import'!B:B,0),1) -> 45.42 | DN5: =INDEX('Stats import'!H:H,MATCH((INDEX(mapping!R:R,MATCH(INDEX(statsCategories,1,17),mapping!P:P,0),1)+INDEX(mapping!H:H,MATCH(C5,mapping!A:A,0),1)),'Stats import'!B:B,0),1) -> 72 | DO5: =INDEX('Stats import'!H:H,MATCH((INDEX(mapping!R:R,MATCH(INDEX(statsCategories,1,18),mapping!P:P,0),1)+INDEX(mapping!H:H,MATCH(C5,mapping!A:A,0),1)),'Stats import'!B:B,0),1) -> 14.8 | DP5: =INDEX('Stats import'!H:H,MATCH((INDEX(mapping!R:R,MATCH(INDEX(statsCategories,1,19),mapping!P:P,0),1)+INDEX(mapping!H:H,MATCH(C5,mapping!A:A,0),1)),'Stats import'!B:B,0),1) -> 86.8 | DQ5: =INDEX('Stats import'!H:H,MATCH((INDEX(mapping!R:R,MATCH(INDEX(statsCategories,1,20),mapping!P:P,0),1)+INDEX(mapping!H:H,MATCH(C5,mapping!A:A,0),1)),'Stats import'!B:B,0),1) -> 6.7 | DR5: =INDEX('Stats import'!H:H,MATCH((INDEX(mapping!R:R,MATCH(INDEX(statsCategories,1,21),mapping!P:P,0),1)+INDEX(mapping!H:H,MATCH(C5,mapping!A:A,0),1)),'Stats import'!B:B,0),1) -> 23.9 | DS5: =INDEX('Stats import'!H:H,MATCH((INDEX(mapping!R:R,MATCH(INDEX(statsCategories,1,22),mapping!P:P,0),1)+INDEX(mapping!H:H,MATCH(C5,mapping!A:A,0),1)),'Stats import'!B:B,0),1) -> 30.8 | DT5: =INDEX('Stats import'!H:H,MATCH((INDEX(mapping!R:R,MATCH(INDEX(statsCategories,1,23),mapping!P:P,0),1)+INDEX(mapping!H:H,MATCH(C5,mapping!A:A,0),1)),'Stats import'!B:B,0),1) -> 32.4 | DU5: =INDEX('Stats import'!H:H,MATCH((INDEX(mapping!R:R,MATCH(INDEX(statsCategories,1,24),mapping!P:P,0),1)+INDEX(mapping!H:H,MATCH(C5,mapping!A:A,0),1)),'Stats import'!B:B,0),1) -> 7.4 | DV5: =INDEX('Stats import'!H:H,MATCH((INDEX(mapping!R:R,MATCH(INDEX(statsCategories,1,25),mapping!P:P,0),1)+INDEX(mapping!H:H,MATCH(C5,mapping!A:A,0),1)),'Stats import'!B:B,0),1) -> -0.8 | DW5: =INDEX('Stats import'!H:H,MATCH((INDEX(mapping!R:R,MATCH(INDEX(statsCategories,1,26),mapping!P:P,0),1)+INDEX(mapping!H:H,MATCH(C5,mapping!A:A,0),1)),'Stats import'!B:B,0),1) -> 11.15 | DX5: =INDEX('Stats import'!H:H,MATCH((INDEX(mapping!R:R,MATCH(INDEX(statsCategories,1,27),mapping!P:P,0),1)+INDEX(mapping!H:H,MATCH(C5,mapping!A:A,0),1)),'Stats import'!B:B,0),1) -> 11.9 | DZ5: =R5 -> -9.3024359 | EA5: =-O5 -> -22.3 | EB5: =INDEX('KenPom import'!J:J,MATCH(INDEX(kpVal,MATCH(C5,valCol,0)),kpTeam,0)) -> 70.9 | EC5: =(CX5-INDEX(FK:FK,4,1))/INDEX(FK:FK,3,1) -> -0.23855238 | ED5: =(CY5-INDEX(FL:FL,4,1))/INDEX(FL:FL,3,1) -> 0.64355753 | EE5: =(CZ5-INDEX(FM:FM,4,1))/INDEX(FM:FM,3,1) -> -0.093141552 | EF5: =(DA5-INDEX(FN:FN,4,1))/INDEX(FN:FN,3,1) -> 1.3738488 | EG5: =(DB5-INDEX(FO:FO,4,1))/INDEX(FO:FO,3,1) -> -0.23783628 | EH5: =(DC5-INDEX(FP:FP,4,1))/INDEX(FP:FP,3,1) -> 1.4881442 | EI5: =(DD5-INDEX(FQ:FQ,4,1))/INDEX(FQ:FQ,3,1) -> 0.42996851 | EJ5: =(DE5-INDEX(FR:FR,4,1))/INDEX(FR:FR,3,1)*-1 -> 0.8751435 | EK5: =(DF5-INDEX(FS:FS,4,1))/INDEX(FS:FS,3,1)*-1 -> -0.43557721 | EL5: =(DG5-INDEX(FT:FT,4,1))/INDEX(FT:FT,3,1) -> 1.2985033 | EM5: =(DH5-INDEX(FU:FU,4,1))/INDEX(FU:FU,3,1) -> -0.85768949 | EN5: =(DI5-INDEX(FV:FV,4,1))/INDEX(FV:FV,3,1) -> 0.90340317 | EO5: =(DJ5-INDEX(FW:FW,4,1))/INDEX(FW:FW,3,1) -> 2.9844488 | EP5: =(DK5-INDEX(FX:FX,4,1))/INDEX(FX:FX,3,1) -> 2.0806557 | EQ5: =(DL5-INDEX(FY:FY,4,1))/INDEX(FY:FY,3,1) -> 2.7522051 | ER5: =(DM5-INDEX(FZ:FZ,4,1))/INDEX(FZ:FZ,3,1) -> 3.0954538 | ES5: =(DN5-INDEX(GA:GA,4,1))/INDEX(GA:GA,3,1)*-1 -> -0.10678939 | ET5: =(DO5-INDEX(GB:GB,4,1))/INDEX(GB:GB,3,1) -> 1.2739393 | EU5: =(DP5-INDEX(GC:GC,4,1))/INDEX(GC:GC,3,1) -> 1.2194685 | EV5: =(DQ5-INDEX(GD:GD,4,1))/INDEX(GD:GD,3,1) -> -0.24222644 | EW5: =(DR5-INDEX(GE:GE,4,1))/INDEX(GE:GE,3,1) -> -0.088140981 | EX5: =(DS5-INDEX(GF:GF,4,1))/INDEX(GF:GF,3,1) -> -2.2921106 | EY5: =(DT5-INDEX(GG:GG,4,1))/INDEX(GG:GG,3,1)*-1 -> 0.056086201 | EZ5: =(DU5-INDEX(GH:GH,4,1))/INDEX(GH:GH,3,1) -> -0.75769507 | FA5: =(DV5-INDEX(GI:GI,4,1))/INDEX(GI:GI,3,1) -> -1.1211944 | FB5: =(DW5-INDEX(GJ:GJ,4,1))/INDEX(GJ:GJ,3,1) -> -0.56466834 | FC5: =(DX5-INDEX(GK:GK,4,1))/INDEX(GK:GK,3,1)*-1 -> -1.0756323 | FD5: =(DZ5-INDEX(GM:GM,4,1))/INDEX(GM:GM,3,1)*-1 -> 1.5685825 | FE5: =(EA5-INDEX(GN:GN,4,1))/INDEX(GN:GN,3,1)*-1 -> 1.4264971 | FF5: =(EB5-INDEX(GO:GO,4,1))/INDEX(GO:GO,3,1) -> 1.3463964 | FG5: =(((DP5-DI5-3*DU5)/2)+1.5*DU5)/DB5-DR5 -> 40.585981 | FH5: =DR5/(DR5+FG5) -> 0.37062319
A6: 5 | B6: Big 12 | C6: Houston | D6: Cougars | E6: 2 | F6: OUT | H6: =_xlfn.IFNA(INDEX(importBPIRkCol,MATCH(INDEX(espnMap,MATCH(C6,valCol,0)),bpiImportCol,0)+rowOffset),INDEX(importBPIRkCol,MATCH(INDEX(espnMap2,MATCH(C6,valCol,0)),bpiImportCol,0)+rowOffset)) -> 4 | I6: =IFERROR(INDEX('Net Import'!A:A,MATCH(INDEX(mapping!B:B,MATCH(C6,mapping!A:A,0),1),'Net Import'!B:B,0),1),0) -> 5 | J6: =_xlfn.IFNA(INDEX(sorRkCol,MATCH(INDEX(espnMap,MATCH(C6,valCol,0)),sorTeamCol,0)+sorRowOffset),INDEX(sorRkCol,MATCH(INDEX(espnMap2,MATCH(C6,valCol,0)),sorTeamCol,0)+sorRowOffset)) -> 6 | K6: 5 | L6: 2 | M6: =CW6+R6*1.8+IF(K6>0,K6-26,0)/2+IF(CV6>0.5,0,10)-0.5*O6-IF(F6="WIN",1,IF(F6="IN",0.5,0))-S6+IF(W6>13.5,2,0)-IF(W6<6,6-W6,0) -> -34.635026 | N6: =IF(COUNTIF(H6:J6,"<50.5")>1.5,1,0) -> 1 | O6: =_xlfn.IFNA(INDEX(importBPICol,MATCH(INDEX(espnMap,MATCH(C6,valCol,0)),bpiImportCol,0)+rowOffset), INDEX(importBPICol,MATCH(INDEX(espnMap2,MATCH(C6,valCol,0)),bpiImportCol,0)+rowOffset)) -> 23 | P6: =INDEX(kpOff,MATCH(INDEX(kpVal,MATCH(C6,valCol,0)),kpTeam,0)) -> 17 | Q6: =INDEX(kpDef,MATCH(INDEX(kpVal,MATCH(C6,valCol,0)),kpTeam,0)) -> 6 | R6: =-1*INDEX(calculatedResVal,MATCH(C6,resValueTeamCol,0)) -> -7.1453846 | S6: 5 | T6: 3 | U6: =COUNTA(AW6:BK6)+COUNTA(Y6:AJ6) -> 10 | V6: =COUNTA(BL6:BX6)+COUNTA(AK6:AV6) -> 6 | W6: =COUNTA(AK6:AV6)+COUNTA(BL6:CS6) -> 6 | X6: =IF(SUM(S6:W6)>0,1,0) -> 1 | Y6: AUB | Z6: ARK | AA6: TTU | AB6: BYU | AC6: KU | AK6: TENN | AL6: TTU | AM6: ISU | AN6: ARIZ | AO6: KU | AP6: ARIZ | AW6: TCU | AX6: WVU | AY6: CIN | AZ6: CIN | BA6: BYU | CT6: =H6*0.4+J6*1.2+I6*0.8 -> 12.8 | CU6: =CT6/2.4 -> 5.3333333 | CV6: =VLOOKUP(B6,'SODiv Index'!A:B,2,FALSE) -> 1 | CW6: =CU6*(10-CV6/5)/10 -> 5.2266667 | CX6: =INDEX('Stats import'!H:H,MATCH((INDEX(mapping!R:R,MATCH(INDEX(statsCategories,1,1),mapping!P:P,0),1)+INDEX(mapping!H:H,MATCH(C6,mapping!A:A,0),1)),'Stats import'!B:B,0),1) -> 1.73 | CY6: =INDEX('Stats import'!H:H,MATCH((INDEX(mapping!R:R,MATCH(INDEX(statsCategories,1,2),mapping!P:P,0),1)+INDEX(mapping!H:H,MATCH(C6,mapping!A:A,0),1)),'Stats import'!B:B,0),1) -> 14.7 | CZ6: =INDEX('Stats import'!H:H,MATCH((INDEX(mapping!R:R,MATCH(INDEX(statsCategories,1,3),mapping!P:P,0),1)+INDEX(mapping!H:H,MATCH(C6,mapping!A:A,0),1)),'Stats import'!B:B,0),1) -> 17 | DA6: =INDEX('Stats import'!H:H,MATCH((INDEX(mapping!R:R,MATCH(INDEX(statsCategories,1,4),mapping!P:P,0),1)+INDEX(mapping!H:H,MATCH(C6,mapping!A:A,0),1)),'Stats import'!B:B,0),1) -> 3.9 | DB6: =INDEX('Stats import'!H:H,MATCH((INDEX(mapping!R:R,MATCH(INDEX(statsCategories,1,5),mapping!P:P,0),1)+INDEX(mapping!H:H,MATCH(C6,mapping!A:A,0),1)),'Stats import'!B:B,0),1) -> 0.521 | DC6: =INDEX('Stats import'!H:H,MATCH((INDEX(mapping!R:R,MATCH(INDEX(statsCategories,1,6),mapping!P:P,0),1)+INDEX(mapping!H:H,MATCH(C6,mapping!A:A,0),1)),'Stats import'!B:B,0),1) -> 8.09 | DD6: =INDEX('Stats import'!H:H,MATCH((INDEX(mapping!R:R,MATCH(INDEX(statsCategories,1,7),mapping!P:P,0),1)+INDEX(mapping!H:H,MATCH(C6,mapping!A:A,0),1)),'Stats import'!B:B,0),1) -> 45 | DE6: =INDEX('Stats import'!H:H,MATCH((INDEX(mapping!R:R,MATCH(INDEX(statsCategories,1,8),mapping!P:P,0),1)+INDEX(mapping!H:H,MATCH(C6,mapping!A:A,0),1)),'Stats import'!B:B,0),1) -> 40 | DF6: =INDEX('Stats import'!H:H,MATCH((INDEX(mapping!R:R,MATCH(INDEX(statsCategories,1,9),mapping!P:P,0),1)+INDEX(mapping!H:H,MATCH(C6,mapping!A:A,0),1)),'Stats import'!B:B,0),1) -> 18 | DG6: =INDEX('Stats import'!H:H,MATCH((INDEX(mapping!R:R,MATCH(INDEX(statsCategories,1,10),mapping!P:P,0),1)+INDEX(mapping!H:H,MATCH(C6,mapping!A:A,0),1)),'Stats import'!B:B,0),1) -> 16.6 | DH6: =INDEX('Stats import'!H:H,MATCH((INDEX(mapping!R:R,MATCH(INDEX(statsCategories,1,11),mapping!P:P,0),1)+INDEX(mapping!H:H,MATCH(C6,mapping!A:A,0),1)),'Stats import'!B:B,0),1) -> 77.2 | DI6: =INDEX('Stats import'!H:H,MATCH((INDEX(mapping!R:R,MATCH(INDEX(statsCategories,1,12),mapping!P:P,0),1)+INDEX(mapping!H:H,MATCH(C6,mapping!A:A,0),1)),'Stats import'!B:B,0),1) -> 12.8 | DJ6: =INDEX('Stats import'!H:H,MATCH((INDEX(mapping!R:R,MATCH(INDEX(statsCategories,1,13),mapping!P:P,0),1)+INDEX(mapping!H:H,MATCH(C6,mapping!A:A,0),1)),'Stats import'!B:B,0),1) -> 3.1 | DK6: =INDEX('Stats import'!H:H,MATCH((INDEX(mapping!R:R,MATCH(INDEX(statsCategories,1,14),mapping!P:P,0),1)+INDEX(mapping!H:H,MATCH(C6,mapping!A:A,0),1)),'Stats import'!B:B,0),1) -> 23.79 | DL6: =INDEX('Stats import'!H:H,MATCH((INDEX(mapping!R:R,MATCH(INDEX(statsCategories,1,15),mapping!P:P,0),1)+INDEX(mapping!H:H,MATCH(C6,mapping!A:A,0),1)),'Stats import'!B:B,0),1) -> 12.79 | DM6: =INDEX('Stats import'!H:H,MATCH((INDEX(mapping!R:R,MATCH(INDEX(statsCategories,1,16),mapping!P:P,0),1)+INDEX(mapping!H:H,MATCH(C6,mapping!A:A,0),1)),'Stats import'!B:B,0),1) -> 36.59 | DN6: =INDEX('Stats import'!H:H,MATCH((INDEX(mapping!R:R,MATCH(INDEX(statsCategories,1,17),mapping!P:P,0),1)+INDEX(mapping!H:H,MATCH(C6,mapping!A:A,0),1)),'Stats import'!B:B,0),1) -> 62.9 | DO6: =INDEX('Stats import'!H:H,MATCH((INDEX(mapping!R:R,MATCH(INDEX(statsCategories,1,18),mapping!P:P,0),1)+INDEX(mapping!H:H,MATCH(C6,mapping!A:A,0),1)),'Stats import'!B:B,0),1) -> 14.3 | DP6: =INDEX('Stats import'!H:H,MATCH((INDEX(mapping!R:R,MATCH(INDEX(statsCategories,1,19),mapping!P:P,0),1)+INDEX(mapping!H:H,MATCH(C6,mapping!A:A,0),1)),'Stats import'!B:B,0),1) -> 77.1 | DQ6: =INDEX('Stats import'!H:H,MATCH((INDEX(mapping!R:R,MATCH(INDEX(statsCategories,1,20),mapping!P:P,0),1)+INDEX(mapping!H:H,MATCH(C6,mapping!A:A,0),1)),'Stats import'!B:B,0),1) -> 7.7 | DR6: =INDEX('Stats import'!H:H,MATCH((INDEX(mapping!R:R,MATCH(INDEX(statsCategories,1,21),mapping!P:P,0),1)+INDEX(mapping!H:H,MATCH(C6,mapping!A:A,0),1)),'Stats import'!B:B,0),1) -> 25.2 | DS6: =INDEX('Stats import'!H:H,MATCH((INDEX(mapping!R:R,MATCH(INDEX(statsCategories,1,22),mapping!P:P,0),1)+INDEX(mapping!H:H,MATCH(C6,mapping!A:A,0),1)),'Stats import'!B:B,0),1) -> 34.9 | DT6: =INDEX('Stats import'!H:H,MATCH((INDEX(mapping!R:R,MATCH(INDEX(statsCategories,1,23),mapping!P:P,0),1)+INDEX(mapping!H:H,MATCH(C6,mapping!A:A,0),1)),'Stats import'!B:B,0),1) -> 32.1 | DU6: =INDEX('Stats import'!H:H,MATCH((INDEX(mapping!R:R,MATCH(INDEX(statsCategories,1,24),mapping!P:P,0),1)+INDEX(mapping!H:H,MATCH(C6,mapping!A:A,0),1)),'Stats import'!B:B,0),1) -> 8.8 | DV6: =INDEX('Stats import'!H:H,MATCH((INDEX(mapping!R:R,MATCH(INDEX(statsCategories,1,25),mapping!P:P,0),1)+INDEX(mapping!H:H,MATCH(C6,mapping!A:A,0),1)),'Stats import'!B:B,0),1) -> 5.2 | DW6: =INDEX('Stats import'!H:H,MATCH((INDEX(mapping!R:R,MATCH(INDEX(statsCategories,1,26),mapping!P:P,0),1)+INDEX(mapping!H:H,MATCH(C6,mapping!A:A,0),1)),'Stats import'!B:B,0),1) -> 13.71 | DX6: =INDEX('Stats import'!H:H,MATCH((INDEX(mapping!R:R,MATCH(INDEX(statsCategories,1,27),mapping!P:P,0),1)+INDEX(mapping!H:H,MATCH(C6,mapping!A:A,0),1)),'Stats import'!B:B,0),1) -> 8.5 | DZ6: =R6 -> -7.1453846 | EA6: =-O6 -> -23 | EB6: =INDEX('KenPom import'!J:J,MATCH(INDEX(kpVal,MATCH(C6,valCol,0)),kpTeam,0)) -> 63.4 | EC6: =(CX6-INDEX(FK:FK,4,1))/INDEX(FK:FK,3,1) -> 1.1938151 | ED6: =(CY6-INDEX(FL:FL,4,1))/INDEX(FL:FL,3,1) -> -0.36282873 | EE6: =(CZ6-INDEX(FM:FM,4,1))/INDEX(FM:FM,3,1) -> -0.76699196 | EF6: =(DA6-INDEX(FN:FN,4,1))/INDEX(FN:FN,3,1) -> 0.15151807 | EG6: =(DB6-INDEX(FO:FO,4,1))/INDEX(FO:FO,3,1) -> -0.80580351 | EH6: =(DC6-INDEX(FP:FP,4,1))/INDEX(FP:FP,3,1) -> -0.96065713 | EI6: =(DD6-INDEX(FQ:FQ,4,1))/INDEX(FQ:FQ,3,1) -> -0.94201079 | EJ6: =(DE6-INDEX(FR:FR,4,1))/INDEX(FR:FR,3,1)*-1 -> 1.2603511 | EK6: =(DF6-INDEX(FS:FS,4,1))/INDEX(FS:FS,3,1)*-1 -> -0.56321889 | EL6: =(DG6-INDEX(FT:FT,4,1))/INDEX(FT:FT,3,1) -> -1.6596764 | EM6: =(DH6-INDEX(FU:FU,4,1))/INDEX(FU:FU,3,1) -> 1.1690565 | EN6: =(DI6-INDEX(FV:FV,4,1))/INDEX(FV:FV,3,1) -> -1.3272219 | EO6: =(DJ6-INDEX(FW:FW,4,1))/INDEX(FW:FW,3,1) -> -0.13833379 | EP6: =(DK6-INDEX(FX:FX,4,1))/INDEX(FX:FX,3,1) -> -0.90312017 | EQ6: =(DL6-INDEX(FY:FY,4,1))/INDEX(FY:FY,3,1) -> 0.78539509 | ER6: =(DM6-INDEX(FZ:FZ,4,1))/INDEX(FZ:FZ,3,1) -> -0.11913643 | ES6: =(DN6-INDEX(GA:GA,4,1))/INDEX(GA:GA,3,1)*-1 -> 1.8613795 | ET6: =(DO6-INDEX(GB:GB,4,1))/INDEX(GB:GB,3,1) -> 1.1612263 | EU6: =(DP6-INDEX(GC:GC,4,1))/INDEX(GC:GC,3,1) -> -0.70392085 | EV6: =(DQ6-INDEX(GD:GD,4,1))/INDEX(GD:GD,3,1) -> 0.50596333 | EW6: =(DR6-INDEX(GE:GE,4,1))/INDEX(GE:GE,3,1) -> 0.23576934 | EX6: =(DS6-INDEX(GF:GF,4,1))/INDEX(GF:GF,3,1) -> -0.2379787 | EY6: =(DT6-INDEX(GG:GG,4,1))/INDEX(GG:GG,3,1)*-1 -> 0.22865913 | EZ6: =(DU6-INDEX(GH:GH,4,1))/INDEX(GH:GH,3,1) -> 0.12444472 | FA6: =(DV6-INDEX(GI:GI,4,1))/INDEX(GI:GI,3,1) -> 1.9878369 | FB6: =(DW6-INDEX(GJ:GJ,4,1))/INDEX(GJ:GJ,3,1) -> 0.91718809 | FC6: =(DX6-INDEX(GK:GK,4,1))/INDEX(GK:GK,3,1)*-1 -> 2.1183851 | FD6: =(DZ6-INDEX(GM:GM,4,1))/INDEX(GM:GM,3,1)*-1 -> 1.3458666 | FE6: =(EA6-INDEX(GN:GN,4,1))/INDEX(GN:GN,3,1)*-1 -> 1.5164867 | FF6: =(EB6-INDEX(GO:GO,4,1))/INDEX(GO:GO,3,1) -> -1.7630641 | FG6: =(((DP6-DI6-3*DU6)/2)+1.5*DU6)/DB6-DR6 -> 36.508253 | FH6: =DR6/(DR6+FG6) -> 0.40837325
A7: 6 | B7: Big East | C7: Connecticut | D7: Huskies | E7: 2 | F7: OUT | H7: =_xlfn.IFNA(INDEX(importBPIRkCol,MATCH(INDEX(espnMap,MATCH(C7,valCol,0)),bpiImportCol,0)+rowOffset),INDEX(importBPIRkCol,MATCH(INDEX(espnMap2,MATCH(C7,valCol,0)),bpiImportCol,0)+rowOffset)) -> 10 | I7: =IFERROR(INDEX('Net Import'!A:A,MATCH(INDEX(mapping!B:B,MATCH(C7,mapping!A:A,0),1),'Net Import'!B:B,0),1),0) -> 10 | J7: =_xlfn.IFNA(INDEX(sorRkCol,MATCH(INDEX(espnMap,MATCH(C7,valCol,0)),sorTeamCol,0)+sorRowOffset),INDEX(sorRkCol,MATCH(INDEX(espnMap2,MATCH(C7,valCol,0)),sorTeamCol,0)+sorRowOffset)) -> 4 | K7: 6 | L7: 2 | M7: =CW7+R7*1.8+IF(K7>0,K7-26,0)/2+IF(CV7>0.5,0,10)-0.5*O7-IF(F7="WIN",1,IF(F7="IN",0.5,0))-S7+IF(W7>13.5,2,0)-IF(W7<6,6-W7,0) -> -32.980308 | N7: =IF(COUNTIF(H7:J7,"<50.5")>1.5,1,0) -> 1 | O7: =_xlfn.IFNA(INDEX(importBPICol,MATCH(INDEX(espnMap,MATCH(C7,valCol,0)),bpiImportCol,0)+rowOffset), INDEX(importBPICol,MATCH(INDEX(espnMap2,MATCH(C7,valCol,0)),bpiImportCol,0)+rowOffset)) -> 19.4 | P7: =INDEX(kpOff,MATCH(INDEX(kpVal,MATCH(C7,valCol,0)),kpTeam,0)) -> 28 | Q7: =INDEX(kpDef,MATCH(INDEX(kpVal,MATCH(C7,valCol,0)),kpTeam,0)) -> 11 | R7: =-1*INDEX(calculatedResVal,MATCH(C7,resValueTeamCol,0)) -> -7.8596154 | S7: 5 | T7: 3 | U7: =COUNTA(AW7:BK7)+COUNTA(Y7:AJ7) -> 10 | V7: =COUNTA(BL7:BX7)+COUNTA(AK7:AV7) -> 3 | W7: =COUNTA(AK7:AV7)+COUNTA(BL7:CS7) -> 5 | X7: =IF(SUM(S7:W7)>0,1,0) -> 1 | Y7: BYU | Z7: ILL | AA7: KU | AB7: FLA | AC7: HALL | AD7: SJU | AK7: ARIZ | AL7: SJU | AM7: SJU | AW7: TEX | AX7: VILL | AY7: VILL | AZ7: HALL | BY7: CREI | BZ7: MARQ | CT7: =H7*0.4+J7*1.2+I7*0.8 -> 16.8 | CU7: =CT7/2.4 -> 7 | CV7: =VLOOKUP(B7,'SODiv Index'!A:B,2,FALSE) -> 0.95 | CW7: =CU7*(10-CV7/5)/10 -> 6.867 | CX7: =INDEX('Stats import'!H:H,MATCH((INDEX(mapping!R:R,MATCH(INDEX(statsCategories,1,1),mapping!P:P,0),1)+INDEX(mapping!H:H,MATCH(C7,mapping!A:A,0),1)),'Stats import'!B:B,0),1) -> 1.64 | CY7: =INDEX('Stats import'!H:H,MATCH((INDEX(mapping!R:R,MATCH(INDEX(statsCategories,1,2),mapping!P:P,0),1)+INDEX(mapping!H:H,MATCH(C7,mapping!A:A,0),1)),'Stats import'!B:B,0),1) -> 18.4 | CZ7: =INDEX('Stats import'!H:H,MATCH((INDEX(mapping!R:R,MATCH(INDEX(statsCategories,1,3),mapping!P:P,0),1)+INDEX(mapping!H:H,MATCH(C7,mapping!A:A,0),1)),'Stats import'!B:B,0),1) -> 16.74 | DA7: =INDEX('Stats import'!H:H,MATCH((INDEX(mapping!R:R,MATCH(INDEX(statsCategories,1,4),mapping!P:P,0),1)+INDEX(mapping!H:H,MATCH(C7,mapping!A:A,0),1)),'Stats import'!B:B,0),1) -> 5.3 | DB7: =INDEX('Stats import'!H:H,MATCH((INDEX(mapping!R:R,MATCH(INDEX(statsCategories,1,5),mapping!P:P,0),1)+INDEX(mapping!H:H,MATCH(C7,mapping!A:A,0),1)),'Stats import'!B:B,0),1) -> 0.553 | DC7: =INDEX('Stats import'!H:H,MATCH((INDEX(mapping!R:R,MATCH(INDEX(statsCategories,1,6),mapping!P:P,0),1)+INDEX(mapping!H:H,MATCH(C7,mapping!A:A,0),1)),'Stats import'!B:B,0),1) -> 9.09 | DD7: =INDEX('Stats import'!H:H,MATCH((INDEX(mapping!R:R,MATCH(INDEX(statsCategories,1,7),mapping!P:P,0),1)+INDEX(mapping!H:H,MATCH(C7,mapping!A:A,0),1)),'Stats import'!B:B,0),1) -> 48.2 | DE7: =INDEX('Stats import'!H:H,MATCH((INDEX(mapping!R:R,MATCH(INDEX(statsCategories,1,8),mapping!P:P,0),1)+INDEX(mapping!H:H,MATCH(C7,mapping!A:A,0),1)),'Stats import'!B:B,0),1) -> 40.2 | DF7: =INDEX('Stats import'!H:H,MATCH((INDEX(mapping!R:R,MATCH(INDEX(statsCategories,1,9),mapping!P:P,0),1)+INDEX(mapping!H:H,MATCH(C7,mapping!A:A,0),1)),'Stats import'!B:B,0),1) -> 18 | DG7: =INDEX('Stats import'!H:H,MATCH((INDEX(mapping!R:R,MATCH(INDEX(statsCategories,1,10),mapping!P:P,0),1)+INDEX(mapping!H:H,MATCH(C7,mapping!A:A,0),1)),'Stats import'!B:B,0),1) -> 17.6 | DH7: =INDEX('Stats import'!H:H,MATCH((INDEX(mapping!R:R,MATCH(INDEX(statsCategories,1,11),mapping!P:P,0),1)+INDEX(mapping!H:H,MATCH(C7,mapping!A:A,0),1)),'Stats import'!B:B,0),1) -> 71.6 | DI7: =INDEX('Stats import'!H:H,MATCH((INDEX(mapping!R:R,MATCH(INDEX(statsCategories,1,12),mapping!P:P,0),1)+INDEX(mapping!H:H,MATCH(C7,mapping!A:A,0),1)),'Stats import'!B:B,0),1) -> 12.6 | DJ7: =INDEX('Stats import'!H:H,MATCH((INDEX(mapping!R:R,MATCH(INDEX(statsCategories,1,13),mapping!P:P,0),1)+INDEX(mapping!H:H,MATCH(C7,mapping!A:A,0),1)),'Stats import'!B:B,0),1) -> 5.6 | DK7: =INDEX('Stats import'!H:H,MATCH((INDEX(mapping!R:R,MATCH(INDEX(statsCategories,1,14),mapping!P:P,0),1)+INDEX(mapping!H:H,MATCH(C7,mapping!A:A,0),1)),'Stats import'!B:B,0),1) -> 24.94 | DL7: =INDEX('Stats import'!H:H,MATCH((INDEX(mapping!R:R,MATCH(INDEX(statsCategories,1,15),mapping!P:P,0),1)+INDEX(mapping!H:H,MATCH(C7,mapping!A:A,0),1)),'Stats import'!B:B,0),1) -> 11.62 | DM7: =INDEX('Stats import'!H:H,MATCH((INDEX(mapping!R:R,MATCH(INDEX(statsCategories,1,16),mapping!P:P,0),1)+INDEX(mapping!H:H,MATCH(C7,mapping!A:A,0),1)),'Stats import'!B:B,0),1) -> 36.56 | DN7: =INDEX('Stats import'!H:H,MATCH((INDEX(mapping!R:R,MATCH(INDEX(statsCategories,1,17),mapping!P:P,0),1)+INDEX(mapping!H:H,MATCH(C7,mapping!A:A,0),1)),'Stats import'!B:B,0),1) -> 65.1 | DO7: =INDEX('Stats import'!H:H,MATCH((INDEX(mapping!R:R,MATCH(INDEX(statsCategories,1,18),mapping!P:P,0),1)+INDEX(mapping!H:H,MATCH(C7,mapping!A:A,0),1)),'Stats import'!B:B,0),1) -> 12.4 | DP7: =INDEX('Stats import'!H:H,MATCH((INDEX(mapping!R:R,MATCH(INDEX(statsCategories,1,19),mapping!P:P,0),1)+INDEX(mapping!H:H,MATCH(C7,mapping!A:A,0),1)),'Stats import'!B:B,0),1) -> 77.5 | DQ7: =INDEX('Stats import'!H:H,MATCH((INDEX(mapping!R:R,MATCH(INDEX(statsCategories,1,20),mapping!P:P,0),1)+INDEX(mapping!H:H,MATCH(C7,mapping!A:A,0),1)),'Stats import'!B:B,0),1) -> 6.9 | DR7: =INDEX('Stats import'!H:H,MATCH((INDEX(mapping!R:R,MATCH(INDEX(statsCategories,1,21),mapping!P:P,0),1)+INDEX(mapping!H:H,MATCH(C7,mapping!A:A,0),1)),'Stats import'!B:B,0),1) -> 23.6 | DS7: =INDEX('Stats import'!H:H,MATCH((INDEX(mapping!R:R,MATCH(INDEX(statsCategories,1,22),mapping!P:P,0),1)+INDEX(mapping!H:H,MATCH(C7,mapping!A:A,0),1)),'Stats import'!B:B,0),1) -> 35.2 | DT7: =INDEX('Stats import'!H:H,MATCH((INDEX(mapping!R:R,MATCH(INDEX(statsCategories,1,23),mapping!P:P,0),1)+INDEX(mapping!H:H,MATCH(C7,mapping!A:A,0),1)),'Stats import'!B:B,0),1) -> 30.3 | DU7: =INDEX('Stats import'!H:H,MATCH((INDEX(mapping!R:R,MATCH(INDEX(statsCategories,1,24),mapping!P:P,0),1)+INDEX(mapping!H:H,MATCH(C7,mapping!A:A,0),1)),'Stats import'!B:B,0),1) -> 8.3 | DV7: =INDEX('Stats import'!H:H,MATCH((INDEX(mapping!R:R,MATCH(INDEX(statsCategories,1,25),mapping!P:P,0),1)+INDEX(mapping!H:H,MATCH(C7,mapping!A:A,0),1)),'Stats import'!B:B,0),1) -> 0.8 | DW7: =INDEX('Stats import'!H:H,MATCH((INDEX(mapping!R:R,MATCH(INDEX(statsCategories,1,26),mapping!P:P,0),1)+INDEX(mapping!H:H,MATCH(C7,mapping!A:A,0),1)),'Stats import'!B:B,0),1) -> 12 | DX7: =INDEX('Stats import'!H:H,MATCH((INDEX(mapping!R:R,MATCH(INDEX(statsCategories,1,27),mapping!P:P,0),1)+INDEX(mapping!H:H,MATCH(C7,mapping!A:A,0),1)),'Stats import'!B:B,0),1) -> 11.2 | DZ7: =R7 -> -7.8596154 | EA7: =-O7 -> -19.4 | EB7: =INDEX('KenPom import'!J:J,MATCH(INDEX(kpVal,MATCH(C7,valCol,0)),kpTeam,0)) -> 64.9 | EC7: =(CX7-INDEX(FK:FK,4,1))/INDEX(FK:FK,3,1) -> 0.81465901 | ED7: =(CY7-INDEX(FL:FL,4,1))/INDEX(FL:FL,3,1) -> 1.5969761 | EE7: =(CZ7-INDEX(FM:FM,4,1))/INDEX(FM:FM,3,1) -> -0.8092091 | EF7: =(DA7-INDEX(FN:FN,4,1))/INDEX(FN:FN,3,1) -> 1.5775705 | EG7: =(DB7-INDEX(FO:FO,4,1))/INDEX(FO:FO,3,1) -> 0.49240731 | EH7: =(DC7-INDEX(FP:FP,4,1))/INDEX(FP:FP,3,1) -> -0.65455695 | EI7: =(DD7-INDEX(FQ:FQ,4,1))/INDEX(FQ:FQ,3,1) -> 0.62596556 | EJ7: =(DE7-INDEX(FR:FR,4,1))/INDEX(FR:FR,3,1)*-1 -> 1.1640492 | EK7: =(DF7-INDEX(FS:FS,4,1))/INDEX(FS:FS,3,1)*-1 -> -0.56321889 | EL7: =(DG7-INDEX(FT:FT,4,1))/INDEX(FT:FT,3,1) -> -1.315702 | EM7: =(DH7-INDEX(FU:FU,4,1))/INDEX(FU:FU,3,1) -> -0.66155278 | EN7: =(DI7-INDEX(FV:FV,4,1))/INDEX(FV:FV,3,1) -> -1.4164469 | EO7: =(DJ7-INDEX(FW:FW,4,1))/INDEX(FW:FW,3,1) -> 0.54648695 | EP7: =(DK7-INDEX(FX:FX,4,1))/INDEX(FX:FX,3,1) -> -0.28037204 | EQ7: =(DL7-INDEX(FY:FY,4,1))/INDEX(FY:FY,3,1) -> 0.094353725 | ER7: =(DM7-INDEX(FZ:FZ,4,1))/INDEX(FZ:FZ,3,1) -> -0.13005802 | ES7: =(DN7-INDEX(GA:GA,4,1))/INDEX(GA:GA,3,1)*-1 -> 1.3855585 | ET7: =(DO7-INDEX(GB:GB,4,1))/INDEX(GB:GB,3,1) -> 0.73291666 | EU7: =(DP7-INDEX(GC:GC,4,1))/INDEX(GC:GC,3,1) -> -0.62460583 | EV7: =(DQ7-INDEX(GD:GD,4,1))/INDEX(GD:GD,3,1) -> -0.092588483 | EW7: =(DR7-INDEX(GE:GE,4,1))/INDEX(GE:GE,3,1) -> -0.16288952 | EX7: =(DS7-INDEX(GF:GF,4,1))/INDEX(GF:GF,3,1) -> -0.087676362 | EY7: =(DT7-INDEX(GG:GG,4,1))/INDEX(GG:GG,3,1)*-1 -> 1.2640967 | EZ7: =(DU7-INDEX(GH:GH,4,1))/INDEX(GH:GH,3,1) -> -0.19060521 | FA7: =(DV7-INDEX(GI:GI,4,1))/INDEX(GI:GI,3,1) -> -0.2921194 | FB7: =(DW7-INDEX(GJ:GJ,4,1))/INDEX(GJ:GJ,3,1) -> -0.072645696 | FC7: =(DX7-INDEX(GK:GK,4,1))/INDEX(GK:GK,3,1)*-1 -> -0.41804051 | FD7: =(DZ7-INDEX(GM:GM,4,1))/INDEX(GM:GM,3,1)*-1 -> 1.419611 | FE7: =(EA7-INDEX(GN:GN,4,1))/INDEX(GN:GN,3,1)*-1 -> 1.0536827 | FF7: =(EB7-INDEX(GO:GO,4,1))/INDEX(GO:GO,3,1) -> -1.141172 | FG7: =(((DP7-DI7-3*DU7)/2)+1.5*DU7)/DB7-DR7 -> 35.079928 | FH7: =DR7/(DR7+FG7) -> 0.40218182
A8: 10 | B8: Big 12 | C8: Iowa State | D8: Cyclones | E8: 2 | F8: OUT | H8: =_xlfn.IFNA(INDEX(importBPIRkCol,MATCH(INDEX(espnMap,MATCH(C8,valCol,0)),bpiImportCol,0)+rowOffset),INDEX(importBPIRkCol,MATCH(INDEX(espnMap2,MATCH(C8,valCol,0)),bpiImportCol,0)+rowOffset)) -> 6 | I8: =IFERROR(INDEX('Net Import'!A:A,MATCH(INDEX(mapping!B:B,MATCH(C8,mapping!A:A,0),1),'Net Import'!B:B,0),1),0) -> 7 | J8: =_xlfn.IFNA(INDEX(sorRkCol,MATCH(INDEX(espnMap,MATCH(C8,valCol,0)),sorTeamCol,0)+sorRowOffset),INDEX(sorRkCol,MATCH(INDEX(espnMap2,MATCH(C8,valCol,0)),sorTeamCol,0)+sorRowOffset)) -> 14 | K8: 7 | L8: 2 | M8: =CW8+R8*1.8+IF(K8>0,K8-26,0)/2+IF(CV8>0.5,0,10)-0.5*O8-IF(F8="WIN",1,IF(F8="IN",0.5,0))-S8+IF(W8>13.5,2,0)-IF(W8<6,6-W8,0) -> -21.549026 | N8: =IF(COUNTIF(H8:J8,"<50.5")>1.5,1,0) -> 1 | O8: =_xlfn.IFNA(INDEX(importBPICol,MATCH(INDEX(espnMap,MATCH(C8,valCol,0)),bpiImportCol,0)+rowOffset), INDEX(importBPICol,MATCH(INDEX(espnMap2,MATCH(C8,valCol,0)),bpiImportCol,0)+rowOffset)) -> 21.5 | P8: =INDEX(kpOff,MATCH(INDEX(kpVal,MATCH(C8,valCol,0)),kpTeam,0)) -> 26 | Q8: =INDEX(kpDef,MATCH(INDEX(kpVal,MATCH(C8,valCol,0)),kpTeam,0)) -> 7 | R8: =-1*INDEX(calculatedResVal,MATCH(C8,resValueTeamCol,0)) -> -4.1253846 | S8: 4 | T8: 4 | U8: =COUNTA(AW8:BK8)+COUNTA(Y8:AJ8) -> 8 | V8: =COUNTA(BL8:BX8)+COUNTA(AK8:AV8) -> 7 | W8: =COUNTA(AK8:AV8)+COUNTA(BL8:CS8) -> 7 | X8: =IF(SUM(S8:W8)>0,1,0) -> 1 | Y8: SJU | Z8: PUR | AA8: KU | AB8: HOU | AC8: TTU | AK8: BYU | AL8: TTU | AM8: ARIZ | AN8: ARIZ | AW8: UCF | AX8: IOWA | AY8: WVU | BL8: KU | BM8: TCU | BN8: CIN | CT8: =H8*0.4+J8*1.2+I8*0.8 -> 24.8 | CU8: =CT8/2.4 -> 10.333333 | CV8: =VLOOKUP(B8,'SODiv Index'!A:B,2,FALSE) -> 1 | CW8: =CU8*(10-CV8/5)/10 -> 10.126667 | CX8: =INDEX('Stats import'!H:H,MATCH((INDEX(mapping!R:R,MATCH(INDEX(statsCategories,1,1),mapping!P:P,0),1)+INDEX(mapping!H:H,MATCH(C8,mapping!A:A,0),1)),'Stats import'!B:B,0),1) -> 1.68 | CY8: =INDEX('Stats import'!H:H,MATCH((INDEX(mapping!R:R,MATCH(INDEX(statsCategories,1,2),mapping!P:P,0),1)+INDEX(mapping!H:H,MATCH(C8,mapping!A:A,0),1)),'Stats import'!B:B,0),1) -> 17.2 | CZ8: =INDEX('Stats import'!H:H,MATCH((INDEX(mapping!R:R,MATCH(INDEX(statsCategories,1,3),mapping!P:P,0),1)+INDEX(mapping!H:H,MATCH(C8,mapping!A:A,0),1)),'Stats import'!B:B,0),1) -> 18.79 | DA8: =INDEX('Stats import'!H:H,MATCH((INDEX(mapping!R:R,MATCH(INDEX(statsCategories,1,4),mapping!P:P,0),1)+INDEX(mapping!H:H,MATCH(C8,mapping!A:A,0),1)),'Stats import'!B:B,0),1) -> 2.7 | DB8: =INDEX('Stats import'!H:H,MATCH((INDEX(mapping!R:R,MATCH(INDEX(statsCategories,1,5),mapping!P:P,0),1)+INDEX(mapping!H:H,MATCH(C8,mapping!A:A,0),1)),'Stats import'!B:B,0),1) -> 0.565 | DC8: =INDEX('Stats import'!H:H,MATCH((INDEX(mapping!R:R,MATCH(INDEX(statsCategories,1,6),mapping!P:P,0),1)+INDEX(mapping!H:H,MATCH(C8,mapping!A:A,0),1)),'Stats import'!B:B,0),1) -> 11.38 | DD8: =INDEX('Stats import'!H:H,MATCH((INDEX(mapping!R:R,MATCH(INDEX(statsCategories,1,7),mapping!P:P,0),1)+INDEX(mapping!H:H,MATCH(C8,mapping!A:A,0),1)),'Stats import'!B:B,0),1) -> 49 | DE8: =INDEX('Stats import'!H:H,MATCH((INDEX(mapping!R:R,MATCH(INDEX(statsCategories,1,8),mapping!P:P,0),1)+INDEX(mapping!H:H,MATCH(C8,mapping!A:A,0),1)),'Stats import'!B:B,0),1) -> 42.6 | DF8: =INDEX('Stats import'!H:H,MATCH((INDEX(mapping!R:R,MATCH(INDEX(statsCategories,1,9),mapping!P:P,0),1)+INDEX(mapping!H:H,MATCH(C8,mapping!A:A,0),1)),'Stats import'!B:B,0),1) -> 16 | DG8: =INDEX('Stats import'!H:H,MATCH((INDEX(mapping!R:R,MATCH(INDEX(statsCategories,1,10),mapping!P:P,0),1)+INDEX(mapping!H:H,MATCH(C8,mapping!A:A,0),1)),'Stats import'!B:B,0),1) -> 20.5 | DH8: =INDEX('Stats import'!H:H,MATCH((INDEX(mapping!R:R,MATCH(INDEX(statsCategories,1,11),mapping!P:P,0),1)+INDEX(mapping!H:H,MATCH(C8,mapping!A:A,0),1)),'Stats import'!B:B,0),1) -> 67.2 | DI8: =INDEX('Stats import'!H:H,MATCH((INDEX(mapping!R:R,MATCH(INDEX(statsCategories,1,12),mapping!P:P,0),1)+INDEX(mapping!H:H,MATCH(C8,mapping!A:A,0),1)),'Stats import'!B:B,0),1) -> 13.8 | DJ8: =INDEX('Stats import'!H:H,MATCH((INDEX(mapping!R:R,MATCH(INDEX(statsCategories,1,13),mapping!P:P,0),1)+INDEX(mapping!H:H,MATCH(C8,mapping!A:A,0),1)),'Stats import'!B:B,0),1) -> 4.6 | DK8: =INDEX('Stats import'!H:H,MATCH((INDEX(mapping!R:R,MATCH(INDEX(statsCategories,1,14),mapping!P:P,0),1)+INDEX(mapping!H:H,MATCH(C8,mapping!A:A,0),1)),'Stats import'!B:B,0),1) -> 23.76 | DL8: =INDEX('Stats import'!H:H,MATCH((INDEX(mapping!R:R,MATCH(INDEX(statsCategories,1,15),mapping!P:P,0),1)+INDEX(mapping!H:H,MATCH(C8,mapping!A:A,0),1)),'Stats import'!B:B,0),1) -> 11.85 | DM8: =INDEX('Stats import'!H:H,MATCH((INDEX(mapping!R:R,MATCH(INDEX(statsCategories,1,16),mapping!P:P,0),1)+INDEX(mapping!H:H,MATCH(C8,mapping!A:A,0),1)),'Stats import'!B:B,0),1) -> 35.62 | DN8: =INDEX('Stats import'!H:H,MATCH((INDEX(mapping!R:R,MATCH(INDEX(statsCategories,1,17),mapping!P:P,0),1)+INDEX(mapping!H:H,MATCH(C8,mapping!A:A,0),1)),'Stats import'!B:B,0),1) -> 65.1 | DO8: =INDEX('Stats import'!H:H,MATCH((INDEX(mapping!R:R,MATCH(INDEX(statsCategories,1,18),mapping!P:P,0),1)+INDEX(mapping!H:H,MATCH(C8,mapping!A:A,0),1)),'Stats import'!B:B,0),1) -> 16.6 | DP8: =INDEX('Stats import'!H:H,MATCH((INDEX(mapping!R:R,MATCH(INDEX(statsCategories,1,19),mapping!P:P,0),1)+INDEX(mapping!H:H,MATCH(C8,mapping!A:A,0),1)),'Stats import'!B:B,0),1) -> 81.8 | DQ8: =INDEX('Stats import'!H:H,MATCH((INDEX(mapping!R:R,MATCH(INDEX(statsCategories,1,20),mapping!P:P,0),1)+INDEX(mapping!H:H,MATCH(C8,mapping!A:A,0),1)),'Stats import'!B:B,0),1) -> 9 | DR8: =INDEX('Stats import'!H:H,MATCH((INDEX(mapping!R:R,MATCH(INDEX(statsCategories,1,21),mapping!P:P,0),1)+INDEX(mapping!H:H,MATCH(C8,mapping!A:A,0),1)),'Stats import'!B:B,0),1) -> 23.4 | DS8: =INDEX('Stats import'!H:H,MATCH((INDEX(mapping!R:R,MATCH(INDEX(statsCategories,1,22),mapping!P:P,0),1)+INDEX(mapping!H:H,MATCH(C8,mapping!A:A,0),1)),'Stats import'!B:B,0),1) -> 38.7 | DT8: =INDEX('Stats import'!H:H,MATCH((INDEX(mapping!R:R,MATCH(INDEX(statsCategories,1,23),mapping!P:P,0),1)+INDEX(mapping!H:H,MATCH(C8,mapping!A:A,0),1)),'Stats import'!B:B,0),1) -> 32.1 | DU8: =INDEX('Stats import'!H:H,MATCH((INDEX(mapping!R:R,MATCH(INDEX(statsCategories,1,24),mapping!P:P,0),1)+INDEX(mapping!H:H,MATCH(C8,mapping!A:A,0),1)),'Stats import'!B:B,0),1) -> 9 | DV8: =INDEX('Stats import'!H:H,MATCH((INDEX(mapping!R:R,MATCH(INDEX(statsCategories,1,25),mapping!P:P,0),1)+INDEX(mapping!H:H,MATCH(C8,mapping!A:A,0),1)),'Stats import'!B:B,0),1) -> 5 | DW8: =INDEX('Stats import'!H:H,MATCH((INDEX(mapping!R:R,MATCH(INDEX(statsCategories,1,26),mapping!P:P,0),1)+INDEX(mapping!H:H,MATCH(C8,mapping!A:A,0),1)),'Stats import'!B:B,0),1) -> 15.26 | DX8: =INDEX('Stats import'!H:H,MATCH((INDEX(mapping!R:R,MATCH(INDEX(statsCategories,1,27),mapping!P:P,0),1)+INDEX(mapping!H:H,MATCH(C8,mapping!A:A,0),1)),'Stats import'!B:B,0),1) -> 10.3 | DZ8: =R8 -> -4.1253846 | EA8: =-O8 -> -21.5 | EB8: =INDEX('KenPom import'!J:J,MATCH(INDEX(kpVal,MATCH(C8,valCol,0)),kpTeam,0)) -> 66.7 | EC8: =(CX8-INDEX(FK:FK,4,1))/INDEX(FK:FK,3,1) -> 0.98317284 | ED8: =(CY8-INDEX(FL:FL,4,1))/INDEX(FL:FL,3,1) -> 0.96136372 | EE8: =(CZ8-INDEX(FM:FM,4,1))/INDEX(FM:FM,3,1) -> -0.47634323 | EF8: =(DA8-INDEX(FN:FN,4,1))/INDEX(FN:FN,3,1) -> -1.0708126 | EG8: =(DB8-INDEX(FO:FO,4,1))/INDEX(FO:FO,3,1) -> 0.97923636 | EH8: =(DC8-INDEX(FP:FP,4,1))/INDEX(FP:FP,3,1) -> 0.046412439 | EI8: =(DD8-INDEX(FQ:FQ,4,1))/INDEX(FQ:FQ,3,1) -> 1.0179596 | EJ8: =(DE8-INDEX(FR:FR,4,1))/INDEX(FR:FR,3,1)*-1 -> 0.0084264161 | EK8: =(DF8-INDEX(FS:FS,4,1))/INDEX(FS:FS,3,1)*-1 -> 0.71319785 | EL8: =(DG8-INDEX(FT:FT,4,1))/INDEX(FT:FT,3,1) -> -0.31817631 | EM8: =(DH8-INDEX(FU:FU,4,1))/INDEX(FU:FU,3,1) -> -2.0998886 | EN8: =(DI8-INDEX(FV:FV,4,1))/INDEX(FV:FV,3,1) -> -0.88109692 | EO8: =(DJ8-INDEX(FW:FW,4,1))/INDEX(FW:FW,3,1) -> 0.27255865 | EP8: =(DK8-INDEX(FX:FX,4,1))/INDEX(FX:FX,3,1) -> -0.91936577 | EQ8: =(DL8-INDEX(FY:FY,4,1))/INDEX(FY:FY,3,1) -> 0.23019946 | ER8: =(DM8-INDEX(FZ:FZ,4,1))/INDEX(FZ:FZ,3,1) -> -0.47226808 | ES8: =(DN8-INDEX(GA:GA,4,1))/INDEX(GA:GA,3,1)*-1 -> 1.3855585 | ET8: =(DO8-INDEX(GB:GB,4,1))/INDEX(GB:GB,3,1) -> 1.6797064 | EU8: =(DP8-INDEX(GC:GC,4,1))/INDEX(GC:GC,3,1) -> 0.2280307 | EV8: =(DQ8-INDEX(GD:GD,4,1))/INDEX(GD:GD,3,1) -> 1.47861 | EW8: =(DR8-INDEX(GE:GE,4,1))/INDEX(GE:GE,3,1) -> -0.21272187 | EX8: =(DS8-INDEX(GF:GF,4,1))/INDEX(GF:GF,3,1) -> 1.6658509 | EY8: =(DT8-INDEX(GG:GG,4,1))/INDEX(GG:GG,3,1)*-1 -> 0.22865913 | EZ8: =(DU8-INDEX(GH:GH,4,1))/INDEX(GH:GH,3,1) -> 0.25046469 | FA8: =(DV8-INDEX(GI:GI,4,1))/INDEX(GI:GI,3,1) -> 1.8842025 | FB8: =(DW8-INDEX(GJ:GJ,4,1))/INDEX(GJ:GJ,3,1) -> 1.8144058 | FC8: =(DX8-INDEX(GK:GK,4,1))/INDEX(GK:GK,3,1)*-1 -> 0.42743468 | FD8: =(DZ8-INDEX(GM:GM,4,1))/INDEX(GM:GM,3,1)*-1 -> 1.034051 | FE8: =(EA8-INDEX(GN:GN,4,1))/INDEX(GN:GN,3,1)*-1 -> 1.3236517 | FF8: =(EB8-INDEX(GO:GO,4,1))/INDEX(GO:GO,3,1) -> -0.39490148 | FG8: =(((DP8-DI8-3*DU8)/2)+1.5*DU8)/DB8-DR8 -> 36.776991 | FH8: =DR8/(DR8+FG8) -> 0.38885294
A9: 12 | B9: Big Ten | C9: Purdue | D9: Boilermakers | E9: 2 | F9: WIN | H9: =_xlfn.IFNA(INDEX(importBPIRkCol,MATCH(INDEX(espnMap,MATCH(C9,valCol,0)),bpiImportCol,0)+rowOffset),INDEX(importBPIRkCol,MATCH(INDEX(espnMap2,MATCH(C9,valCol,0)),bpiImportCol,0)+rowOffset)) -> 9 | I9: =IFERROR(INDEX('Net Import'!A:A,MATCH(INDEX(mapping!B:B,MATCH(C9,mapping!A:A,0),1),'Net Import'!B:B,0),1),0) -> 9 | J9: =_xlfn.IFNA(INDEX(sorRkCol,MATCH(INDEX(espnMap,MATCH(C9,valCol,0)),sorTeamCol,0)+sorRowOffset),INDEX(sorRkCol,MATCH(INDEX(espnMap2,MATCH(C9,valCol,0)),sorTeamCol,0)+sorRowOffset)) -> 12 | K9: 18 | L9: 3 | M9: =CW9+R9*1.8+IF(K9>0,K9-26,0)/2+IF(CV9>0.5,0,10)-0.5*O9-IF(F9="WIN",1,IF(F9="IN",0.5,0))-S9+IF(W9>13.5,2,0)-IF(W9<6,6-W9,0) -> -18.646923 | N9: =IF(COUNTIF(H9:J9,"<50.5")>1.5,1,0) -> 1 | O9: =_xlfn.IFNA(INDEX(importBPICol,MATCH(INDEX(espnMap,MATCH(C9,valCol,0)),bpiImportCol,0)+rowOffset), INDEX(importBPICol,MATCH(INDEX(espnMap2,MATCH(C9,valCol,0)),bpiImportCol,0)+rowOffset)) -> 20.4 | P9: =INDEX(kpOff,MATCH(INDEX(kpVal,MATCH(C9,valCol,0)),kpTeam,0)) -> 2 | Q9: =INDEX(kpDef,MATCH(INDEX(kpVal,MATCH(C9,valCol,0)),kpTeam,0)) -> 39 | R9: =-1*INDEX(calculatedResVal,MATCH(C9,resValueTeamCol,0)) -> -4.8538462 | S9: 5 | T9: 3 | U9: =COUNTA(AW9:BK9)+COUNTA(Y9:AJ9) -> 12 | V9: =COUNTA(BL9:BX9)+COUNTA(AK9:AV9) -> 8 | W9: =COUNTA(AK9:AV9)+COUNTA(BL9:CS9) -> 8 | X9: =IF(SUM(S9:W9)>0,1,0) -> 1 | Y9: ALA | Z9: TTU | AA9: AUB | AB9: NEB | AC9: NEB | AD9: MICH | AK9: ISU | AL9: ILL | AM9: MICH | AN9: MSU | AW9: WIS | AX9: IU | AY9: IOWA | AZ9: USC | BA9: IOWA | BB9: UCLA | BL9: UCLA | BM9: IU | BN9: OSU | BO9: WIS | CT9: =H9*0.4+J9*1.2+I9*0.8 -> 25.2 | CU9: =CT9/2.4 -> 10.5 | CV9: =VLOOKUP(B9,'SODiv Index'!A:B,2,FALSE) -> 1 | CW9: =CU9*(10-CV9/5)/10 -> 10.29 | CX9: =INDEX('Stats import'!H:H,MATCH((INDEX(mapping!R:R,MATCH(INDEX(statsCategories,1,1),mapping!P:P,0),1)+INDEX(mapping!H:H,MATCH(C9,mapping!A:A,0),1)),'Stats import'!B:B,0),1) -> 2.19 | CY9: =INDEX('Stats import'!H:H,MATCH((INDEX(mapping!R:R,MATCH(INDEX(statsCategories,1,2),mapping!P:P,0),1)+INDEX(mapping!H:H,MATCH(C9,mapping!A:A,0),1)),'Stats import'!B:B,0),1) -> 19.9 | CZ9: =INDEX('Stats import'!H:H,MATCH((INDEX(mapping!R:R,MATCH(INDEX(statsCategories,1,3),mapping!P:P,0),1)+INDEX(mapping!H:H,MATCH(C9,mapping!A:A,0),1)),'Stats import'!B:B,0),1) -> 21.82 | DA9: =INDEX('Stats import'!H:H,MATCH((INDEX(mapping!R:R,MATCH(INDEX(statsCategories,1,4),mapping!P:P,0),1)+INDEX(mapping!H:H,MATCH(C9,mapping!A:A,0),1)),'Stats import'!B:B,0),1) -> 2.7 | DB9: =INDEX('Stats import'!H:H,MATCH((INDEX(mapping!R:R,MATCH(INDEX(statsCategories,1,5),mapping!P:P,0),1)+INDEX(mapping!H:H,MATCH(C9,mapping!A:A,0),1)),'Stats import'!B:B,0),1) -> 0.577 | DC9: =INDEX('Stats import'!H:H,MATCH((INDEX(mapping!R:R,MATCH(INDEX(statsCategories,1,6),mapping!P:P,0),1)+INDEX(mapping!H:H,MATCH(C9,mapping!A:A,0),1)),'Stats import'!B:B,0),1) -> 8.03 | DD9: =INDEX('Stats import'!H:H,MATCH((INDEX(mapping!R:R,MATCH(INDEX(statsCategories,1,7),mapping!P:P,0),1)+INDEX(mapping!H:H,MATCH(C9,mapping!A:A,0),1)),'Stats import'!B:B,0),1) -> 49.8 | DE9: =INDEX('Stats import'!H:H,MATCH((INDEX(mapping!R:R,MATCH(INDEX(statsCategories,1,8),mapping!P:P,0),1)+INDEX(mapping!H:H,MATCH(C9,mapping!A:A,0),1)),'Stats import'!B:B,0),1) -> 44.5 | DF9: =INDEX('Stats import'!H:H,MATCH((INDEX(mapping!R:R,MATCH(INDEX(statsCategories,1,9),mapping!P:P,0),1)+INDEX(mapping!H:H,MATCH(C9,mapping!A:A,0),1)),'Stats import'!B:B,0),1) -> 14.7 | DG9: =INDEX('Stats import'!H:H,MATCH((INDEX(mapping!R:R,MATCH(INDEX(statsCategories,1,10),mapping!P:P,0),1)+INDEX(mapping!H:H,MATCH(C9,mapping!A:A,0),1)),'Stats import'!B:B,0),1) -> 17 | DH9: =INDEX('Stats import'!H:H,MATCH((INDEX(mapping!R:R,MATCH(INDEX(statsCategories,1,11),mapping!P:P,0),1)+INDEX(mapping!H:H,MATCH(C9,mapping!A:A,0),1)),'Stats import'!B:B,0),1) -> 74.4 | DI9: =INDEX('Stats import'!H:H,MATCH((INDEX(mapping!R:R,MATCH(INDEX(statsCategories,1,12),mapping!P:P,0),1)+INDEX(mapping!H:H,MATCH(C9,mapping!A:A,0),1)),'Stats import'!B:B,0),1) -> 12.6 | DJ9: =INDEX('Stats import'!H:H,MATCH((INDEX(mapping!R:R,MATCH(INDEX(statsCategories,1,13),mapping!P:P,0),1)+INDEX(mapping!H:H,MATCH(C9,mapping!A:A,0),1)),'Stats import'!B:B,0),1) -> 7.3 | DK9: =INDEX('Stats import'!H:H,MATCH((INDEX(mapping!R:R,MATCH(INDEX(statsCategories,1,14),mapping!P:P,0),1)+INDEX(mapping!H:H,MATCH(C9,mapping!A:A,0),1)),'Stats import'!B:B,0),1) -> 24.21 | DL9: =INDEX('Stats import'!H:H,MATCH((INDEX(mapping!R:R,MATCH(INDEX(statsCategories,1,15),mapping!P:P,0),1)+INDEX(mapping!H:H,MATCH(C9,mapping!A:A,0),1)),'Stats import'!B:B,0),1) -> 11.41 | DM9: =INDEX('Stats import'!H:H,MATCH((INDEX(mapping!R:R,MATCH(INDEX(statsCategories,1,16),mapping!P:P,0),1)+INDEX(mapping!H:H,MATCH(C9,mapping!A:A,0),1)),'Stats import'!B:B,0),1) -> 35.62 | DN9: =INDEX('Stats import'!H:H,MATCH((INDEX(mapping!R:R,MATCH(INDEX(statsCategories,1,17),mapping!P:P,0),1)+INDEX(mapping!H:H,MATCH(C9,mapping!A:A,0),1)),'Stats import'!B:B,0),1) -> 70.1 | DO9: =INDEX('Stats import'!H:H,MATCH((INDEX(mapping!R:R,MATCH(INDEX(statsCategories,1,18),mapping!P:P,0),1)+INDEX(mapping!H:H,MATCH(C9,mapping!A:A,0),1)),'Stats import'!B:B,0),1) -> 11.6 | DP9: =INDEX('Stats import'!H:H,MATCH((INDEX(mapping!R:R,MATCH(INDEX(statsCategories,1,19),mapping!P:P,0),1)+INDEX(mapping!H:H,MATCH(C9,mapping!A:A,0),1)),'Stats import'!B:B,0),1) -> 81.7 | DQ9: =INDEX('Stats import'!H:H,MATCH((INDEX(mapping!R:R,MATCH(INDEX(statsCategories,1,20),mapping!P:P,0),1)+INDEX(mapping!H:H,MATCH(C9,mapping!A:A,0),1)),'Stats import'!B:B,0),1) -> 5.6 | DR9: =INDEX('Stats import'!H:H,MATCH((INDEX(mapping!R:R,MATCH(INDEX(statsCategories,1,21),mapping!P:P,0),1)+INDEX(mapping!H:H,MATCH(C9,mapping!A:A,0),1)),'Stats import'!B:B,0),1) -> 24.8 | DS9: =INDEX('Stats import'!H:H,MATCH((INDEX(mapping!R:R,MATCH(INDEX(statsCategories,1,22),mapping!P:P,0),1)+INDEX(mapping!H:H,MATCH(C9,mapping!A:A,0),1)),'Stats import'!B:B,0),1) -> 38.1 | DT9: =INDEX('Stats import'!H:H,MATCH((INDEX(mapping!R:R,MATCH(INDEX(statsCategories,1,23),mapping!P:P,0),1)+INDEX(mapping!H:H,MATCH(C9,mapping!A:A,0),1)),'Stats import'!B:B,0),1) -> 34.3 | DU9: =INDEX('Stats import'!H:H,MATCH((INDEX(mapping!R:R,MATCH(INDEX(statsCategories,1,24),mapping!P:P,0),1)+INDEX(mapping!H:H,MATCH(C9,mapping!A:A,0),1)),'Stats import'!B:B,0),1) -> 9.4 | DV9: =INDEX('Stats import'!H:H,MATCH((INDEX(mapping!R:R,MATCH(INDEX(statsCategories,1,25),mapping!P:P,0),1)+INDEX(mapping!H:H,MATCH(C9,mapping!A:A,0),1)),'Stats import'!B:B,0),1) -> 1.3 | DW9: =INDEX('Stats import'!H:H,MATCH((INDEX(mapping!R:R,MATCH(INDEX(statsCategories,1,26),mapping!P:P,0),1)+INDEX(mapping!H:H,MATCH(C9,mapping!A:A,0),1)),'Stats import'!B:B,0),1) -> 10.32 | DX9: =INDEX('Stats import'!H:H,MATCH((INDEX(mapping!R:R,MATCH(INDEX(statsCategories,1,27),mapping!P:P,0),1)+INDEX(mapping!H:H,MATCH(C9,mapping!A:A,0),1)),'Stats import'!B:B,0),1) -> 9.1 | DZ9: =R9 -> -4.8538462 | EA9: =-O9 -> -20.4 | EB9: =INDEX('KenPom import'!J:J,MATCH(INDEX(kpVal,MATCH(C9,valCol,0)),kpTeam,0)) -> 64.9 | EC9: =(CX9-INDEX(FK:FK,4,1))/INDEX(FK:FK,3,1) -> 3.1317241 | ED9: =(CY9-INDEX(FL:FL,4,1))/INDEX(FL:FL,3,1) -> 2.3914916 | EE9: =(CZ9-INDEX(FM:FM,4,1))/INDEX(FM:FM,3,1) -> 0.015648755 | EF9: =(DA9-INDEX(FN:FN,4,1))/INDEX(FN:FN,3,1) -> -1.0708126 | EG9: =(DB9-INDEX(FO:FO,4,1))/INDEX(FO:FO,3,1) -> 1.4660654 | EH9: =(DC9-INDEX(FP:FP,4,1))/INDEX(FP:FP,3,1) -> -0.97902314 | EI9: =(DD9-INDEX(FQ:FQ,4,1))/INDEX(FQ:FQ,3,1) -> 1.4099537 | EJ9: =(DE9-INDEX(FR:FR,4,1))/INDEX(FR:FR,3,1)*-1 -> -0.90644162 | EK9: =(DF9-INDEX(FS:FS,4,1))/INDEX(FS:FS,3,1)*-1 -> 1.5428687 | EL9: =(DG9-INDEX(FT:FT,4,1))/INDEX(FT:FT,3,1) -> -1.5220867 | EM9: =(DH9-INDEX(FU:FU,4,1))/INDEX(FU:FU,3,1) -> 0.25375187 | EN9: =(DI9-INDEX(FV:FV,4,1))/INDEX(FV:FV,3,1) -> -1.4164469 | EO9: =(DJ9-INDEX(FW:FW,4,1))/INDEX(FW:FW,3,1) -> 1.0121651 | EP9: =(DK9-INDEX(FX:FX,4,1))/INDEX(FX:FX,3,1) -> -0.67568172 | EQ9: =(DL9-INDEX(FY:FY,4,1))/INDEX(FY:FY,3,1) -> -0.029679341 | ER9: =(DM9-INDEX(FZ:FZ,4,1))/INDEX(FZ:FZ,3,1) -> -0.47226808 | ES9: =(DN9-INDEX(GA:GA,4,1))/INDEX(GA:GA,3,1)*-1 -> 0.30414698 | ET9: =(DO9-INDEX(GB:GB,4,1))/INDEX(GB:GB,3,1) -> 0.55257577 | EU9: =(DP9-INDEX(GC:GC,4,1))/INDEX(GC:GC,3,1) -> 0.20820194 | EV9: =(DQ9-INDEX(GD:GD,4,1))/INDEX(GD:GD,3,1) -> -1.0652352 | EW9: =(DR9-INDEX(GE:GE,4,1))/INDEX(GE:GE,3,1) -> 0.13610462 | EX9: =(DS9-INDEX(GF:GF,4,1))/INDEX(GF:GF,3,1) -> 1.3652462 | EY9: =(DT9-INDEX(GG:GG,4,1))/INDEX(GG:GG,3,1)*-1 -> -1.0368757 | EZ9: =(DU9-INDEX(GH:GH,4,1))/INDEX(GH:GH,3,1) -> 0.50250463 | FA9: =(DV9-INDEX(GI:GI,4,1))/INDEX(GI:GI,3,1) -> -0.033033458 | FB9: =(DW9-INDEX(GJ:GJ,4,1))/INDEX(GJ:GJ,3,1) -> -1.045114 | FC9: =(DX9-INDEX(GK:GK,4,1))/INDEX(GK:GK,3,1)*-1 -> 1.5547349 | FD9: =(DZ9-INDEX(GM:GM,4,1))/INDEX(GM:GM,3,1)*-1 -> 1.1092648 | FE9: =(EA9-INDEX(GN:GN,4,1))/INDEX(GN:GN,3,1)*-1 -> 1.1822394 | FF9: =(EB9-INDEX(GO:GO,4,1))/INDEX(GO:GO,3,1) -> -1.141172 | FG9: =(((DP9-DI9-3*DU9)/2)+1.5*DU9)/DB9-DR9 -> 35.078683 | FH9: =DR9/(DR9+FG9) -> 0.41417077
A10: 7 | B10: WCC | C10: Gonzaga | D10: Bulldogs | E10: 3 | F10: WIN | H10: =_xlfn.IFNA(INDEX(importBPIRkCol,MATCH(INDEX(espnMap,MATCH(C10,valCol,0)),bpiImportCol,0)+rowOffset),INDEX(importBPIRkCol,MATCH(INDEX(espnMap2,MATCH(C10,valCol,0)),bpiImportCol,0)+rowOffset)) -> 8 | I10: =IFERROR(INDEX('Net Import'!A:A,MATCH(INDEX(mapping!B:B,MATCH(C10,mapping!A:A,0),1),'Net Import'!B:B,0),1),0) -> 6 | J10: =_xlfn.IFNA(INDEX(sorRkCol,MATCH(INDEX(espnMap,MATCH(C10,valCol,0)),sorTeamCol,0)+sorRowOffset),INDEX(sorRkCol,MATCH(INDEX(espnMap2,MATCH(C10,valCol,0)),sorTeamCol,0)+sorRowOffset)) -> 11 | K10: 12 | L10: 4 | M10: =CW10+R10*1.8+IF(K10>0,K10-26,0)/2+IF(CV10>0.5,0,10)-0.5*O10-IF(F10="WIN",1,IF(F10="IN",0.5,0))-S10+IF(W10>13.5,2,0)-IF(W10<6,6-W10,0) -> -24.826077 | N10: =IF(COUNTIF(H10:J10,"<50.5")>1.5,1,0) -> 1 | O10: =_xlfn.IFNA(INDEX(importBPICol,MATCH(INDEX(espnMap,MATCH(C10,valCol,0)),bpiImportCol,0)+rowOffset), INDEX(importBPICol,MATCH(INDEX(espnMap2,MATCH(C10,valCol,0)),bpiImportCol,0)+rowOffset)) -> 20.7 | P10: =INDEX(kpOff,MATCH(INDEX(kpVal,MATCH(C10,valCol,0)),kpTeam,0)) -> 34 | Q10: =INDEX(kpDef,MATCH(INDEX(kpVal,MATCH(C10,valCol,0)),kpTeam,0)) -> 8 | R10: =-1*INDEX(calculatedResVal,MATCH(C10,resValueTeamCol,0)) -> -2.8711538 | S10: 7 | T10: 1 | U10: =COUNTA(AW10:BK10)+COUNTA(Y10:AJ10) -> 7 | V10: =COUNTA(BL10:BX10)+COUNTA(AK10:AV10) -> 2 | W10: =COUNTA(AK10:AV10)+COUNTA(BL10:CS10) -> 3 | X10: =IF(SUM(S10:W10)>0,1,0) -> 1 | Y10: CREI | Z10: ALA | AA10: UK | AB10: UCLA | AK10: MICH | AW10: SMC | AX10: SCU | AY10: SCU | BL10: SMC | BY10: PORT | CT10: =H10*0.4+J10*1.2+I10*0.8 -> 21.2 | CU10: =CT10/2.4 -> 8.8333333 | CV10: =VLOOKUP(B10,'SODiv Index'!A:B,2,FALSE) -> 0.8 | CW10: =CU10*(10-CV10/5)/10 -> 8.692 | CX10: =INDEX('Stats import'!H:H,MATCH((INDEX(mapping!R:R,MATCH(INDEX(statsCategories,1,1),mapping!P:P,0),1)+INDEX(mapping!H:H,MATCH(C10,mapping!A:A,0),1)),'Stats import'!B:B,0),1) -> 1.9 | CY10: =INDEX('Stats import'!H:H,MATCH((INDEX(mapping!R:R,MATCH(INDEX(statsCategories,1,2),mapping!P:P,0),1)+INDEX(mapping!H:H,MATCH(C10,mapping!A:A,0),1)),'Stats import'!B:B,0),1) -> 18.3 | CZ10: =INDEX('Stats import'!H:H,MATCH((INDEX(mapping!R:R,MATCH(INDEX(statsCategories,1,3),mapping!P:P,0),1)+INDEX(mapping!H:H,MATCH(C10,mapping!A:A,0),1)),'Stats import'!B:B,0),1) -> 34.73 | DA10: =INDEX('Stats import'!H:H,MATCH((INDEX(mapping!R:R,MATCH(INDEX(statsCategories,1,4),mapping!P:P,0),1)+INDEX(mapping!H:H,MATCH(C10,mapping!A:A,0),1)),'Stats import'!B:B,0),1) -> 3.7 | DB10: =INDEX('Stats import'!H:H,MATCH((INDEX(mapping!R:R,MATCH(INDEX(statsCategories,1,5),mapping!P:P,0),1)+INDEX(mapping!H:H,MATCH(C10,mapping!A:A,0),1)),'Stats import'!B:B,0),1) -> 0.563 | DC10: =INDEX('Stats import'!H:H,MATCH((INDEX(mapping!R:R,MATCH(INDEX(statsCategories,1,6),mapping!P:P,0),1)+INDEX(mapping!H:H,MATCH(C10,mapping!A:A,0),1)),'Stats import'!B:B,0),1) -> 15.24 | DD10: =INDEX('Stats import'!H:H,MATCH((INDEX(mapping!R:R,MATCH(INDEX(statsCategories,1,7),mapping!P:P,0),1)+INDEX(mapping!H:H,MATCH(C10,mapping!A:A,0),1)),'Stats import'!B:B,0),1) -> 51 | DE10: =INDEX('Stats import'!H:H,MATCH((INDEX(mapping!R:R,MATCH(INDEX(statsCategories,1,8),mapping!P:P,0),1)+INDEX(mapping!H:H,MATCH(C10,mapping!A:A,0),1)),'Stats import'!B:B,0),1) -> 39.5 | DF10: =INDEX('Stats import'!H:H,MATCH((INDEX(mapping!R:R,MATCH(INDEX(statsCategories,1,9),mapping!P:P,0),1)+INDEX(mapping!H:H,MATCH(C10,mapping!A:A,0),1)),'Stats import'!B:B,0),1) -> 16.8 | DG10: =INDEX('Stats import'!H:H,MATCH((INDEX(mapping!R:R,MATCH(INDEX(statsCategories,1,10),mapping!P:P,0),1)+INDEX(mapping!H:H,MATCH(C10,mapping!A:A,0),1)),'Stats import'!B:B,0),1) -> 19.7 | DH10: =INDEX('Stats import'!H:H,MATCH((INDEX(mapping!R:R,MATCH(INDEX(statsCategories,1,11),mapping!P:P,0),1)+INDEX(mapping!H:H,MATCH(C10,mapping!A:A,0),1)),'Stats import'!B:B,0),1) -> 69.9 | DI10: =INDEX('Stats import'!H:H,MATCH((INDEX(mapping!R:R,MATCH(INDEX(statsCategories,1,12),mapping!P:P,0),1)+INDEX(mapping!H:H,MATCH(C10,mapping!A:A,0),1)),'Stats import'!B:B,0),1) -> 13.8 | DJ10: =INDEX('Stats import'!H:H,MATCH((INDEX(mapping!R:R,MATCH(INDEX(statsCategories,1,13),mapping!P:P,0),1)+INDEX(mapping!H:H,MATCH(C10,mapping!A:A,0),1)),'Stats import'!B:B,0),1) -> 7.7 | DK10: =INDEX('Stats import'!H:H,MATCH((INDEX(mapping!R:R,MATCH(INDEX(statsCategories,1,14),mapping!P:P,0),1)+INDEX(mapping!H:H,MATCH(C10,mapping!A:A,0),1)),'Stats import'!B:B,0),1) -> 27.94 | DL10: =INDEX('Stats import'!H:H,MATCH((INDEX(mapping!R:R,MATCH(INDEX(statsCategories,1,15),mapping!P:P,0),1)+INDEX(mapping!H:H,MATCH(C10,mapping!A:A,0),1)),'Stats import'!B:B,0),1) -> 11.97 | DM10: =INDEX('Stats import'!H:H,MATCH((INDEX(mapping!R:R,MATCH(INDEX(statsCategories,1,16),mapping!P:P,0),1)+INDEX(mapping!H:H,MATCH(C10,mapping!A:A,0),1)),'Stats import'!B:B,0),1) -> 39.91 | DN10: =INDEX('Stats import'!H:H,MATCH((INDEX(mapping!R:R,MATCH(INDEX(statsCategories,1,17),mapping!P:P,0),1)+INDEX(mapping!H:H,MATCH(C10,mapping!A:A,0),1)),'Stats import'!B:B,0),1) -> 66 | DO10: =INDEX('Stats import'!H:H,MATCH((INDEX(mapping!R:R,MATCH(INDEX(statsCategories,1,18),mapping!P:P,0),1)+INDEX(mapping!H:H,MATCH(C10,mapping!A:A,0),1)),'Stats import'!B:B,0),1) -> 19.1 | DP10: =INDEX('Stats import'!H:H,MATCH((INDEX(mapping!R:R,MATCH(INDEX(statsCategories,1,19),mapping!P:P,0),1)+INDEX(mapping!H:H,MATCH(C10,mapping!A:A,0),1)),'Stats import'!B:B,0),1) -> 85.1 | DQ10: =INDEX('Stats import'!H:H,MATCH((INDEX(mapping!R:R,MATCH(INDEX(statsCategories,1,20),mapping!P:P,0),1)+INDEX(mapping!H:H,MATCH(C10,mapping!A:A,0),1)),'Stats import'!B:B,0),1) -> 8.5 | DR10: =INDEX('Stats import'!H:H,MATCH((INDEX(mapping!R:R,MATCH(INDEX(statsCategories,1,21),mapping!P:P,0),1)+INDEX(mapping!H:H,MATCH(C10,mapping!A:A,0),1)),'Stats import'!B:B,0),1) -> 19.6 | DS10: =INDEX('Stats import'!H:H,MATCH((INDEX(mapping!R:R,MATCH(INDEX(statsCategories,1,22),mapping!P:P,0),1)+INDEX(mapping!H:H,MATCH(C10,mapping!A:A,0),1)),'Stats import'!B:B,0),1) -> 34 | DT10: =INDEX('Stats import'!H:H,MATCH((INDEX(mapping!R:R,MATCH(INDEX(statsCategories,1,23),mapping!P:P,0),1)+INDEX(mapping!H:H,MATCH(C10,mapping!A:A,0),1)),'Stats import'!B:B,0),1) -> 30.8 | DU10: =INDEX('Stats import'!H:H,MATCH((INDEX(mapping!R:R,MATCH(INDEX(statsCategories,1,24),mapping!P:P,0),1)+INDEX(mapping!H:H,MATCH(C10,mapping!A:A,0),1)),'Stats import'!B:B,0),1) -> 6.7 | DV10: =INDEX('Stats import'!H:H,MATCH((INDEX(mapping!R:R,MATCH(INDEX(statsCategories,1,25),mapping!P:P,0),1)+INDEX(mapping!H:H,MATCH(C10,mapping!A:A,0),1)),'Stats import'!B:B,0),1) -> 4.8 | DW10: =INDEX('Stats import'!H:H,MATCH((INDEX(mapping!R:R,MATCH(INDEX(statsCategories,1,26),mapping!P:P,0),1)+INDEX(mapping!H:H,MATCH(C10,mapping!A:A,0),1)),'Stats import'!B:B,0),1) -> 14.45 | DX10: =INDEX('Stats import'!H:H,MATCH((INDEX(mapping!R:R,MATCH(INDEX(statsCategories,1,27),mapping!P:P,0),1)+INDEX(mapping!H:H,MATCH(C10,mapping!A:A,0),1)),'Stats import'!B:B,0),1) -> 9.7 | DZ10: =R10 -> -2.8711538 | EA10: =-O10 -> -20.7 | EB10: =INDEX('KenPom import'!J:J,MATCH(INDEX(kpVal,MATCH(C10,valCol,0)),kpTeam,0)) -> 69.1 | EC10: =(CX10-INDEX(FK:FK,4,1))/INDEX(FK:FK,3,1) -> 1.9099989 | ED10: =(CY10-INDEX(FL:FL,4,1))/INDEX(FL:FL,3,1) -> 1.5440084 | EE10: =(CZ10-INDEX(FM:FM,4,1))/INDEX(FM:FM,3,1) -> 2.1118918 | EF10: =(DA10-INDEX(FN:FN,4,1))/INDEX(FN:FN,3,1) -> -0.052203706 | EG10: =(DB10-INDEX(FO:FO,4,1))/INDEX(FO:FO,3,1) -> 0.89809819 | EH10: =(DC10-INDEX(FP:FP,4,1))/INDEX(FP:FP,3,1) -> 1.2279591 | EI10: =(DD10-INDEX(FQ:FQ,4,1))/INDEX(FQ:FQ,3,1) -> 1.9979449 | EJ10: =(DE10-INDEX(FR:FR,4,1))/INDEX(FR:FR,3,1)*-1 -> 1.5011058 | EK10: =(DF10-INDEX(FS:FS,4,1))/INDEX(FS:FS,3,1)*-1 -> 0.20263116 | EL10: =(DG10-INDEX(FT:FT,4,1))/INDEX(FT:FT,3,1) -> -0.59335582 | EM10: =(DH10-INDEX(FU:FU,4,1))/INDEX(FU:FU,3,1) -> -1.2172735 | EN10: =(DI10-INDEX(FV:FV,4,1))/INDEX(FV:FV,3,1) -> -0.88109692 | EO10: =(DJ10-INDEX(FW:FW,4,1))/INDEX(FW:FW,3,1) -> 1.1217364 | EP10: =(DK10-INDEX(FX:FX,4,1))/INDEX(FX:FX,3,1) -> 1.3441883 | EQ10: =(DL10-INDEX(FY:FY,4,1))/INDEX(FY:FY,3,1) -> 0.3010755 | ER10: =(DM10-INDEX(FZ:FZ,4,1))/INDEX(FZ:FZ,3,1) -> 1.0895204 | ES10: =(DN10-INDEX(GA:GA,4,1))/INDEX(GA:GA,3,1)*-1 -> 1.1909044 | ET10: =(DO10-INDEX(GB:GB,4,1))/INDEX(GB:GB,3,1) -> 2.2432717 | EU10: =(DP10-INDEX(GC:GC,4,1))/INDEX(GC:GC,3,1) -> 0.88237966 | EV10: =(DQ10-INDEX(GD:GD,4,1))/INDEX(GD:GD,3,1) -> 1.1045151 | EW10: =(DR10-INDEX(GE:GE,4,1))/INDEX(GE:GE,3,1) -> -1.1595366 | EX10: =(DS10-INDEX(GF:GF,4,1))/INDEX(GF:GF,3,1) -> -0.68888571 | EY10: =(DT10-INDEX(GG:GG,4,1))/INDEX(GG:GG,3,1)*-1 -> 0.97647513 | EZ10: =(DU10-INDEX(GH:GH,4,1))/INDEX(GH:GH,3,1) -> -1.198765 | FA10: =(DV10-INDEX(GI:GI,4,1))/INDEX(GI:GI,3,1) -> 1.7805682 | FB10: =(DW10-INDEX(GJ:GJ,4,1))/INDEX(GJ:GJ,3,1) -> 1.3455372 | FC10: =(DX10-INDEX(GK:GK,4,1))/INDEX(GK:GK,3,1)*-1 -> 0.99108481 | FD10: =(DZ10-INDEX(GM:GM,4,1))/INDEX(GM:GM,3,1)*-1 -> 0.90455149 | FE10: =(EA10-INDEX(GN:GN,4,1))/INDEX(GN:GN,3,1)*-1 -> 1.2208064 | FF10: =(EB10-INDEX(GO:GO,4,1))/INDEX(GO:GO,3,1) -> 0.60012586 | FG10: =(((DP10-DI10-3*DU10)/2)+1.5*DU10)/DB10-DR10 -> 43.721492 | FH10: =DR10/(DR10+FG10) -> 0.30953156
A11: 9 | B11: ACC | C11: Virginia | D11: Cavaliers | E11: 3 | F11: OUT | H11: =_xlfn.IFNA(INDEX(importBPIRkCol,MATCH(INDEX(espnMap,MATCH(C11,valCol,0)),bpiImportCol,0)+rowOffset),INDEX(importBPIRkCol,MATCH(INDEX(espnMap2,MATCH(C11,valCol,0)),bpiImportCol,0)+rowOffset)) -> 20 | I11: =IFERROR(INDEX('Net Import'!A:A,MATCH(INDEX(mapping!B:B,MATCH(C11,mapping!A:A,0),1),'Net Import'!B:B,0),1),0) -> 12 | J11: =_xlfn.IFNA(INDEX(sorRkCol,MATCH(INDEX(espnMap,MATCH(C11,valCol,0)),sorTeamCol,0)+sorRowOffset),INDEX(sorRkCol,MATCH(INDEX(espnMap2,MATCH(C11,valCol,0)),sorTeamCol,0)+sorRowOffset)) -> 8 | K11: 10 | L11: 3 | M11: =CW11+R11*1.8+IF(K11>0,K11-26,0)/2+IF(CV11>0.5,0,10)-0.5*O11-IF(F11="WIN",1,IF(F11="IN",0.5,0))-S11+IF(W11>13.5,2,0)-IF(W11<6,6-W11,0) -> -22.077103 | N11: =IF(COUNTIF(H11:J11,"<50.5")>1.5,1,0) -> 1 | O11: =_xlfn.IFNA(INDEX(importBPICol,MATCH(INDEX(espnMap,MATCH(C11,valCol,0)),bpiImportCol,0)+rowOffset), INDEX(importBPICol,MATCH(INDEX(espnMap2,MATCH(C11,valCol,0)),bpiImportCol,0)+rowOffset)) -> 16.7 | P11: =INDEX(kpOff,MATCH(INDEX(kpVal,MATCH(C11,valCol,0)),kpTeam,0)) -> 33 | Q11: =INDEX(kpDef,MATCH(INDEX(kpVal,MATCH(C11,valCol,0)),kpTeam,0)) -> 16 | R11: =-1*INDEX(calculatedResVal,MATCH(C11,resValueTeamCol,0)) -> -5.4632051 | S11: 6 | T11: 2 | U11: =COUNTA(AW11:BK11)+COUNTA(Y11:AJ11) -> 11 | V11: =COUNTA(BL11:BX11)+COUNTA(AK11:AV11) -> 4 | W11: =COUNTA(AK11:AV11)+COUNTA(BL11:CS11) -> 5 | X11: =IF(SUM(S11:W11)>0,1,0) -> 1 | Y11: LOU | AK11: UNC | AL11: DUKE | AM11: DUKE | AW11: TEX | AX11: NCSU | AY11: OSU | AZ11: SMU | BA11: CAL | BB11: MIA | BC11: NCSU | BD11: VT | BE11: NCSU | BF11: MIA | BL11: VT | BY11: BUT | CT11: =H11*0.4+J11*1.2+I11*0.8 -> 27.2 | CU11: =CT11/2.4 -> 11.333333 | CV11: =VLOOKUP(B11,'SODiv Index'!A:B,2,FALSE) -> 1 | CW11: =CU11*(10-CV11/5)/10 -> 11.106667 | CX11: =INDEX('Stats import'!H:H,MATCH((INDEX(mapping!R:R,MATCH(INDEX(statsCategories,1,1),mapping!P:P,0),1)+INDEX(mapping!H:H,MATCH(C11,mapping!A:A,0),1)),'Stats import'!B:B,0),1) -> 1.53 | CY11: =INDEX('Stats import'!H:H,MATCH((INDEX(mapping!R:R,MATCH(INDEX(statsCategories,1,2),mapping!P:P,0),1)+INDEX(mapping!H:H,MATCH(C11,mapping!A:A,0),1)),'Stats import'!B:B,0),1) -> 16.6 | CZ11: =INDEX('Stats import'!H:H,MATCH((INDEX(mapping!R:R,MATCH(INDEX(statsCategories,1,3),mapping!P:P,0),1)+INDEX(mapping!H:H,MATCH(C11,mapping!A:A,0),1)),'Stats import'!B:B,0),1) -> 28.59 | DA11: =INDEX('Stats import'!H:H,MATCH((INDEX(mapping!R:R,MATCH(INDEX(statsCategories,1,4),mapping!P:P,0),1)+INDEX(mapping!H:H,MATCH(C11,mapping!A:A,0),1)),'Stats import'!B:B,0),1) -> 6.5 | DB11: =INDEX('Stats import'!H:H,MATCH((INDEX(mapping!R:R,MATCH(INDEX(statsCategories,1,5),mapping!P:P,0),1)+INDEX(mapping!H:H,MATCH(C11,mapping!A:A,0),1)),'Stats import'!B:B,0),1) -> 0.546 | DC11: =INDEX('Stats import'!H:H,MATCH((INDEX(mapping!R:R,MATCH(INDEX(statsCategories,1,6),mapping!P:P,0),1)+INDEX(mapping!H:H,MATCH(C11,mapping!A:A,0),1)),'Stats import'!B:B,0),1) -> 11.62 | DD11: =INDEX('Stats import'!H:H,MATCH((INDEX(mapping!R:R,MATCH(INDEX(statsCategories,1,7),mapping!P:P,0),1)+INDEX(mapping!H:H,MATCH(C11,mapping!A:A,0),1)),'Stats import'!B:B,0),1) -> 46.3 | DE11: =INDEX('Stats import'!H:H,MATCH((INDEX(mapping!R:R,MATCH(INDEX(statsCategories,1,8),mapping!P:P,0),1)+INDEX(mapping!H:H,MATCH(C11,mapping!A:A,0),1)),'Stats import'!B:B,0),1) -> 39.5 | DF11: =INDEX('Stats import'!H:H,MATCH((INDEX(mapping!R:R,MATCH(INDEX(statsCategories,1,9),mapping!P:P,0),1)+INDEX(mapping!H:H,MATCH(C11,mapping!A:A,0),1)),'Stats import'!B:B,0),1) -> 17.6 | DG11: =INDEX('Stats import'!H:H,MATCH((INDEX(mapping!R:R,MATCH(INDEX(statsCategories,1,10),mapping!P:P,0),1)+INDEX(mapping!H:H,MATCH(C11,mapping!A:A,0),1)),'Stats import'!B:B,0),1) -> 20 | DH11: =INDEX('Stats import'!H:H,MATCH((INDEX(mapping!R:R,MATCH(INDEX(statsCategories,1,11),mapping!P:P,0),1)+INDEX(mapping!H:H,MATCH(C11,mapping!A:A,0),1)),'Stats import'!B:B,0),1) -> 72.6 | DI11: =INDEX('Stats import'!H:H,MATCH((INDEX(mapping!R:R,MATCH(INDEX(statsCategories,1,12),mapping!P:P,0),1)+INDEX(mapping!H:H,MATCH(C11,mapping!A:A,0),1)),'Stats import'!B:B,0),1) -> 14.5 | DJ11: =INDEX('Stats import'!H:H,MATCH((INDEX(mapping!R:R,MATCH(INDEX(statsCategories,1,13),mapping!P:P,0),1)+INDEX(mapping!H:H,MATCH(C11,mapping!A:A,0),1)),'Stats import'!B:B,0),1) -> 7.4 | DK11: =INDEX('Stats import'!H:H,MATCH((INDEX(mapping!R:R,MATCH(INDEX(statsCategories,1,14),mapping!P:P,0),1)+INDEX(mapping!H:H,MATCH(C11,mapping!A:A,0),1)),'Stats import'!B:B,0),1) -> 27 | DL11: =INDEX('Stats import'!H:H,MATCH((INDEX(mapping!R:R,MATCH(INDEX(statsCategories,1,15),mapping!P:P,0),1)+INDEX(mapping!H:H,MATCH(C11,mapping!A:A,0),1)),'Stats import'!B:B,0),1) -> 13.21 | DM11: =INDEX('Stats import'!H:H,MATCH((INDEX(mapping!R:R,MATCH(INDEX(statsCategories,1,16),mapping!P:P,0),1)+INDEX(mapping!H:H,MATCH(C11,mapping!A:A,0),1)),'Stats import'!B:B,0),1) -> 40.21 | DN11: =INDEX('Stats import'!H:H,MATCH((INDEX(mapping!R:R,MATCH(INDEX(statsCategories,1,17),mapping!P:P,0),1)+INDEX(mapping!H:H,MATCH(C11,mapping!A:A,0),1)),'Stats import'!B:B,0),1) -> 68.4 | DO11: =INDEX('Stats import'!H:H,MATCH((INDEX(mapping!R:R,MATCH(INDEX(statsCategories,1,18),mapping!P:P,0),1)+INDEX(mapping!H:H,MATCH(C11,mapping!A:A,0),1)),'Stats import'!B:B,0),1) -> 12.2 | DP11: =INDEX('Stats import'!H:H,MATCH((INDEX(mapping!R:R,MATCH(INDEX(statsCategories,1,19),mapping!P:P,0),1)+INDEX(mapping!H:H,MATCH(C11,mapping!A:A,0),1)),'Stats import'!B:B,0),1) -> 80.6 | DQ11: =INDEX('Stats import'!H:H,MATCH((INDEX(mapping!R:R,MATCH(INDEX(statsCategories,1,20),mapping!P:P,0),1)+INDEX(mapping!H:H,MATCH(C11,mapping!A:A,0),1)),'Stats import'!B:B,0),1) -> 6.4 | DR11: =INDEX('Stats import'!H:H,MATCH((INDEX(mapping!R:R,MATCH(INDEX(statsCategories,1,21),mapping!P:P,0),1)+INDEX(mapping!H:H,MATCH(C11,mapping!A:A,0),1)),'Stats import'!B:B,0),1) -> 28.1 | DS11: =INDEX('Stats import'!H:H,MATCH((INDEX(mapping!R:R,MATCH(INDEX(statsCategories,1,22),mapping!P:P,0),1)+INDEX(mapping!H:H,MATCH(C11,mapping!A:A,0),1)),'Stats import'!B:B,0),1) -> 35.9 | DT11: =INDEX('Stats import'!H:H,MATCH((INDEX(mapping!R:R,MATCH(INDEX(statsCategories,1,23),mapping!P:P,0),1)+INDEX(mapping!H:H,MATCH(C11,mapping!A:A,0),1)),'Stats import'!B:B,0),1) -> 30.9 | DU11: =INDEX('Stats import'!H:H,MATCH((INDEX(mapping!R:R,MATCH(INDEX(statsCategories,1,24),mapping!P:P,0),1)+INDEX(mapping!H:H,MATCH(C11,mapping!A:A,0),1)),'Stats import'!B:B,0),1) -> 10.1 | DV11: =INDEX('Stats import'!H:H,MATCH((INDEX(mapping!R:R,MATCH(INDEX(statsCategories,1,25),mapping!P:P,0),1)+INDEX(mapping!H:H,MATCH(C11,mapping!A:A,0),1)),'Stats import'!B:B,0),1) -> -0.3 | DW11: =INDEX('Stats import'!H:H,MATCH((INDEX(mapping!R:R,MATCH(INDEX(statsCategories,1,26),mapping!P:P,0),1)+INDEX(mapping!H:H,MATCH(C11,mapping!A:A,0),1)),'Stats import'!B:B,0),1) -> 10.56 | DX11: =INDEX('Stats import'!H:H,MATCH((INDEX(mapping!R:R,MATCH(INDEX(statsCategories,1,27),mapping!P:P,0),1)+INDEX(mapping!H:H,MATCH(C11,mapping!A:A,0),1)),'Stats import'!B:B,0),1) -> 10.8 | DZ11: =R11 -> -5.4632051 | EA11: =-O11 -> -16.7 | EB11: =INDEX('KenPom import'!J:J,MATCH(INDEX(kpVal,MATCH(C11,valCol,0)),kpTeam,0)) -> 65.8 | EC11: =(CX11-INDEX(FK:FK,4,1))/INDEX(FK:FK,3,1) -> 0.351246 | ED11: =(CY11-INDEX(FL:FL,4,1))/INDEX(FL:FL,3,1) -> 0.64355753 | EE11: =(CZ11-INDEX(FM:FM,4,1))/INDEX(FM:FM,3,1) -> 1.114918 | EF11: =(DA11-INDEX(FN:FN,4,1))/INDEX(FN:FN,3,1) -> 2.7999012 | EG11: =(DB11-INDEX(FO:FO,4,1))/INDEX(FO:FO,3,1) -> 0.20842369 | EH11: =(DC11-INDEX(FP:FP,4,1))/INDEX(FP:FP,3,1) -> 0.11987648 | EI11: =(DD11-INDEX(FQ:FQ,4,1))/INDEX(FQ:FQ,3,1) -> -0.3050204 | EJ11: =(DE11-INDEX(FR:FR,4,1))/INDEX(FR:FR,3,1)*-1 -> 1.5011058 | EK11: =(DF11-INDEX(FS:FS,4,1))/INDEX(FS:FS,3,1)*-1 -> -0.30793554 | EL11: =(DG11-INDEX(FT:FT,4,1))/INDEX(FT:FT,3,1) -> -0.49016351 | EM11: =(DH11-INDEX(FU:FU,4,1))/INDEX(FU:FU,3,1) -> -0.33465826 | EN11: =(DI11-INDEX(FV:FV,4,1))/INDEX(FV:FV,3,1) -> -0.5688094 | EO11: =(DJ11-INDEX(FW:FW,4,1))/INDEX(FW:FW,3,1) -> 1.0395579 | EP11: =(DK11-INDEX(FX:FX,4,1))/INDEX(FX:FX,3,1) -> 0.8351594 | EQ11: =(DL11-INDEX(FY:FY,4,1))/INDEX(FY:FY,3,1) -> 1.0334612 | ER11: =(DM11-INDEX(FZ:FZ,4,1))/INDEX(FZ:FZ,3,1) -> 1.1987363 | ES11: =(DN11-INDEX(GA:GA,4,1))/INDEX(GA:GA,3,1)*-1 -> 0.6718269 | ET11: =(DO11-INDEX(GB:GB,4,1))/INDEX(GB:GB,3,1) -> 0.68783144 | EU11: =(DP11-INDEX(GC:GC,4,1))/INDEX(GC:GC,3,1) -> -0.0099143782 | EV11: =(DQ11-INDEX(GD:GD,4,1))/INDEX(GD:GD,3,1) -> -0.46668336 | EW11: =(DR11-INDEX(GE:GE,4,1))/INDEX(GE:GE,3,1) -> 0.95833851 | EX11: =(DS11-INDEX(GF:GF,4,1))/INDEX(GF:GF,3,1) -> 0.26302909 | EY11: =(DT11-INDEX(GG:GG,4,1))/INDEX(GG:GG,3,1)*-1 -> 0.91895083 | EZ11: =(DU11-INDEX(GH:GH,4,1))/INDEX(GH:GH,3,1) -> 0.94357453 | FA11: =(DV11-INDEX(GI:GI,4,1))/INDEX(GI:GI,3,1) -> -0.86210849 | FB11: =(DW11-INDEX(GJ:GJ,4,1))/INDEX(GJ:GJ,3,1) -> -0.90618993 | FC11: =(DX11-INDEX(GK:GK,4,1))/INDEX(GK:GK,3,1)*-1 -> -0.04227376 | FD11: =(DZ11-INDEX(GM:GM,4,1))/INDEX(GM:GM,3,1)*-1 -> 1.1721813 | FE11: =(EA11-INDEX(GN:GN,4,1))/INDEX(GN:GN,3,1)*-1 -> 0.70657966 | FF11: =(EB11-INDEX(GO:GO,4,1))/INDEX(GO:GO,3,1) -> -0.76803673 | FG11: =(((DP11-DI11-3*DU11)/2)+1.5*DU11)/DB11-DR11 -> 32.431136 | FH11: =DR11/(DR11+FG11) -> 0.4642239
A12: 11 | B12: Big Ten | C12: Michigan State | D12: Spartans | E12: 3 | F12: OUT | H12: =_xlfn.IFNA(INDEX(importBPIRkCol,MATCH(INDEX(espnMap,MATCH(C12,valCol,0)),bpiImportCol,0)+rowOffset),INDEX(importBPIRkCol,MATCH(INDEX(espnMap2,MATCH(C12,valCol,0)),bpiImportCol,0)+rowOffset)) -> 13 | I12: =IFERROR(INDEX('Net Import'!A:A,MATCH(INDEX(mapping!B:B,MATCH(C12,mapping!A:A,0),1),'Net Import'!B:B,0),1),0) -> 11 | J12: =_xlfn.IFNA(INDEX(sorRkCol,MATCH(INDEX(espnMap,MATCH(C12,valCol,0)),sorTeamCol,0)+sorRowOffset),INDEX(sorRkCol,MATCH(INDEX(espnMap2,MATCH(C12,valCol,0)),sorTeamCol,0)+sorRowOffset)) -> 13 | K12: 8 | L12: 2 | M12: =CW12+R12*1.8+IF(K12>0,K12-26,0)/2+IF(CV12>0.5,0,10)-0.5*O12-IF(F12="WIN",1,IF(F12="IN",0.5,0))-S12+IF(W12>13.5,2,0)-IF(W12<6,6-W12,0) -> -21.336949 | N12: =IF(COUNTIF(H12:J12,"<50.5")>1.5,1,0) -> 1 | O12: =_xlfn.IFNA(INDEX(importBPICol,MATCH(INDEX(espnMap,MATCH(C12,valCol,0)),bpiImportCol,0)+rowOffset), INDEX(importBPICol,MATCH(INDEX(espnMap2,MATCH(C12,valCol,0)),bpiImportCol,0)+rowOffset)) -> 18.4 | P12: =INDEX(kpOff,MATCH(INDEX(kpVal,MATCH(C12,valCol,0)),kpTeam,0)) -> 27 | Q12: =INDEX(kpDef,MATCH(INDEX(kpVal,MATCH(C12,valCol,0)),kpTeam,0)) -> 9 | R12: =-1*INDEX(calculatedResVal,MATCH(C12,resValueTeamCol,0)) -> -5.1242308 | S12: 6 | T12: 2 | U12: =COUNTA(AW12:BK12)+COUNTA(Y12:AJ12) -> 11 | V12: =COUNTA(BL12:BX12)+COUNTA(AK12:AV12) -> 6 | W12: =COUNTA(AK12:AV12)+COUNTA(BL12:CS12) -> 7 | X12: =IF(SUM(S12:W12)>0,1,0) -> 1 | Y12: ARK | Z12: UK | AA12: UNC | AB12: ILL | AC12: PUR | AK12: DUKE | AL12: NEB | AM12: MICH | AN12: MICH | AW12: IOWA | AX12: USC | AY12: IU | AZ12: UCLA | BA12: OSU | BB12: IU | BL12: WIS | BM12: UCLA | BY12: MINN | CT12: =H12*0.4+J12*1.2+I12*0.8 -> 29.6 | CU12: =CT12/2.4 -> 12.333333 | CV12: =VLOOKUP(B12,'SODiv Index'!A:B,2,FALSE) -> 1 | CW12: =CU12*(10-CV12/5)/10 -> 12.086667 | CX12: =INDEX('Stats import'!H:H,MATCH((INDEX(mapping!R:R,MATCH(INDEX(statsCategories,1,1),mapping!P:P,0),1)+INDEX(mapping!H:H,MATCH(C12,mapping!A:A,0),1)),'Stats import'!B:B,0),1) -> 1.61 | CY12: =INDEX('Stats import'!H:H,MATCH((INDEX(mapping!R:R,MATCH(INDEX(statsCategories,1,2),mapping!P:P,0),1)+INDEX(mapping!H:H,MATCH(C12,mapping!A:A,0),1)),'Stats import'!B:B,0),1) -> 18.5 | CZ12: =INDEX('Stats import'!H:H,MATCH((INDEX(mapping!R:R,MATCH(INDEX(statsCategories,1,3),mapping!P:P,0),1)+INDEX(mapping!H:H,MATCH(C12,mapping!A:A,0),1)),'Stats import'!B:B,0),1) -> 21.38 | DA12: =INDEX('Stats import'!H:H,MATCH((INDEX(mapping!R:R,MATCH(INDEX(statsCategories,1,4),mapping!P:P,0),1)+INDEX(mapping!H:H,MATCH(C12,mapping!A:A,0),1)),'Stats import'!B:B,0),1) -> 4.1 | DB12: =INDEX('Stats import'!H:H,MATCH((INDEX(mapping!R:R,MATCH(INDEX(statsCategories,1,5),mapping!P:P,0),1)+INDEX(mapping!H:H,MATCH(C12,mapping!A:A,0),1)),'Stats import'!B:B,0),1) -> 0.536 | DC12: =INDEX('Stats import'!H:H,MATCH((INDEX(mapping!R:R,MATCH(INDEX(statsCategories,1,6),mapping!P:P,0),1)+INDEX(mapping!H:H,MATCH(C12,mapping!A:A,0),1)),'Stats import'!B:B,0),1) -> 16.06 | DD12: =INDEX('Stats import'!H:H,MATCH((INDEX(mapping!R:R,MATCH(INDEX(statsCategories,1,7),mapping!P:P,0),1)+INDEX(mapping!H:H,MATCH(C12,mapping!A:A,0),1)),'Stats import'!B:B,0),1) -> 47.1 | DE12: =INDEX('Stats import'!H:H,MATCH((INDEX(mapping!R:R,MATCH(INDEX(statsCategories,1,8),mapping!P:P,0),1)+INDEX(mapping!H:H,MATCH(C12,mapping!A:A,0),1)),'Stats import'!B:B,0),1) -> 41 | DF12: =INDEX('Stats import'!H:H,MATCH((INDEX(mapping!R:R,MATCH(INDEX(statsCategories,1,9),mapping!P:P,0),1)+INDEX(mapping!H:H,MATCH(C12,mapping!A:A,0),1)),'Stats import'!B:B,0),1) -> 16.3 | DG12: =INDEX('Stats import'!H:H,MATCH((INDEX(mapping!R:R,MATCH(INDEX(statsCategories,1,10),mapping!P:P,0),1)+INDEX(mapping!H:H,MATCH(C12,mapping!A:A,0),1)),'Stats import'!B:B,0),1) -> 21.2 | DH12: =INDEX('Stats import'!H:H,MATCH((INDEX(mapping!R:R,MATCH(INDEX(statsCategories,1,11),mapping!P:P,0),1)+INDEX(mapping!H:H,MATCH(C12,mapping!A:A,0),1)),'Stats import'!B:B,0),1) -> 76.3 | DI12: =INDEX('Stats import'!H:H,MATCH((INDEX(mapping!R:R,MATCH(INDEX(statsCategories,1,12),mapping!P:P,0),1)+INDEX(mapping!H:H,MATCH(C12,mapping!A:A,0),1)),'Stats import'!B:B,0),1) -> 16.2 | DJ12: =INDEX('Stats import'!H:H,MATCH((INDEX(mapping!R:R,MATCH(INDEX(statsCategories,1,13),mapping!P:P,0),1)+INDEX(mapping!H:H,MATCH(C12,mapping!A:A,0),1)),'Stats import'!B:B,0),1) -> 11.6 | DK12: =INDEX('Stats import'!H:H,MATCH((INDEX(mapping!R:R,MATCH(INDEX(statsCategories,1,14),mapping!P:P,0),1)+INDEX(mapping!H:H,MATCH(C12,mapping!A:A,0),1)),'Stats import'!B:B,0),1) -> 27.13 | DL12: =INDEX('Stats import'!H:H,MATCH((INDEX(mapping!R:R,MATCH(INDEX(statsCategories,1,15),mapping!P:P,0),1)+INDEX(mapping!H:H,MATCH(C12,mapping!A:A,0),1)),'Stats import'!B:B,0),1) -> 12.72 | DM12: =INDEX('Stats import'!H:H,MATCH((INDEX(mapping!R:R,MATCH(INDEX(statsCategories,1,16),mapping!P:P,0),1)+INDEX(mapping!H:H,MATCH(C12,mapping!A:A,0),1)),'Stats import'!B:B,0),1) -> 39.84 | DN12: =INDEX('Stats import'!H:H,MATCH((INDEX(mapping!R:R,MATCH(INDEX(statsCategories,1,17),mapping!P:P,0),1)+INDEX(mapping!H:H,MATCH(C12,mapping!A:A,0),1)),'Stats import'!B:B,0),1) -> 68.4 | DO12: =INDEX('Stats import'!H:H,MATCH((INDEX(mapping!R:R,MATCH(INDEX(statsCategories,1,18),mapping!P:P,0),1)+INDEX(mapping!H:H,MATCH(C12,mapping!A:A,0),1)),'Stats import'!B:B,0),1) -> 10.5 | DP12: =INDEX('Stats import'!H:H,MATCH((INDEX(mapping!R:R,MATCH(INDEX(statsCategories,1,19),mapping!P:P,0),1)+INDEX(mapping!H:H,MATCH(C12,mapping!A:A,0),1)),'Stats import'!B:B,0),1) -> 78.9 | DQ12: =INDEX('Stats import'!H:H,MATCH((INDEX(mapping!R:R,MATCH(INDEX(statsCategories,1,20),mapping!P:P,0),1)+INDEX(mapping!H:H,MATCH(C12,mapping!A:A,0),1)),'Stats import'!B:B,0),1) -> 5.1 | DR12: =INDEX('Stats import'!H:H,MATCH((INDEX(mapping!R:R,MATCH(INDEX(statsCategories,1,21),mapping!P:P,0),1)+INDEX(mapping!H:H,MATCH(C12,mapping!A:A,0),1)),'Stats import'!B:B,0),1) -> 21.3 | DS12: =INDEX('Stats import'!H:H,MATCH((INDEX(mapping!R:R,MATCH(INDEX(statsCategories,1,22),mapping!P:P,0),1)+INDEX(mapping!H:H,MATCH(C12,mapping!A:A,0),1)),'Stats import'!B:B,0),1) -> 35.9 | DT12: =INDEX('Stats import'!H:H,MATCH((INDEX(mapping!R:R,MATCH(INDEX(statsCategories,1,23),mapping!P:P,0),1)+INDEX(mapping!H:H,MATCH(C12,mapping!A:A,0),1)),'Stats import'!B:B,0),1) -> 32.9 | DU12: =INDEX('Stats import'!H:H,MATCH((INDEX(mapping!R:R,MATCH(INDEX(statsCategories,1,24),mapping!P:P,0),1)+INDEX(mapping!H:H,MATCH(C12,mapping!A:A,0),1)),'Stats import'!B:B,0),1) -> 7.7 | DV12: =INDEX('Stats import'!H:H,MATCH((INDEX(mapping!R:R,MATCH(INDEX(statsCategories,1,25),mapping!P:P,0),1)+INDEX(mapping!H:H,MATCH(C12,mapping!A:A,0),1)),'Stats import'!B:B,0),1) -> -1.6 | DW12: =INDEX('Stats import'!H:H,MATCH((INDEX(mapping!R:R,MATCH(INDEX(statsCategories,1,26),mapping!P:P,0),1)+INDEX(mapping!H:H,MATCH(C12,mapping!A:A,0),1)),'Stats import'!B:B,0),1) -> 9.94 | DX12: =INDEX('Stats import'!H:H,MATCH((INDEX(mapping!R:R,MATCH(INDEX(statsCategories,1,27),mapping!P:P,0),1)+INDEX(mapping!H:H,MATCH(C12,mapping!A:A,0),1)),'Stats import'!B:B,0),1) -> 11.5 | DZ12: =R12 -> -5.1242308 | EA12: =-O12 -> -18.4 | EB12: =INDEX('KenPom import'!J:J,MATCH(INDEX(kpVal,MATCH(C12,valCol,0)),kpTeam,0)) -> 65.9 | EC12: =(CX12-INDEX(FK:FK,4,1))/INDEX(FK:FK,3,1) -> 0.68827365 | ED12: =(CY12-INDEX(FL:FL,4,1))/INDEX(FL:FL,3,1) -> 1.6499438 | EE12: =(CZ12-INDEX(FM:FM,4,1))/INDEX(FM:FM,3,1) -> -0.055795626 | EF12: =(DA12-INDEX(FN:FN,4,1))/INDEX(FN:FN,3,1) -> 0.35523985 | EG12: =(DB12-INDEX(FO:FO,4,1))/INDEX(FO:FO,3,1) -> -0.19726719 | EH12: =(DC12-INDEX(FP:FP,4,1))/INDEX(FP:FP,3,1) -> 1.4789612 | EI12: =(DD12-INDEX(FQ:FQ,4,1))/INDEX(FQ:FQ,3,1) -> 0.086973688 | EJ12: =(DE12-INDEX(FR:FR,4,1))/INDEX(FR:FR,3,1)*-1 -> 0.77884161 | EK12: =(DF12-INDEX(FS:FS,4,1))/INDEX(FS:FS,3,1)*-1 -> 0.52173534 | EL12: =(DG12-INDEX(FT:FT,4,1))/INDEX(FT:FT,3,1) -> -0.077394238 | EM12: =(DH12-INDEX(FU:FU,4,1))/INDEX(FU:FU,3,1) -> 0.87485145 | EN12: =(DI12-INDEX(FV:FV,4,1))/INDEX(FV:FV,3,1) -> 0.18960313 | EO12: =(DJ12-INDEX(FW:FW,4,1))/INDEX(FW:FW,3,1) -> 2.1900567 | EP12: =(DK12-INDEX(FX:FX,4,1))/INDEX(FX:FX,3,1) -> 0.90555701 | EQ12: =(DL12-INDEX(FY:FY,4,1))/INDEX(FY:FY,3,1) -> 0.74405073 | ER12: =(DM12-INDEX(FZ:FZ,4,1))/INDEX(FZ:FZ,3,1) -> 1.0640366 | ES12: =(DN12-INDEX(GA:GA,4,1))/INDEX(GA:GA,3,1)*-1 -> 0.6718269 | ET12: =(DO12-INDEX(GB:GB,4,1))/INDEX(GB:GB,3,1) -> 0.30460704 | EU12: =(DP12-INDEX(GC:GC,4,1))/INDEX(GC:GC,3,1) -> -0.34700324 | EV12: =(DQ12-INDEX(GD:GD,4,1))/INDEX(GD:GD,3,1) -> -1.4393301 | EW12: =(DR12-INDEX(GE:GE,4,1))/INDEX(GE:GE,3,1) -> -0.73596162 | EX12: =(DS12-INDEX(GF:GF,4,1))/INDEX(GF:GF,3,1) -> 0.26302909 | EY12: =(DT12-INDEX(GG:GG,4,1))/INDEX(GG:GG,3,1)*-1 -> -0.23153534 | EZ12: =(DU12-INDEX(GH:GH,4,1))/INDEX(GH:GH,3,1) -> -0.56866512 | FA12: =(DV12-INDEX(GI:GI,4,1))/INDEX(GI:GI,3,1) -> -1.5357319 | FB12: =(DW12-INDEX(GJ:GJ,4,1))/INDEX(GJ:GJ,3,1) -> -1.265077 | FC12: =(DX12-INDEX(GK:GK,4,1))/INDEX(GK:GK,3,1)*-1 -> -0.69986558 | FD12: =(DZ12-INDEX(GM:GM,4,1))/INDEX(GM:GM,3,1)*-1 -> 1.1371821 | FE12: =(EA12-INDEX(GN:GN,4,1))/INDEX(GN:GN,3,1)*-1 -> 0.92512602 | FF12: =(EB12-INDEX(GO:GO,4,1))/INDEX(GO:GO,3,1) -> -0.72657726 | FG12: =(((DP12-DI12-3*DU12)/2)+1.5*DU12)/DB12-DR12 -> 37.188806 | FH12: =DR12/(DR12+FG12) -> 0.36417225
A13: 13 | B13: Big Ten | C13: Illinois | D13: Fighting Illini | E13: 3 | F13: OUT | H13: =_xlfn.IFNA(INDEX(importBPIRkCol,MATCH(INDEX(espnMap,MATCH(C13,valCol,0)),bpiImportCol,0)+rowOffset),INDEX(importBPIRkCol,MATCH(INDEX(espnMap2,MATCH(C13,valCol,0)),bpiImportCol,0)+rowOffset)) -> 7 | I13: =IFERROR(INDEX('Net Import'!A:A,MATCH(INDEX(mapping!B:B,MATCH(C13,mapping!A:A,0),1),'Net Import'!B:B,0),1),0) -> 8 | J13: =_xlfn.IFNA(INDEX(sorRkCol,MATCH(INDEX(espnMap,MATCH(C13,valCol,0)),sorTeamCol,0)+sorRowOffset),INDEX(sorRkCol,MATCH(INDEX(espnMap2,MATCH(C13,valCol,0)),sorTeamCol,0)+sorRowOffset)) -> 17 | K13: 9 | L13: 3 | M13: =CW13+R13*1.8+IF(K13>0,K13-26,0)/2+IF(CV13>0.5,0,10)-0.5*O13-IF(F13="WIN",1,IF(F13="IN",0.5,0))-S13+IF(W13>13.5,2,0)-IF(W13<6,6-W13,0) -> -17.066564 | N13: =IF(COUNTIF(H13:J13,"<50.5")>1.5,1,0) -> 1 | O13: =_xlfn.IFNA(INDEX(importBPICol,MATCH(INDEX(espnMap,MATCH(C13,valCol,0)),bpiImportCol,0)+rowOffset), INDEX(importBPICol,MATCH(INDEX(espnMap2,MATCH(C13,valCol,0)),bpiImportCol,0)+rowOffset)) -> 21 | P13: =INDEX(kpOff,MATCH(INDEX(kpVal,MATCH(C13,valCol,0)),kpTeam,0)) -> 1 | Q13: =INDEX(kpDef,MATCH(INDEX(kpVal,MATCH(C13,valCol,0)),kpTeam,0)) -> 26 | R13: =-1*INDEX(calculatedResVal,MATCH(C13,resValueTeamCol,0)) -> -3.4184615 | S13: 4 | T13: 4 | U13: =COUNTA(AW13:BK13)+COUNTA(Y13:AJ13) -> 9 | V13: =COUNTA(BL13:BX13)+COUNTA(AK13:AV13) -> 8 | W13: =COUNTA(AK13:AV13)+COUNTA(BL13:CS13) -> 8 | X13: =IF(SUM(S13:W13)>0,1,0) -> 1 | Y13: TTU | Z13: TENN | AA13: IOWA | AB13: PUR | AC13: NEB | AK13: ALA | AL13: CONN | AM13: NEB | AN13: MSU | AO13: MICH | AP13: WIS | AW13: OSU | AX13: MIZ | AY13: USC | AZ13: IU | BL13: WIS | BM13: UCLA | CT13: =H13*0.4+J13*1.2+I13*0.8 -> 29.6 | CU13: =CT13/2.4 -> 12.333333 | CV13: =VLOOKUP(B13,'SODiv Index'!A:B,2,FALSE) -> 1 | CW13: =CU13*(10-CV13/5)/10 -> 12.086667 | CX13: =INDEX('Stats import'!H:H,MATCH((INDEX(mapping!R:R,MATCH(INDEX(statsCategories,1,1),mapping!P:P,0),1)+INDEX(mapping!H:H,MATCH(C13,mapping!A:A,0),1)),'Stats import'!B:B,0),1) -> 1.65 | CY13: =INDEX('Stats import'!H:H,MATCH((INDEX(mapping!R:R,MATCH(INDEX(statsCategories,1,2),mapping!P:P,0),1)+INDEX(mapping!H:H,MATCH(C13,mapping!A:A,0),1)),'Stats import'!B:B,0),1) -> 14.7 | CZ13: =INDEX('Stats import'!H:H,MATCH((INDEX(mapping!R:R,MATCH(INDEX(statsCategories,1,3),mapping!P:P,0),1)+INDEX(mapping!H:H,MATCH(C13,mapping!A:A,0),1)),'Stats import'!B:B,0),1) -> 19.75 | DA13: =INDEX('Stats import'!H:H,MATCH((INDEX(mapping!R:R,MATCH(INDEX(statsCategories,1,4),mapping!P:P,0),1)+INDEX(mapping!H:H,MATCH(C13,mapping!A:A,0),1)),'Stats import'!B:B,0),1) -> 4.6 | DB13: =INDEX('Stats import'!H:H,MATCH((INDEX(mapping!R:R,MATCH(INDEX(statsCategories,1,5),mapping!P:P,0),1)+INDEX(mapping!H:H,MATCH(C13,mapping!A:A,0),1)),'Stats import'!B:B,0),1) -> 0.551 | DC13: =INDEX('Stats import'!H:H,MATCH((INDEX(mapping!R:R,MATCH(INDEX(statsCategories,1,6),mapping!P:P,0),1)+INDEX(mapping!H:H,MATCH(C13,mapping!A:A,0),1)),'Stats import'!B:B,0),1) -> 5.88 | DD13: =INDEX('Stats import'!H:H,MATCH((INDEX(mapping!R:R,MATCH(INDEX(statsCategories,1,7),mapping!P:P,0),1)+INDEX(mapping!H:H,MATCH(C13,mapping!A:A,0),1)),'Stats import'!B:B,0),1) -> 46.3 | DE13: =INDEX('Stats import'!H:H,MATCH((INDEX(mapping!R:R,MATCH(INDEX(statsCategories,1,8),mapping!P:P,0),1)+INDEX(mapping!H:H,MATCH(C13,mapping!A:A,0),1)),'Stats import'!B:B,0),1) -> 41 | DF13: =INDEX('Stats import'!H:H,MATCH((INDEX(mapping!R:R,MATCH(INDEX(statsCategories,1,9),mapping!P:P,0),1)+INDEX(mapping!H:H,MATCH(C13,mapping!A:A,0),1)),'Stats import'!B:B,0),1) -> 13.4 | DG13: =INDEX('Stats import'!H:H,MATCH((INDEX(mapping!R:R,MATCH(INDEX(statsCategories,1,10),mapping!P:P,0),1)+INDEX(mapping!H:H,MATCH(C13,mapping!A:A,0),1)),'Stats import'!B:B,0),1) -> 20.4 | DH13: =INDEX('Stats import'!H:H,MATCH((INDEX(mapping!R:R,MATCH(INDEX(statsCategories,1,11),mapping!P:P,0),1)+INDEX(mapping!H:H,MATCH(C13,mapping!A:A,0),1)),'Stats import'!B:B,0),1) -> 78.9 | DI13: =INDEX('Stats import'!H:H,MATCH((INDEX(mapping!R:R,MATCH(INDEX(statsCategories,1,12),mapping!P:P,0),1)+INDEX(mapping!H:H,MATCH(C13,mapping!A:A,0),1)),'Stats import'!B:B,0),1) -> 16.1 | DJ13: =INDEX('Stats import'!H:H,MATCH((INDEX(mapping!R:R,MATCH(INDEX(statsCategories,1,13),mapping!P:P,0),1)+INDEX(mapping!H:H,MATCH(C13,mapping!A:A,0),1)),'Stats import'!B:B,0),1) -> 9.6 | DK13: =INDEX('Stats import'!H:H,MATCH((INDEX(mapping!R:R,MATCH(INDEX(statsCategories,1,14),mapping!P:P,0),1)+INDEX(mapping!H:H,MATCH(C13,mapping!A:A,0),1)),'Stats import'!B:B,0),1) -> 27.47 | DL13: =INDEX('Stats import'!H:H,MATCH((INDEX(mapping!R:R,MATCH(INDEX(statsCategories,1,15),mapping!P:P,0),1)+INDEX(mapping!H:H,MATCH(C13,mapping!A:A,0),1)),'Stats import'!B:B,0),1) -> 13.19 | DM13: =INDEX('Stats import'!H:H,MATCH((INDEX(mapping!R:R,MATCH(INDEX(statsCategories,1,16),mapping!P:P,0),1)+INDEX(mapping!H:H,MATCH(C13,mapping!A:A,0),1)),'Stats import'!B:B,0),1) -> 40.66 | DN13: =INDEX('Stats import'!H:H,MATCH((INDEX(mapping!R:R,MATCH(INDEX(statsCategories,1,17),mapping!P:P,0),1)+INDEX(mapping!H:H,MATCH(C13,mapping!A:A,0),1)),'Stats import'!B:B,0),1) -> 69.8 | DO13: =INDEX('Stats import'!H:H,MATCH((INDEX(mapping!R:R,MATCH(INDEX(statsCategories,1,18),mapping!P:P,0),1)+INDEX(mapping!H:H,MATCH(C13,mapping!A:A,0),1)),'Stats import'!B:B,0),1) -> 14.6 | DP13: =INDEX('Stats import'!H:H,MATCH((INDEX(mapping!R:R,MATCH(INDEX(statsCategories,1,19),mapping!P:P,0),1)+INDEX(mapping!H:H,MATCH(C13,mapping!A:A,0),1)),'Stats import'!B:B,0),1) -> 84.4 | DQ13: =INDEX('Stats import'!H:H,MATCH((INDEX(mapping!R:R,MATCH(INDEX(statsCategories,1,20),mapping!P:P,0),1)+INDEX(mapping!H:H,MATCH(C13,mapping!A:A,0),1)),'Stats import'!B:B,0),1) -> 3.8 | DR13: =INDEX('Stats import'!H:H,MATCH((INDEX(mapping!R:R,MATCH(INDEX(statsCategories,1,21),mapping!P:P,0),1)+INDEX(mapping!H:H,MATCH(C13,mapping!A:A,0),1)),'Stats import'!B:B,0),1) -> 31.4 | DS13: =INDEX('Stats import'!H:H,MATCH((INDEX(mapping!R:R,MATCH(INDEX(statsCategories,1,22),mapping!P:P,0),1)+INDEX(mapping!H:H,MATCH(C13,mapping!A:A,0),1)),'Stats import'!B:B,0),1) -> 34.7 | DT13: =INDEX('Stats import'!H:H,MATCH((INDEX(mapping!R:R,MATCH(INDEX(statsCategories,1,23),mapping!P:P,0),1)+INDEX(mapping!H:H,MATCH(C13,mapping!A:A,0),1)),'Stats import'!B:B,0),1) -> 31.4 | DU13: =INDEX('Stats import'!H:H,MATCH((INDEX(mapping!R:R,MATCH(INDEX(statsCategories,1,24),mapping!P:P,0),1)+INDEX(mapping!H:H,MATCH(C13,mapping!A:A,0),1)),'Stats import'!B:B,0),1) -> 10.9 | DV13: =INDEX('Stats import'!H:H,MATCH((INDEX(mapping!R:R,MATCH(INDEX(statsCategories,1,25),mapping!P:P,0),1)+INDEX(mapping!H:H,MATCH(C13,mapping!A:A,0),1)),'Stats import'!B:B,0),1) -> -1.1 | DW13: =INDEX('Stats import'!H:H,MATCH((INDEX(mapping!R:R,MATCH(INDEX(statsCategories,1,26),mapping!P:P,0),1)+INDEX(mapping!H:H,MATCH(C13,mapping!A:A,0),1)),'Stats import'!B:B,0),1) -> 7.81 | DX13: =INDEX('Stats import'!H:H,MATCH((INDEX(mapping!R:R,MATCH(INDEX(statsCategories,1,27),mapping!P:P,0),1)+INDEX(mapping!H:H,MATCH(C13,mapping!A:A,0),1)),'Stats import'!B:B,0),1) -> 8.9 | DZ13: =R13 -> -3.4184615 | EA13: =-O13 -> -21 | EB13: =INDEX('KenPom import'!J:J,MATCH(INDEX(kpVal,MATCH(C13,valCol,0)),kpTeam,0)) -> 65.5 | EC13: =(CX13-INDEX(FK:FK,4,1))/INDEX(FK:FK,3,1) -> 0.85678747 | ED13: =(CY13-INDEX(FL:FL,4,1))/INDEX(FL:FL,3,1) -> -0.36282873 | EE13: =(CZ13-INDEX(FM:FM,4,1))/INDEX(FM:FM,3,1) -> -0.32046458 | EF13: =(DA13-INDEX(FN:FN,4,1))/INDEX(FN:FN,3,1) -> 0.8645443 | EG13: =(DB13-INDEX(FO:FO,4,1))/INDEX(FO:FO,3,1) -> 0.41126913 | EH13: =(DC13-INDEX(FP:FP,4,1))/INDEX(FP:FP,3,1) -> -1.6371385 | EI13: =(DD13-INDEX(FQ:FQ,4,1))/INDEX(FQ:FQ,3,1) -> -0.3050204 | EJ13: =(DE13-INDEX(FR:FR,4,1))/INDEX(FR:FR,3,1)*-1 -> 0.77884161 | EK13: =(DF13-INDEX(FS:FS,4,1))/INDEX(FS:FS,3,1)*-1 -> 2.3725396 | EL13: =(DG13-INDEX(FT:FT,4,1))/INDEX(FT:FT,3,1) -> -0.35257375 | EM13: =(DH13-INDEX(FU:FU,4,1))/INDEX(FU:FU,3,1) -> 1.7247772 | EN13: =(DI13-INDEX(FV:FV,4,1))/INDEX(FV:FV,3,1) -> 0.14499063 | EO13: =(DJ13-INDEX(FW:FW,4,1))/INDEX(FW:FW,3,1) -> 1.6422001 | EP13: =(DK13-INDEX(FX:FX,4,1))/INDEX(FX:FX,3,1) -> 1.0896739 | EQ13: =(DL13-INDEX(FY:FY,4,1))/INDEX(FY:FY,3,1) -> 1.0216485 | ER13: =(DM13-INDEX(FZ:FZ,4,1))/INDEX(FZ:FZ,3,1) -> 1.3625603 | ES13: =(DN13-INDEX(GA:GA,4,1))/INDEX(GA:GA,3,1)*-1 -> 0.36903167 | ET13: =(DO13-INDEX(GB:GB,4,1))/INDEX(GB:GB,3,1) -> 1.2288541 | EU13: =(DP13-INDEX(GC:GC,4,1))/INDEX(GC:GC,3,1) -> 0.74357836 | EV13: =(DQ13-INDEX(GD:GD,4,1))/INDEX(GD:GD,3,1) -> -2.4119767 | EW13: =(DR13-INDEX(GE:GE,4,1))/INDEX(GE:GE,3,1) -> 1.7805724 | EX13: =(DS13-INDEX(GF:GF,4,1))/INDEX(GF:GF,3,1) -> -0.33818026 | EY13: =(DT13-INDEX(GG:GG,4,1))/INDEX(GG:GG,3,1)*-1 -> 0.63132928 | EZ13: =(DU13-INDEX(GH:GH,4,1))/INDEX(GH:GH,3,1) -> 1.4476544 | FA13: =(DV13-INDEX(GI:GI,4,1))/INDEX(GI:GI,3,1) -> -1.276646 | FB13: =(DW13-INDEX(GJ:GJ,4,1))/INDEX(GJ:GJ,3,1) -> -2.4980279 | FC13: =(DX13-INDEX(GK:GK,4,1))/INDEX(GK:GK,3,1)*-1 -> 1.7426183 | FD13: =(DZ13-INDEX(GM:GM,4,1))/INDEX(GM:GM,3,1)*-1 -> 0.96106111 | FE13: =(EA13-INDEX(GN:GN,4,1))/INDEX(GN:GN,3,1)*-1 -> 1.2593734 | FF13: =(EB13-INDEX(GO:GO,4,1))/INDEX(GO:GO,3,1) -> -0.89241514 | FG13: =(((DP13-DI13-3*DU13)/2)+1.5*DU13)/DB13-DR13 -> 30.578221 | FH13: =DR13/(DR13+FG13) -> 0.50662958
